Workbook
Name Structure_Map: Overview!$D$80
Name Tab1_Map: Overview!$D$238
Name Tab2_Map: Overview!$D$265
Name Tab3_Map: Overview!$D$295
Name Tab4_Map: Overview!$D$326
Name Tab5_Map: Overview!$D$357
Name Tab6_Map: Overview!$D$386

Sheet Overview
A86: View detailed regulatory mapping for Tab 1 >
A93: View detailed regulatory mapping for Tab 2 >
A99: View detailed regulatory mapping for Tab 3 >
A104: View detailed regulatory mapping for Tab 4 >
A110: View detailed regulatory mapping for Tab 5 >
A116: View detailed regulatory mapping for Tab 6 >
A231: Return to: 3. Structure of the Workbook ^
E237: Area | F237: Specific FCA Provisions (examples) | G237: Key FCA Expectations | H237: How Tab 1 helps evidence this
E238: Consumer Duty – products & services; price & value; communications | F238: PRIN 2A – The Consumer Duty: PRIN 2A.3 Products and services outcome (design, target market, distribution). (FCA Handbook) PRIN 2A.4 Price and value outcome (reasonable relationship between price and benefits). (FCA Handbook) PRIN 2.1.1R (Principle 7) – information that is clear, fair and not misleading. (FCA) | G238: - Products must be fit for purpose and designed to meet the needs, characteristics and objectives of an identified target market. - Firms must ensure a reasonable relationship between price and value – no obvious structural unfairness or extraction. - Customers should be able to understand key features and limitations from the firm’s communications. (FCA Handbook) | H238: - Sections A & E assess token purpose, utility and economic design (allocations, vesting, emissions, incentives), helping show the token is not inherently misaligned with customer needs or structurally unfair on value. - Sections C & D assess token holder rights and the quality/completeness of disclosures (e.g. whitepaper), supporting evidence that material features, risks and limitations are not obscured and can be explained clearly to retail. - Overall, Tab 1 provides a documented basis that the token is coherent, explainable and not obviously exploitative, which you can cross-reference in Consumer Duty product & value assessments.
E239: Product governance – design, approval and understanding of instruments (PROD) | F239: PROD 3.2 – Product governance for manufacturers: e.g. PROD 3.2.1R / 3.2.3R – maintain, operate and review a product approval process for each product and significant adaptation. (FCA Handbook) PROD 3.3 – Product governance for distributors: PROD 3.3.1R and related rules – distributors must understand the financial instruments they distribute and assess compatibility with clients’ needs. (FCA Handbook) FCA MiFID II product governance review / good-practice commentary (e.g. 2021 multi-firm review). (FCA) | G239: - Manufacturers: operate a formal product approval process considering target market, risk/return profile and distribution strategy. - Distributors: understand product features, risks and costs and only distribute where compatible with the needs and objectives of the target market. - Maintain an evidence trail showing that products have been assessed and reviewed over time (not just one-off sign-off). (FCA Handbook) | H239: - Tab 1 functions as the front-end product approval template for tokens, capturing their purpose, governance, rights and economic model in a consistent way. - The questions force a structured articulation of how the token works, how value flows, who controls key decisions, and what holders actually get – satisfying the PROD expectation that distributors “understand the instruments” they sell. - Re-running Tab 1 when governance, tokenomics or rights change provides a repeatable review process you can point to in product governance/POG frameworks and product approval committee minutes.
E240: Governance & SMCR – SYSC systems and controls, risk identification and oversight | F240: SYSC 4.1.1R – General requirements: firms must have robust governance arrangements, including clear structures and effective processes to identify, manage, monitor and report the risks they are or might be exposed to. (FCA Handbook) SYSC 3.1 – Systems and controls: firms must take reasonable care to establish and maintain effective systems and controls for compliance with regulatory requirements and risk management. (Square Mile Research) SM&CR guidance emphasising Senior Managers’ responsibility for effective oversight of products and associated risks. (BDO) | G240: - Have formal processes and controls to identify and monitor product-level risks, not just business-line or balance-sheet risks. - Ensure Senior Managers can demonstrate they understand and have challenged significant new products and that decisions are evidenced. - Embed product and conduct risks into the firm’s overall risk management and governance framework. | H240: - Tab 1 gives a structured risk identification mechanism for token fundamentals and governance: numerical scores, risk bands, and a “weakest link” indicator for the domain. - The section-level summaries and narratives provide a concise briefing pack for Senior Managers and committees, making it easier to show that listing decisions were considered and challenged (rather than rubber-stamped). - As part of the wider engine, Tab 1 supports the argument that you have robust governance arrangements and systems and controls to identify and manage product-specific risks, in line with SYSC 4.1.1R and SYSC 3.1.
E241: FCA focus on product governance and value (cross-cutting guidance) | F241: FCA product governance / value publications and reviews, e.g.: - MiFID II product governance multi-firm review (2021). (FCA) - Consumer Duty and its impact on product governance and target market work (various guidance / good-practice papers). (DWF) | G241: - Firms should be able to demonstrate how they have assessed value, target market and product design, especially for complex / higher-risk products. - Supervisors expect documented frameworks rather than informal judgements, particularly for novel or high-risk asset classes like cryptoassets. | H241: - Tab 1 is a key part of your evidential framework for crypto tokens, showing that you have gone beyond surface-level marketing claims to interrogate fundamentals, governance and tokenomics. - Outputs from Tab 1 can be lifted directly into Product Approval Committee packs, listing committee papers, IA/product files and regulatory submissions to demonstrate that crypto products have been through the same, or stronger, governance as traditional products.
A258: Return to: 3. Structure of the Workbook ^
E264: Area | F264: Specific FCA Provisions (examples) | G264: Key FCA Expectations | H264: How Tab 2 helps evidence this
E265: Financial promotion regime – cryptoassets and high-risk investments | F265: FSMA 2000 s.21 – Financial promotion restriction: a person must not, in the course of business, communicate an invitation or inducement to engage in investment activity unless the promotion is issued or approved by an authorised person or an exemption applies. (Legislation.gov.uk) COBS 4 – Communicating with clients, including financial promotions: promotions must be fair, clear and not misleading and comply with detailed rules (e.g. risk warnings, prominence, appropriate balancing of benefits and risks). (FCA Handbook) PS23/6 – Financial promotion rules for cryptoassets and FG23/3: extend the financial promotion regime to qualifying cryptoassets, imposing RMMI-style requirements (risk warnings, 24-hour cooling off, appropriateness, banned incentives, etc.). (FCA) Crypto promotions rely on routes under FSMA and the FPO (e.g. newly introduced exemptions for FCA-registered crypto businesses). (FCA) | G265: - Firms must ensure that any cryptoasset promotion to UK consumers is lawfully communicated under s.21 FSMA, via an authorised person, an exemption, or another lawful route. - Promotions must meet high standards of clarity and risk disclosure (fair, clear, not misleading; prominent, prescribed warnings; appropriate framing of risks vs returns). - Cryptoassets treated as high-risk investments must comply with strengthened rules around risk warnings, incentives, cooling-off and appropriateness. (FCA) | H265: - Tab 2 captures how the token is being promoted to UK customers and under which lawful route (authorised firm promotion, s.21 approval, exemption or overseas-only marketing), giving you a structured record that the financial promotion restriction has been considered. - Questions around disclosure content, prominence of risk warnings, use of incentives, cooling-off and appropriateness allow you to benchmark the token’s promotional materials against the crypto financial promotion regime in PS23/6 / FG23-3 and the underlying COBS 4 standards. - The tab’s scoring and narrative provide an auditable explanation of why the firm believes the promotions are compliant, or why additional controls (re-wording, target-market limits, professional-only routes) are needed.
E266: Approval and ongoing oversight of financial promotions | F266: COBS 4.10 – Approving financial promotions: firms approving a promotion must take reasonable steps to ensure it complies with the rules and remains so for its lifetime. (FCA Handbook) COBS 4.11 – Record-keeping: financial promotions: firms must keep adequate records of promotions they communicate, approve or confirm compliance with. (FCA Handbook) FSMA 2023 – Financial promotion gateway (“approver permission”): new requirement for firms to obtain specific permission to approve promotions for unauthorised persons. (FCA) FCA cryptoasset financial promotions guidance emphasises the need for firms approving promotions to understand the token and associated risks. (Burges Salmon) | G266: - Firms that approve promotions must have appropriate expertise and due diligence processes to satisfy themselves the promotion is compliant on approval and remains compliant over time. - Firms must maintain records of approvals, underlying assessments and monitoring, enabling them to demonstrate why they considered a promotion compliant at the time. - Under the new gateway, only firms with the specific “approver permission” may approve promotions for unauthorised persons, and the FCA expects high standards of scrutiny, especially for cryptoassets. | H266: - Tab 2 provides a standardised due diligence record for each token’s regulatory/legal profile and promotional set-up. This can be cited as part of the file evidencing your s.21 approval or oversight of promotions. - Questions on regulatory route, risk classification, and disclosures demonstrate that the firm has considered the key issues the FCA expects approvers to address before signing off crypto promotions. - The tab’s outputs can be cross-referenced in your COBS 4.10/4.11 records and in your internal financial promotion approval logs, showing how each promotion was assessed in light of the token’s regulatory/legal risks.
E267: Regulatory perimeter & classification of the token / activities | F267: FSMA 2000 and the RAO – define “regulated activities” and “specified investments” (e.g. securities, units in collective investment schemes, contracts for differences, etc.). FCA perimeter guidance including PERG 2 & PERG 8 on the financial promotion regime and what constitutes “investment activity”. (sedric.ai) FCA and HM Treasury material on the future Designated Activities Regime (DAR) for cryptoassets under FSMA 2023, under which certain crypto activities will be designated and subject to activity-specific rules. (Taylor Wessing) | G267: - Firms must assess whether a token or associated activities fall inside or outside the current regulatory perimeter (e.g. security token vs unregulated cryptoasset vs e-money vs CIS / AIF structure). - Even where a token itself is unregulated, perimeter issues can arise (e.g. units in a CIS, operating a trading platform, custody, payment services). - As the DAR and other reforms are implemented, firms will be expected to understand whether their crypto offerings fall within designated activities and to comply with the associated rule-sets. | H267: - Tab 2 prompts a structured assessment of the token’s likely classification (security-like features, rights, redemption terms, profit-sharing, pooling of assets, etc.) and the associated regulated activities that may be triggered. - This gives you a documented, repeatable trail of the perimeter analysis that underpins your decision to treat a token as: - a regulated instrument (with full FSMA/COBS/PROD implications), - an unregulated cryptoasset subject to the financial promotion regime, or - part of a broader arrangement (e.g. pooled vehicles) that might itself be a regulated CIS. - As DAR and future rules come in, the same Tab 2 structure can be extended to track which designated activities are in scope and what additional legal/regulatory constraints apply.
E268: Consumer Duty & retail distribution – suitability, appropriateness and high-risk categorisation | F268: PRIN 2A – The Consumer Duty (especially: products & services, price & value, consumer understanding). (FCA Handbook) FCA high-risk investment / crypto promotion work, including the classification of qualifying cryptoassets as Restricted Mass Market Investments (RMMIs) with enhanced promotion rules. (FCA) COBS 10 & 10A – Appropriateness (for complex/high-risk investments) – assessing whether a non-advised client has the necessary experience and knowledge to understand the risks. (FCA Handbook) | G268: - Even where crypto activities themselves are not fully regulated yet, the Consumer Duty and strengthened financial promotion rules emphasise: - clear identification of target market vs restricted/professional-only distribution; - robust appropriateness tests for high-risk or complex products; - enhanced warnings and frictions (e.g. cooling-off) for RMMIs such as crypto. - Firms should be able to demonstrate why a given token is appropriate for a particular retail segment (or why retail access is restricted) in light of its risks and complexity. | H268: - Tab 2 consolidates your thinking on whether a given token: - should be treated as a high-risk investment for retail purposes, - should be accessible only to restricted / sophisticated / professional clients, or - should not be offered at all. - It links the token’s regulatory and legal profile to distribution and suitability decisions (e.g. requirement for appropriateness tests, extra risk warnings, or channel restrictions). - These outputs can be used to justify your target market definition, your use of appropriateness tests, and any distribution restrictions in internal Consumer Duty and product governance documentation.
E269: Cross-border and jurisdictional legal risk | F269: FCA Principles (e.g. Principle 1 – Integrity, Principle 2 – Due skill, care and diligence) and SYSC 6 expectations around having adequate compliance functions and controls to identify and manage legal/regulatory risks across jurisdictions. (FCA Handbook) Overseas regimes that may restrict marketing or availability of certain tokens to local investors (e.g. local securities or derivatives laws, bans, enforcement actions). | G269: - Firms are expected to avoid engaging in or facilitating activity that breaches local law in other jurisdictions, even if some aspects of the token are unregulated in the UK. - Compliance and legal teams must be able to identify where a token is subject to material overseas restrictions or enforcement, and decide whether and how to offer exposure from the UK. | H269: - Tab 2 includes questions on jurisdictional mapping, overseas regulatory actions and local restrictions affecting the token or its issuer. - This creates a central place where you record whether there are material overseas legal risks (e.g. securities enforcement, bans on retail marketing) that should influence your decision to list the token, how you structure access, or whether you apply additional warnings or exclusions for particular client segments or geographies.
A287: Return to: 3. Structure of the Workbook ^
E294: Area | F294: Specific FCA Provisions (examples) | G294: Key FCA Expectations | H294: How Tab 3 helps evidence this
E295: Core AML/CTF regime & firm-wide risk assessment | F295: Money Laundering, Terrorist Financing and Transfer of Funds (Information on the Payer) Regulations 2017 (MLRs) – e.g.: - Regulation 18 – firm-wide risk assessment of money laundering and terrorist financing risks. (Legislation.gov.uk) - Regulation 19 – policies, controls and procedures to mitigate and manage those risks. (Legislation.gov.uk) FCA Financial Crime Guide (FCG) and FG18/5 – guidance on systems and controls to counter financial crime, including market-related risks. (FCA Handbook) | G295: - Firms must identify, assess and understand their ML/TF risk profile, including new products and technologies, and maintain documented risk assessments. - Appropriate policies, controls and procedures must be implemented and kept up to date to mitigate identified risks. - New or developing technologies (such as cryptoassets) require a specific risk assessment and tailored controls under the risk-based approach. (Legislation.gov.uk) | H295: - Tab 3 provides a structured product-level ML/TF risk assessment for each token, feeding into your firm-wide Reg 18 risk assessment and product risk register. - Questions around anonymity features, obfuscation tools, typical use-cases and high-risk geographies show that you have explicitly considered ML/TF risk factors for this cryptoasset, not just for the customer base in general. - The scoring and risk banding can be referenced in your Reg 18 assessment and in the documentation of the AML risk classification for each token (e.g. “standard”, “elevated”, “intolerable”).
E296: Customer due diligence (CDD), enhanced due diligence (EDD) & high-risk factors | F296: MLRs 2017 – key CDD/EDD obligations: - Regulation 27–30 – customer due diligence and ongoing monitoring. - Regulation 33 – enhanced due diligence for higher-risk situations (including high-risk third countries, complex or unusually large transactions). (Legislation.gov.uk) - Regulation 35 – PEPs; Regulation 33–35 together set out higher-risk customer factors. (Legislation.gov.uk) JMLSG Guidance (e.g. Part I, Ch. 4 – risk-based approach) emphasises assessing ML/TF risk for new products and technologies. (jmlsg.org.uk) | G296: - Firms must perform CDD and adapt the depth of checks based on risk, applying EDD where higher risks are identified (e.g. high-risk countries, complex structures, unusual patterns). - For new products or technologies, firms must understand how those products can be used to obscure beneficial ownership, source of funds or transaction trails, and adjust CDD/EDD accordingly. - Ongoing monitoring must detect atypical patterns and trigger review or escalation. (Legislation.gov.uk) | H296: - Tab 3 analyses product-specific risk factors that drive the need for EDD: - embedded privacy features, mixers/bridges/ecosystem tools commonly used for obfuscation, - typical customer and transactional profiles, - links to typologies such as scams, darknet markets or ransomware. - By scoring these factors, Tab 3 gives concrete input to your CDD/EDD risk scoring models, helping justify when a token (or flows involving a token) should be treated as requiring EDD, additional monitoring rules, or even hard blocks in certain jurisdictions or counterparties.
E297: FCA cryptoasset AML/CTF registration and expectations | F297: FCA Cryptoassets: AML / CTF regime – cryptoasset businesses in scope must register with the FCA under the MLRs and comply with the regulations. (FCA) FCA guidance on what the FCA expects to see in an AML registration application for cryptoasset firms (understanding and implementing the MLRs, including risk assessments, CDD/EDD and monitoring). (FCA) | G297: - In-scope crypto businesses must show a comprehensive understanding of the UK AML regime and how it is applied in the context of their products and services. - Firms must have a robust financial crime framework tailored to crypto-specific risks (e.g. pseudonymous transactions, high-velocity flows, cross-border activity). - Supervisors expect firms to evidence product-specific ML/TF risk assessment rather than generic AML boilerplate. (FCA) | H297: - Tab 3 evidences that your firm has gone beyond generic AML policy and carried out a cryptoasset-specific risk assessment at the individual token level. - It helps demonstrate to the FCA (or internal audit) that the firm understands: - which tokens are higher-risk from an ML/TF perspective, - how those risks are mitigated (e.g. venue choice, monitoring scenarios, thresholds, restricted jurisdictions), and - where the firm may decide not to list or to delist a token. - This can be referenced in your FCA registration file and ongoing supervisory interactions as evidence of a structured financial crime control environment around crypto offerings.
E298: Sanctions compliance – UK sanctions framework & OFSI guidance | F298: Sanctions and Anti-Money Laundering Act 2018 – primary legislation for the UK’s autonomous sanctions regimes. (Legislation.gov.uk) UK financial sanctions general guidance from OFSI and HM Treasury (how to comply with financial sanctions, screening expectations, asset freezes, reporting). (GOV.UK) Wider guidance and commentary on the UK sanctions regime (e.g. Law Society guidance). (Law Society) | G298: - Firms must ensure they do not: - deal with sanctioned persons or entities, - make funds or economic resources available, directly or indirectly, to designated persons, or - participate in arrangements that circumvent sanctions. - Appropriate screening and controls must be in place for customers, counterparties, and (for crypto) potentially for wallets/addresses, protocols or projects that are the subject of sanctions or sectoral measures. (GOV.UK) | H298: - Tab 3 contains questions specifically focused on sanctions exposure, such as: - whether relevant token contracts, treasuries or major counterparties are linked to designated persons or sanctioned jurisdictions; - the presence of OFAC/UK-sanctioned addresses or entities in the project’s history or ecosystem; - whether the token is widely used in typologies that overlap with sanctions evasion. - By assigning a sanctions risk score and band, Tab 3 gives a transparent basis for deciding: - whether to permit any activity involving the token, - whether to limit access (e.g. no support for self-hosted wallets in particular jurisdictions), and - how to parameterise sanctions screening and alerts for flows involving that token.
E299: Financial crime systems & controls – SYSC 6 | F299: SYSC 6.1.1R – firms must establish, implement and maintain adequate policies and procedures to ensure compliance with obligations under the regulatory system, including countering the risk that the firm might be used to further financial crime. (FCA Handbook) FCA Financial Crime Guide (FCG) and related FG18/5 guidance on financial crime systems and controls, including application of SYSC 6.1.1R. (FCA Handbook) | G299: - Firms must have effective systems and controls proportionate to the nature, scale and complexity of their activities, including products and services that present higher financial crime risk (such as cryptoassets). - They should be able to demonstrate how they identify, assess and mitigate financial crime risks at the product, customer and transaction levels. - Supervisors place particular scrutiny on how new products and technologies are risk assessed and embedded into the financial crime framework. (FCA Handbook) | H299: - Tab 3 acts as a product-level financial crime risk tool within your wider SYSC 6 framework. - It documents, in a consistent and repeatable way, the key ML/TF and sanctions risk factors for each token and assigns a risk band that can feed into: - onboarding decisions (list vs do not list), - monitoring rules and thresholds (e.g. stricter surveillance for higher-risk tokens), and - periodic re-assessment cycles. - This can be pointed to in your SYSC 6 documentation and financial crime policies as the mechanism by which crypto products are brought within the firm’s risk identification, assessment and mitigation processes.
E300: International standards & typologies (FATF, JMLSG, etc.) | F300: FATF Recommendations on virtual assets (VAs) and VASPs, including risk-based approach, Travel Rule, and expectations around VA-specific ML/TF risks. (Reflected in UK implementation via MLRs and FCA guidance.) (ICAEW) JMLSG guidance on risk-based approach for new products and technologies (Part I, Ch. 4). (jmlsg.org.uk) | G300: - Regulators expect firms to have regard to international standards on cryptoasset ML/TF risk, especially FATF’s VA/VASP guidance. - Firms should understand and respond to emerging typologies (e.g. mixing, DeFi, cross-chain bridges, ransomware, darknet markets) and not treat crypto like a simple extension of fiat payments. | H300: - Tab 3 explicitly incorporates crypto-specific typologies and technology risks (e.g. mixers, privacy protocols, DeFi exploits, high-risk venues) into its scoring, aligning your analysis with emerging FATF/JMLSG expectations. - This makes it easier, in audits or supervisory visits, to show that your AML/CTF assessments for cryptoassets are aligned with current international standards and not based on outdated or purely fiat-centric assumptions.
A317: Return to: 3. Structure of the Workbook ^
E325: Area | F325: Specific FCA Provisions (examples) | G325: Key FCA Expectations | H325: How Tab 4 helps evidence this
E326: Systems and controls for technology & operational risk (SYSC) | F326: SYSC 3.1.1R – firms must take reasonable care to establish and maintain effective systems and controls for compliance with regulatory obligations and for managing risk. SYSC 4.1.1R – firms must have robust governance arrangements, including effective processes to identify, manage, monitor and report risks. SYSC 13 & 13.7 (for certain firms) – additional expectations around operational risk and business continuity. | G326: - Technology and operational arrangements (including those supporting crypto services) must be fit for purpose, controlled, and subject to appropriate risk management. - Firms must be able to identify and monitor key operational/technical risks in the products they offer, not just in their own internal IT stack. - Senior management should be able to explain how technical risk in products is understood, monitored and reflected in risk appetite and controls. | H326: - Tab 4 gives a structured assessment of protocol and smart contract security, feeding directly into the firm’s SYSC 3/4 view of operational risk associated with the token. - Questions around vulnerability management, incident history, governance controls and resilience build a documented record of the technical risks you are accepting by listing/supporting this token. - The resulting scores and risk bands can be referenced in risk appetite discussions, product approval papers and the operational risk register as evidence that crypto product technical risks are being actively assessed.
E327: Operational resilience – important business services and impact of disruption | F327: FCA Operational Resilience framework (PS21/3 and related rules in the FCA Handbook – primarily in SYSC and the Operational Resilience sourcebook for in-scope firms): firms must identify important business services, set impact tolerances and ensure they can remain within those tolerances under severe but plausible disruptions. | G327: - Firms must understand how reliance on particular technologies, infrastructures or third-party services could cause intolerable harm to customers or market integrity if they fail. - Crypto-related services (e.g. custody, trading, staking) that are “important business services” require particular attention to resilience and failure modes. - There should be a clear view of how protocol-level failures or exploits could affect the firm’s ability to deliver services within impact tolerances. | H327: - Tab 4 helps identify tokens where protocol or contract weaknesses could realistically cause service disruption (e.g. trading halts, frozen funds, permanent loss) for your clients. - Where a token underpins an important business service (e.g. major trading pair, staking product), Tab 4 scores and narratives inform your operational resilience mapping, by documenting the likelihood and impact of technical failure. - These insights can be used to support decisions such as position limits, venue selection, contingency plans and disclosure in operational resilience documentation.
E328: Outsourcing, third-party and dependency risk | F328: SYSC 8 – outsourcing: requires that where a firm outsources critical or important operational functions, it must ensure the service provider has the ability, capacity and authorisation to carry out the functions reliably and professionally, and that the firm remains responsible for compliance. FCA outsourcing / third-party risk guidance emphasises understanding dependencies and ensuring appropriate oversight and exit strategies. | G328: - Firms must identify and manage critical dependencies on third-party providers (including technology providers, infrastructure, and crucial external services such as oracles or bridges). - Outsourcing or relying on third parties does not dilute the firm’s responsibility; firms must ensure they have adequate oversight, contingency and control. | H328: - Tab 4 captures key technical dependencies for each token (e.g. reliance on a specific oracle network, bridge, centralised sequencer, governance admin key, custodian or infrastructure provider). - It allows you to flag tokens where a single failure point (e.g. centralised multisig, unaudited bridge, off-chain oracle dependency) creates an unacceptable level of dependency risk. - You can use the Tab 4 outputs to explain, in your outsourcing/third-party risk framework, why certain tokens are restricted, require additional monitoring, or are only supported on particular venues or custody arrangements.
E329: Cyber & information security expectations | F329: FCA guidance and SYSC provisions emphasising IT and cyber security as part of effective systems and controls (e.g. FCG cyber guidance, thematic reviews on cyber and technology resilience). PRA/FCA material on cyber risk (e.g. cyber resilience statements, Dear CEO letters) often stresses the need for robust protection against cyber attacks and fraud. | G329: - Firms must take steps to ensure that IT environments and interfaces with external systems (including crypto protocols, APIs, nodes, wallets) are secure. - Where a product relies on external protocols and smart contracts, firms should understand key vulnerability vectors (e.g. admin key compromise, oracle manipulation, re-entrancy exploits) and reflect them in risk management. | H329: - Tab 4 surfaces whether a token’s protocol and contracts have a history of exploits or critical vulnerabilities, whether security best practices (e.g. audited, open-source, peer-reviewed code) are in place, and how quickly issues have been remediated in the past. - This allows your IT/cyber risk function and product owners to see where technical risk is particularly acute and where additional controls (e.g. limited functionality, enhanced monitoring, no leverage or derivatives on that token) may be required. - It also creates a record that cyber/technical risk has been considered at product level, not just at infrastructure level.
E330: Market integrity and conduct – impact of technical design on fairness and manipulation | F330: Principles for Businesses – particularly: - Principle 1 (Integrity) – conducting business with integrity. - Principle 2 (Skill, care and diligence) – managing products and risks competently. FCA market abuse / market integrity expectations (while the formal UK MAR regime may not apply directly to unregulated cryptoassets, the FCA expects firms to manage market integrity and abuse risks in line with their authorisations and permissions). | G330: - Firms are expected not to facilitate markets or products that are structurally prone to abuse or unfair outcomes, particularly where technical design encourages manipulation or unfair advantage. - Even where a specific regime (like MAR) is not fully applicable, firms must consider conduct and integrity risks arising from product structures and protocols (e.g. privileged insiders, upgrade powers, oracle design). | H330: - Tab 4 includes questions on upgrade and control mechanisms, oracle design, admin keys and governance rights, which affect the potential for technical manipulation (e.g. changing rules mid-game, pausing contracts, shutting out users). - By scoring these factors, you can distinguish between tokens with robust, decentralised, transparent technical control structures and those where a small group can materially change or halt the protocol, raising integrity concerns. - This supports conduct and market integrity obligations by demonstrating that technical features that could facilitate unfair practices have been explicitly considered before listing.
E331: Consumer Duty – reliability and foreseeable harm from technical failure | F331: PRIN 2A – Consumer Duty, especially: - Products and services outcome (PRIN 2A.3) – products should function as anticipated and deliver outcomes in line with customers’ needs. - Consumer support / foreseeable harm concepts – firms should avoid causing foreseeable harm through poor product design or unreliable services. | G331: - Firms should not offer products where foreseeable and material technical failures are likely to cause harm (e.g. repeated contract exploits, unsafe bridges, known critical vulnerabilities). - Where technical risk is material, it should be reflected in product design, disclosures, restrictions, and ongoing oversight. | H331: - Tab 4 gives an explicit, quantitative view of foreseeable technical harms: probability and impact of exploit, contract failure, or protocol malfunction. - This supports Consumer Duty by allowing you to show that you identified foreseeable technical harms, assessed their severity, and either: - mitigated them (through controls, disclosures, product design), or - decided not to offer or to withdraw exposure to certain tokens. - The Tab 4 narrative can be incorporated into Duty-focused product reviews and outcome assessments.
A349: Return to: 3. Structure of the Workbook ^
E356: Area | F356: Specific FCA Provisions (examples) | G356: Key FCA Expectations | H356: How Tab 5 helps evidence this
E357: Market integrity & market abuse (even where MAR doesn’t strictly apply) | F357: FCA Market Abuse Regulation (MAR) material – MAR aims to increase market integrity and investor protection by tackling insider dealing, unlawful disclosure and market manipulation.(FCA) FCA market abuse pages stress firms’ responsibility for safeguards against abusive behaviours.(FCA) FCA DP24/4 – Regulating cryptoassets: Admissions & Disclosures and Market Abuse Regime for Cryptoassets (MARC) – developing a crypto-specific market abuse regime that mirrors MAR-style outcomes.(FCA) | G357: - Firms should not facilitate trading environments that are systemically prone to abuse (e.g. persistent manipulation, wash trading, insider dealing), even where MAR technically applies only to certain instruments/venues. - Cryptoasset markets are increasingly expected to align with market integrity standards similar to those under MAR, especially as a dedicated MARC framework is developed. - Firms should have arrangements and surveillance to identify unusual or abusive patterns and respond appropriately.(FCA) | H357: - Tab 5 specifically looks for indicators of wash trading, spoofing-style activity, extreme concentration of volume or holdings, and structurally weak venues, giving a transparent assessment of the market integrity for each token. - High scores in the “manipulation/abuse” questions provide a clear signal that the token’s trading environment may be inconsistent with the FCA’s expectations on orderly and abuse-resistant markets, even if the token/venue is formally outside MAR. - These outputs support your argument that you either: - apply enhanced surveillance and restrictions for certain tokens; or - decline to list them where market integrity is too weak.
E358: Best execution, order handling and fair pricing / liquidity | F358: COBS 11 – Dealing and managing: - COBS 11.2A (Best execution – MiFID provisions) – firms must take all reasonable steps to obtain the best possible result for clients, considering price, costs, speed, likelihood of execution/settlement and other relevant factors.(beta-handbook.fca.org.uk) - COBS 11.3 – client order handling rules (fair, prompt, expeditious execution; avoiding adverse impact on clients). | G358: - Where best execution obligations apply, firms must be able to demonstrate that they considered liquidity, spreads, depth and execution likelihood across different venues when designing execution arrangements. - Even outside strict MiFID best execution scope, firms promoting trading in certain assets are expected to consider whether the trading environment produces fair pricing and reasonable execution outcomes. | H358: - Tab 5’s focus on liquidity depth, spreads, slippage and venue quality gives a structured view of whether it is realistically possible to achieve “good” execution outcomes in the token under plausible trade sizes. - The scores highlight tokens where liquidity is so thin or fragmented that material slippage or failed execution is likely, which can be factored into: - your best execution policy, - internal lists of tokens permitted for execution, and - position size / ticket size guidance. - This helps demonstrate that you have considered liquidity and execution factors in line with COBS 11.2A/11.3, even where the token trades on venues technically outside MiFID scope.
E359: Consumer Duty – price & value, foreseeable harm from illiquidity and volatile trading conditions | F359: PRIN 2A – Consumer Duty: - PRIN 2A.3 Products and services outcome – products should work as reasonably expected and be designed for a defined target market. - PRIN 2A.4 Price and value outcome – there should be a reasonable relationship between price and benefits; poor value can arise where trading conditions impose excessive friction.(FCA) FCA commentary on high-risk investments and crypto promotions emphasises the need to consider liquidity, volatility and exit risk when assessing suitability for retail investors.(FCA) | G359: - Firms should not put customers into products where foreseeable trading conditions (e.g. chronic illiquidity, extreme slippage, inability to exit) are likely to cause foreseeable harm or poor value. - Liquidity, volatility and depth should be factored into decisions about whether a cryptoasset is appropriate for retail, restricted to certain client types, or not offered at all. | H359: - Tab 5 quantifies liquidity and exit risk (spreads, depth, ability to execute in typical trade sizes) and flags tokens where customers may struggle to exit positions at a fair price. - It also considers volatility / market quality elements that can make realisable value materially different from notional value (e.g. manipulated pumps, thin order books). - These insights support your Consumer Duty work by linking the economic experience clients actually get in the market to your product and value assessments – and can justify limiting or prohibiting retail access where market conditions are consistently poor.
E360: Financial promotions for high-risk investments / cryptoassets – clarity about trading conditions | F360: PS23/6 – Financial promotion rules for cryptoassets and associated guidance: qualifying cryptoassets are treated as Restricted Mass Market Investments (RMMIs) with strengthened promotion rules (risk warnings, appropriateness, cooling-off, banned incentives).(FCA) FCA good and poor practice review on back-end cryptoasset financial promotions (2024) emphasises that firms must ensure ongoing promotions remain fair, clear and not misleading, including around liquidity and trading risks.(FCA) Under COBS 4, financial promotions (including crypto) must be fair, clear and not misleading, and must not disguise, diminish or obscure important information.(FCA) | G360: - Promotions for cryptoassets must give a balanced and accurate picture of the risks, including those arising from illiquidity, volatility, potential for slippage, and venue quality. - Firms must ensure that what is said about tradability, liquidity and “ease of exit” is true in practice and not undermined by actual market conditions. - Where liquidity or market quality changes over time, firms should review whether promotions remain accurate and compliant. | H360: - Tab 5 helps you check whether claims about a token being “liquid”, “widely traded” or “easy to exit” are actually supported by data (depth, spreads, number/quality of venues). - Where Tab 5 scores indicate weak or deteriorating liquidity, you can: - review and adjust cryptoasset promotions, - add or strengthen risk warnings about liquidity/exit risk, or - restrict marketing to certain client types. - This provides a clear evidential link between observed market conditions and how you draft and maintain crypto financial promotions under PS23/6 and COBS 4.
E361: Financial crime through markets – wash trading, layering and manipulation via illiquid markets | F361: FCA analysis on Money Laundering Through the Markets (MLTM) highlights how capital markets can be used to move criminally generated funds and that thin or opaque markets are particularly vulnerable to manipulation and layering.(FCA) FCA speeches and strategy documents on fighting financial crime and market abuse stress surveillance and controls in markets with higher inherent manipulation risk.(FCA) | G361: - Firms should recognise that illiquid or lightly regulated trading venues can be used to facilitate both market abuse and broader financial crime (e.g. wash trading to create artificial volume, layering to move value). - They are expected to design surveillance and product governance frameworks that account for these vulnerabilities, especially where they list or support trading in such instruments. | H361: - Tab 5 explicitly looks at volume quality, patterns of trading and concentration, making it easier to identify tokens where wash trading or artificial volume is likely. - High-risk findings in Tab 5 can be directly linked into: - enhanced surveillance scenarios, - controls around which venues you will route orders to, and - decisions to avoid listing or to delist tokens with persistent integrity red flags. - This shows that your firm is connecting market integrity and financial crime risks into product and venue selection, not just client-level AML controls.
A378: Return to: 3. Structure of the Workbook ^
E385: Area | F385: Specific FCA Provisions (examples) | G385: Key FCA Expectations | H385: How Tab 6 helps evidence this
E386: Consumer Duty – culture, foreseeable harm and trust | F386: PRIN 2A – Consumer Duty: requires firms to act to deliver good outcomes for retail customers, including products & services, price & value, consumer understanding and support.(FCA Handbook) The Duty and related guidance emphasise firm culture, governance and monitoring of outcomes, not just technical rule compliance.(Simmons & Simmons) | G386: - Firms should not engage in or promote products where foreseeable harm is likely – including harm to trust and confidence – because of the way a project behaves, communicates or treats users. - Culture and conduct around products (e.g. repeated controversies, misleading claims, aggressive hype) are relevant to assessing overall outcomes. - Boards and senior managers must consider whether a product fits with the firm’s values and customer proposition, not just whether it’s technically allowed. | H386: - Tab 6 surfaces strategic and reputational red flags: past scandals, enforcement actions, fraud allegations, customer harm episodes, or patterns of behaviour by founders/teams that make foreseeable harm more likely. - It allows you to document when a token is in tension with your stated customer outcomes and values, even if it can be structured to be technically compliant. - The resulting scores and narratives support Consumer Duty governance by showing you have considered wider trust and cultural aspects in deciding whether to list / maintain / restrict a token.
E387: Anti-greenwashing & ESG/sustainability claims | F387: FCA’s Sustainability Disclosure Requirements (SDR) and investment labels regime (PS23/16) introduces an anti-greenwashing rule that applies to all FCA-authorised firms making sustainability-related claims.(FCA) The anti-greenwashing rule requires that any sustainability-related claims be fair, clear and not misleading and consistent with the product’s actual sustainability characteristics.(FCA) FCA guiding principles on ESG/sustainable investment funds (Dear Chair letter and follow-up reviews) set expectations that ESG claims are specific, evidence-based and reflected in holdings.(FCA) | G387: - Any claims your firm makes about ESG, sustainability, impact or responsibility – including in crypto-related products and marketing – must be accurate, substantiated and not exaggerated. - Firms must avoid greenwashing or “ESG-washing”, including by associating with projects whose actual practices conflict with the sustainability story presented to clients. - If a firm positions itself as ESG-aware or uses sustainability language, its product set should be broadly coherent with that positioning. | H387: - Tab 6 assesses whether the token’s environmental, social and governance reality is broadly aligned with any ESG or “responsible investing” narrative you use, or that the issuer uses and you might amplify. - High ESG-risk scores (e.g. significant environmental concerns, governance controversies, social harms) help you identify tokens where including them in “responsible” or ESG-themed offerings could breach anti-greenwashing expectations. - The tab’s outputs can be referenced when documenting how you have ensured ESG-related claims about your crypto offerings are consistent with underlying assets, in line with the anti-greenwashing rule and SDR expectations.
E388: ESG / sustainability disclosure expectations for investment products | F388: FCA PS23/16 – SDR and investment labels: sets rules for UK asset managers on sustainability labels, product & entity-level ESG disclosures, and naming & marketing of sustainable products.(FCA) FCA’s earlier guiding principles for ESG/sustainable funds highlight design, delivery and disclosure expectations – clear ESG objectives, coherent strategies and holdings that match stated aims.(FCA) | G388: - Where firms offer sustainable or ESG-labelled products, regulators expect a clear link between: - the stated ESG objectives of the product, and - the actual assets held or referenced (including tokens). - ESG claims should be internally consistent across products, disclosures and marketing; holdings should not materially contradict the stated ESG characteristics. | H388: - Tab 6 helps you determine whether including a particular token in ESG-labelled or sustainability-themed portfolios would be credible, or whether it would undermine those claims. - For tokens scoring poorly on ESG dimensions (e.g. environmentally intensive, governance controversies, social harms), Tab 6 provides a documented rationale for: - excluding them from ESG products, - restricting them to non-ESG ranges, or - applying additional disclosure if exposures are unavoidable. - This supports your ability to evidence that ESG-themed offerings match their stated ESG profile, as expected under SDR and related guidance.
E389: Governance, SMCR and reputational risk management | F389: PRIN 2.1 – Principles for Businesses include: - Principle 1 – Integrity, - Principle 2 – Skill, care and diligence, - Principle 3 – Management and control (adequate risk management systems), and - Principle 6 – Customers’ interests.(FCA Handbook) SYSC 4.1.1R – firms must have robust governance arrangements including effective processes to identify, manage, monitor and report the risks they are exposed to.(FCA Handbook) FCA commentary on reputational risk highlights the need for firms to use that concept carefully and consistently, not as a vague catch-all, and to link it to concrete risk factors and decisions.(FCA) | G389: - Firms are expected to manage reputational risk in a structured way linked to real underlying issues (e.g. customer harm, misconduct, ESG controversies), not as an arbitrary veto. - Senior Managers must be able to explain and justify why certain products or relationships are acceptable or not in terms of the firm’s integrity, culture and risk appetite. - Governance frameworks should show how issues such as misconduct history, enforcement actions, social harm, or controversial industries are factored into product decisions. | H389: - Tab 6 gives you a systematic framework for assessing reputational risk at the token/project level: - prior enforcement or regulatory actions; - serious fraud or misconduct allegations; - ongoing controversies or social harms; - alignment with or divergence from your firm’s stated values and strategy. - The resulting reputational/strategic risk scores and bands can be explicitly referenced in product approval, review and exit decisions, demonstrating that reputational risk has been considered in a structured, evidence-based way rather than as an ad hoc label. - This supports PRIN 1–3 and SYSC expectations around integrity, skill and control in managing your product set.
E390: Culture, conduct and wider societal impact / ESG expectations | F390: FCA speeches, Dear CEO letters and thematic work on culture and conduct emphasise that firms must embed cultures that prioritise good customer outcomes and integrity, not short-term gains. FCA sustainable finance/ESG work (e.g. SDR, guiding principles, consultations on ESG ratings) reflects broader regulatory expectations that firms take ESG factors and societal impact seriously where relevant to their activities.(FCA) | G390: - The FCA increasingly expects firms to think about how their products affect customers and markets in the round, including societal and environmental dimensions where relevant. - Culture is judged not just by internal policies, but by which clients, sectors and products firms choose to support, and how they behave when issues arise. | H390: - Tab 6 allows you to capture whether association with a given token is consistent with the culture and societal stance your firm is trying to maintain (e.g. around environmental impact, human rights, exploitation, governance standards). - By documenting where there is a serious misalignment (e.g. repeated association with scams, exploitative schemes, or environmentally extreme practices), Tab 6 helps you justify: - declining to list or withdrawing support; - limiting distribution channels; or - applying enhanced disclosures and governance around that token. - This makes it easier to show, in culture and ESG discussions with regulators, that product choices are aligned with the firm’s stated values and ESG strategy, not just short-term commercial opportunities.

Sheet Token Fundamentals & Governance
A1: Question_ID | B1: Question_Text | C1: Raw_Response | D1: Confidence | E1: Raw_Points | F1: Reliability_Modifier | G1: Reliability_Adjusted_Points | H1: Source_Citations | I1: Source_Dates | J1: Accessed_Dates | K1: Most_Recent_Source_Date | L1: Days_Since_Source | M1: Staleness_Class | N1: Staleness_Penalty | O1: Final_Score | P1: Board_Escalation_Flag | Q1: Trigger_Rule_Description | R1: Narrative_Justification | S1: Debug Notes
B2: A. Purpose & Utility
A4: A1.1 | B4: Primary token category (Primary & Secondary). Answer using exactly this format: "Primary: <one of: Native L1, Gas/Fee, Governance, Utility, LP/AMM, Stablecoin, Asset-Backed, Meme/Narrative, Other>; Secondary: <one of the same list>". Do not add explanations or extra words. | C4: Primary: Native L1; Secondary: Gas/Fee | D4: High | E4: =IF(ISNUMBER(SEARCH("Primary: Meme",C4)),22,IF(ISNUMBER(SEARCH("Primary: Asset",C4)),18,IF(ISNUMBER(SEARCH("Primary: Liquidity",C4)),15,IF(ISNUMBER(SEARCH("Primary: Governance",C4)),12,IF(ISNUMBER(SEARCH("Primary: Utility",C4)),7,IF(ISNUMBER(SEARCH("Primary: Gas",C4)),5,IF(ISNUMBER(SEARCH("Primary: Native",C4)),0,IF(ISNUMBER(SEARCH("Primary: Stablecoin",C4)),5,IF(ISNUMBER(SEARCH("Primary: LP/AMM",C4)),15,IF(C4="","",10)))))))))) -> 0 | F4: =IF(D4="High",0,IF(D4="Medium",0.05,IF(D4="Low",0.1,IF(D4="Unknown",0.15,"")))) -> 0 | G4: =E4*(1+F4) -> 0 | H4: https://docs.avax.network/learn/avalanche/avax; https://docs.avax.network/build/subnet/elastic-subnets/avalanche-c-chain | I4: 2023-06-01; 2023-05-01 | J4: 2025-12-12; 2025-12-12 | K4: =IF(I4="","",MAX(IFERROR(DATEVALUE(TRIM(MID(SUBSTITUTE(I4,";",REPT(" ",50)),1,50))),0),IFERROR(DATEVALUE(TRIM(MID(SUBSTITUTE(I4,";",REPT(" ",50)),51,50))),0),IFERROR(DATEVALUE(TRIM(MID(SUBSTITUTE(I4,";",REPT(" ",50)),101,50))),0),IFERROR(DATEVALUE(TRIM(MID(SUBSTITUTE(I4,";",REPT(" ",50)),151,50))),0),IFERROR(DATEVALUE(TRIM(MID(SUBSTITUTE(I4,";",REPT(" ",50)),201,50))),0),IFERROR(DATEVALUE(TRIM(MID(SUBSTITUTE(I4,";",REPT(" ",50)),251,50))),0),IFERROR(DATEVALUE(TRIM(MID(SUBSTITUTE(I4,";",REPT(" ",50)),301,50))),0),IFERROR(DATEVALUE(TRIM(MID(SUBSTITUTE(I4,";",REPT(" ",50)),351,50))),0),IFERROR(DATEVALUE(TRIM(MID(SUBSTITUTE(I4,";",REPT(" ",50)),401,50))),0),IFERROR(DATEVALUE(TRIM(MID(SUBSTITUTE(I4,";",REPT(" ",50)),451,50))),0))) -> 45078 | L4: =IF(K4="","",TODAY()-K4) -> 926 | M4: Evergreen–No Penalty | N4: =IF(M4="","",IF(L4="",INDEX($F$92:$F$95,MATCH(M4,$C$92:$C$95,0)),IF(L4<=INDEX($D$92:$D$95,MATCH(M4,$C$92:$C$95,0)),0,IF(L4<=INDEX($E$92:$E$95,MATCH(M4,$C$92:$C$95,0)),INDEX($F$92:$F$95,MATCH(M4,$C$92:$C$95,0)),INDEX($G$92:$G$95,MATCH(M4,$C$92:$C$95,0)))))) -> 0 | O4: =G4+N4 -> 0 | P4: No Review | Q4: Helper row; scored via primary role only. | R4: AVAX is the native token of the Avalanche network, required for staking/validation and used as the base unit of account across its subnets, making it a Native L1 asset. It is also the primary gas and transaction fee token on the C-Chain and other EVM-compatible subnets, so Gas/Fee is the most appropriate secondary category.
A5: A1.2 | B5: Stated value proposition (one-sentence summary). | C5: Avalanche aims to provide a highly scalable, low-latency, and customizable Layer-1 blockchain platform—powered by its Avalanche consensus and subnet architecture—for deploying decentralized applications and custom blockchains with near-instant finality and low fees. | D5: High | E5: 0 | F5: =IF(D5="High",0,IF(D5="Medium",0.05,IF(D5="Low",0.1,IF(D5="Unknown",0.15,"")))) -> 0 | G5: =E5*(1+F5) -> 0 | H5: https://www.avax.network/about/avalanche-avax/; https://www.avax.network/about/press/introduction-to-avalanche/; https://www.avax.network/about/consensus | I5: 2024-11-15; 2024-10-20; 2024-10-01 | J5: 2025-12-12; 2025-12-12; 2025-12-12 | K5: =IF(I5="","",MAX(IFERROR(DATEVALUE(TRIM(MID(SUBSTITUTE(I5,";",REPT(" ",50)),1,50))),0),IFERROR(DATEVALUE(TRIM(MID(SUBSTITUTE(I5,";",REPT(" ",50)),51,50))),0),IFERROR(DATEVALUE(TRIM(MID(SUBSTITUTE(I5,";",REPT(" ",50)),101,50))),0),IFERROR(DATEVALUE(TRIM(MID(SUBSTITUTE(I5,";",REPT(" ",50)),151,50))),0),IFERROR(DATEVALUE(TRIM(MID(SUBSTITUTE(I5,";",REPT(" ",50)),201,50))),0),IFERROR(DATEVALUE(TRIM(MID(SUBSTITUTE(I5,";",REPT(" ",50)),251,50))),0),IFERROR(DATEVALUE(TRIM(MID(SUBSTITUTE(I5,";",REPT(" ",50)),301,50))),0),IFERROR(DATEVALUE(TRIM(MID(SUBSTITUTE(I5,";",REPT(" ",50)),351,50))),0),IFERROR(DATEVALUE(TRIM(MID(SUBSTITUTE(I5,";",REPT(" ",50)),401,50))),0),IFERROR(DATEVALUE(TRIM(MID(SUBSTITUTE(I5,";",REPT(" ",50)),451,50))),0))) -> 45611 | L5: =IF(K5="","",TODAY()-K5) -> 393 | M5: Evergreen–No Penalty | N5: =IF(M5="","",IF(L5="",INDEX($F$92:$F$95,MATCH(M5,$C$92:$C$95,0)),IF(L5<=INDEX($D$92:$D$95,MATCH(M5,$C$92:$C$95,0)),0,IF(L5<=INDEX($E$92:$E$95,MATCH(M5,$C$92:$C$95,0)),INDEX($F$92:$F$95,MATCH(M5,$C$92:$C$95,0)),INDEX($G$92:$G$95,MATCH(M5,$C$92:$C$95,0)))))) -> 0 | O5: =G5+N5 -> 0 | P5: No Review | Q5: Descriptive only; no escalation. | R5: Avalanche’s own materials describe it as an open, programmable, highly scalable platform offering high throughput, sub‑second or near‑instant finality, low fees, and support for custom blockchains/subnets for diverse dApps and asset tokenization, which together form its core value proposition.
A6: A1.3 | B6: Does real-world usage match the stated purpose? (Yes / Partial / No). | C6: Partial | D6: High | E6: =IF(C6="Yes",0,IF(C6="Partial",10,IF(C6="No",20,""))) -> 10 | F6: =IF(D6="High",0,IF(D6="Medium",0.05,IF(D6="Low",0.1,IF(D6="Unknown",0.15,"")))) -> 0 | G6: =E6*(1+F6) -> 10 | H6: https://www.avax.network/about/avalanche-avax/; https://messari.io/report/state-of-avalanche-q3-2024; https://blockchainreporter.net/avalanche-tvl-hits-1-74b-top-10-projects-dominating-the-ecosystem/ | I6: 2025-05-14; 2024-10-15; 2024-02-01 | J6: 2025-12-12; 2025-12-12; 2025-12-12 | K6: =IF(I6="","",MAX(IFERROR(DATEVALUE(TRIM(MID(SUBSTITUTE(I6,";",REPT(" ",50)),1,50))),0),IFERROR(DATEVALUE(TRIM(MID(SUBSTITUTE(I6,";",REPT(" ",50)),51,50))),0),IFERROR(DATEVALUE(TRIM(MID(SUBSTITUTE(I6,";",REPT(" ",50)),101,50))),0),IFERROR(DATEVALUE(TRIM(MID(SUBSTITUTE(I6,";",REPT(" ",50)),151,50))),0),IFERROR(DATEVALUE(TRIM(MID(SUBSTITUTE(I6,";",REPT(" ",50)),201,50))),0),IFERROR(DATEVALUE(TRIM(MID(SUBSTITUTE(I6,";",REPT(" ",50)),251,50))),0),IFERROR(DATEVALUE(TRIM(MID(SUBSTITUTE(I6,";",REPT(" ",50)),301,50))),0),IFERROR(DATEVALUE(TRIM(MID(SUBSTITUTE(I6,";",REPT(" ",50)),351,50))),0),IFERROR(DATEVALUE(TRIM(MID(SUBSTITUTE(I6,";",REPT(" ",50)),401,50))),0),IFERROR(DATEVALUE(TRIM(MID(SUBSTITUTE(I6,";",REPT(" ",50)),451,50))),0))) -> 45791 | L6: =IF(K6="","",TODAY()-K6) -> 213 | M6: Operational–Medium | N6: =IF(M6="","",IF(L6="",INDEX($F$92:$F$95,MATCH(M6,$C$92:$C$95,0)),IF(L6<=INDEX($D$92:$D$95,MATCH(M6,$C$92:$C$95,0)),0,IF(L6<=INDEX($E$92:$E$95,MATCH(M6,$C$92:$C$95,0)),INDEX($F$92:$F$95,MATCH(M6,$C$92:$C$95,0)),INDEX($G$92:$G$95,MATCH(M6,$C$92:$C$95,0)))))) -> 3 | O6: =G6+N6 -> 13 | P6: =IF(AND(C6="No",D6="Low"),"Review Required","No Review") -> No Review | Q6: Escalate only if stated purpose does not match real-world usage AND confidence is Low. | R6: Avalanche’s stated purpose is to be a high‑throughput, low‑latency, programmable platform for DeFi, dApps, and custom blockchains, ultimately aiming to tokenize global assets. In practice, it has significant DeFi adoption (Aave, Benqi, Trader Joe/LFJ, GMX) with TVL in the low‑billion‑dollar range and active usage of subnets, including gaming and real‑world‑asset tokenization like BlackRock‑backed BUIDL. This shows strong alignment with its DeFi/dApp and subnet vision, but its broader ambition to digitize “all the world’s assets” remains only partially realized, so alignment is best described as Partial.
A7: A1.4 | B7: List current real use cases (bulleted). | C7: - Decentralized finance (DeFi): Lending, DEXs, stablecoin settlement, and yield protocols on the C‑Chain (e.g., Aave, Curve and broader DeFi activity supported by growing on‑chain stablecoin supply). - Gaming and metaverse: High‑throughput game subnets such as DeFi Kingdoms’ DFK Chain, Shrapnel, Gunzilla/Off the Grid and Beam, using AVAX infrastructure for in‑game assets and transactions. - Enterprise / institutional finance: Tokenization and settlement of financial instruments and funds on Avalanche Evergreen/regulated subnets by institutions like JP Morgan, Citi, HSBC, VanEck and others (e.g., tokenized treasuries, short‑term debt, private equity, portfolio management). - Real‑world asset (RWA) tokenization: Tokenized real estate, film rights, structured finance products (e.g., IntainMARKETS), carbon and other assets issued on Avalanche subnets and the C‑Chain. - Ticketing & loyalty: Enterprise partners (e.g., Dreamus/OK Cashbag, Tixbase/PASSO) using Avalanche to issue verifiable event tickets and loyalty benefits, reducing fraud and enabling secondary markets. - Public sector and registries: Projects like the California DMV’s pilot to put vehicle titles and transfers on Avalanche infrastructure. - NFTs, collectibles & media: NFT marketplaces and media projects using Avalanche for digital collectibles, creator monetization and related Web3 experiences. - Core network utility: AVAX used as gas, for staking/validation, and for securing and participating in subnets, which power many of the above applications. | D7: High | E7: =IF(C7="","",IF(((LEN(C7)-LEN(SUBSTITUTE(C7,",","")))+(LEN(C7)-LEN(SUBSTITUTE(C7,";","")))+(LEN(C7)-LEN(SUBSTITUTE(C7,CHAR(10),""))))>=1,0,10)) -> 0 | F7: =IF(D7="High",0,IF(D7="Medium",0.05,IF(D7="Low",0.1,IF(D7="Unknown",0.15,"")))) -> 0 | G7: =E7*(1+F7) -> 0 | H7: https://www.avax.network/about/blog/7-avalanche-use-cases/; https://levex.com/en/blog/avalanche-guide; https://ambcrypto.com/blog/what-is-avax-avalanche-crypto-guide/ | I7: 2025-11-20; 2025-12-01; 2025-06-01 | J7: 2025-12-12; 2025-12-12; 2025-12-12 | K7: =IF(I7="","",MAX(IFERROR(DATEVALUE(TRIM(MID(SUBSTITUTE(I7,";",REPT(" ",50)),1,50))),0),IFERROR(DATEVALUE(TRIM(MID(SUBSTITUTE(I7,";",REPT(" ",50)),51,50))),0),IFERROR(DATEVALUE(TRIM(MID(SUBSTITUTE(I7,";",REPT(" ",50)),101,50))),0),IFERROR(DATEVALUE(TRIM(MID(SUBSTITUTE(I7,";",REPT(" ",50)),151,50))),0),IFERROR(DATEVALUE(TRIM(MID(SUBSTITUTE(I7,";",REPT(" ",50)),201,50))),0),IFERROR(DATEVALUE(TRIM(MID(SUBSTITUTE(I7,";",REPT(" ",50)),251,50))),0),IFERROR(DATEVALUE(TRIM(MID(SUBSTITUTE(I7,";",REPT(" ",50)),301,50))),0),IFERROR(DATEVALUE(TRIM(MID(SUBSTITUTE(I7,";",REPT(" ",50)),351,50))),0),IFERROR(DATEVALUE(TRIM(MID(SUBSTITUTE(I7,";",REPT(" ",50)),401,50))),0),IFERROR(DATEVALUE(TRIM(MID(SUBSTITUTE(I7,";",REPT(" ",50)),451,50))),0))) -> 45992 | L7: =IF(K7="","",TODAY()-K7) -> 12 | M7: Operational–Medium | N7: =IF(M7="","",IF(L7="",INDEX($F$92:$F$95,MATCH(M7,$C$92:$C$95,0)),IF(L7<=INDEX($D$92:$D$95,MATCH(M7,$C$92:$C$95,0)),0,IF(L7<=INDEX($E$92:$E$95,MATCH(M7,$C$92:$C$95,0)),INDEX($F$92:$F$95,MATCH(M7,$C$92:$C$95,0)),INDEX($G$92:$G$95,MATCH(M7,$C$92:$C$95,0)))))) -> 0 | O7: =G7+N7 -> 0 | P7: No Review | Q7: No trigger; used by A1.5/A3.1. | R7: Bullets summarize major categories of live Avalanche usage across DeFi, gaming subnets, institutional tokenization/RWAs, ticketing/loyalty, public registries, NFTs, and core network functions. Each cited source directly documents concrete applications or institutional integrations rather than hypothetical plans, supporting that these are current real use cases.
A8: A1.5 | B8: Identify and weight the main user groups of the token. Answer only in this format, using up to three groups: "<Group1> (primary), <Group2> (secondary), <Group3> (minor)". Choose user groups from: Developers, Validators, Retail, Institutions, Protocol integrators, Speculators. If speculators are only a minor group, write "Speculators (minor)". If they are a major driver, write "Speculators (primary)". Do not add any other words or explanation. | C8: Retail (primary), Developers (secondary), Speculators (minor) | D8: Medium | E8: =IF(C8="","",IF(ISNUMBER(SEARCH("Speculators (primary)",C8)),20,IF(ISNUMBER(SEARCH("Speculators (secondary)",C8)),15,IF(ISNUMBER(SEARCH("Speculators (minor)",C8)),10,IF(OR(ISNUMBER(SEARCH("Retail",C8)),ISNUMBER(SEARCH("Institutions",C8))),5,0))))) -> 10 | F8: =IF(D8="High",0,IF(D8="Medium",0.05,IF(D8="Low",0.1,IF(D8="Unknown",0.15,"")))) -> 0.05 | G8: =E8*(1+F8) -> 10.5 | K8: =IF(I8="","",MAX(IFERROR(DATEVALUE(TRIM(MID(SUBSTITUTE(I8,";",REPT(" ",50)),1,50))),0),IFERROR(DATEVALUE(TRIM(MID(SUBSTITUTE(I8,";",REPT(" ",50)),51,50))),0),IFERROR(DATEVALUE(TRIM(MID(SUBSTITUTE(I8,";",REPT(" ",50)),101,50))),0),IFERROR(DATEVALUE(TRIM(MID(SUBSTITUTE(I8,";",REPT(" ",50)),151,50))),0),IFERROR(DATEVALUE(TRIM(MID(SUBSTITUTE(I8,";",REPT(" ",50)),201,50))),0),IFERROR(DATEVALUE(TRIM(MID(SUBSTITUTE(I8,";",REPT(" ",50)),251,50))),0),IFERROR(DATEVALUE(TRIM(MID(SUBSTITUTE(I8,";",REPT(" ",50)),301,50))),0),IFERROR(DATEVALUE(TRIM(MID(SUBSTITUTE(I8,";",REPT(" ",50)),351,50))),0),IFERROR(DATEVALUE(TRIM(MID(SUBSTITUTE(I8,";",REPT(" ",50)),401,50))),0),IFERROR(DATEVALUE(TRIM(MID(SUBSTITUTE(I8,";",REPT(" ",50)),451,50))),0))) | L8: =IF(K8="","",TODAY()-K8) | M8: Operational–Medium | N8: =IF(M8="","",IF(L8="",INDEX($F$92:$F$95,MATCH(M8,$C$92:$C$95,0)),IF(L8<=INDEX($D$92:$D$95,MATCH(M8,$C$92:$C$95,0)),0,IF(L8<=INDEX($E$92:$E$95,MATCH(M8,$C$92:$C$95,0)),INDEX($F$92:$F$95,MATCH(M8,$C$92:$C$95,0)),INDEX($G$92:$G$95,MATCH(M8,$C$92:$C$95,0)))))) -> 3 | O8: =G8+N8 -> 13.5 | P8: =IF(AND(ISNUMBER(SEARCH("Speculator",C8)),E7=20),"Review Required","No Review") -> No Review | Q8: Escalate only if speculative demand dominates AND no real use cases exist (A1.4 = 0 items). | R8: AVAX is broadly used by retail users for transfers, DeFi, and dApps on Avalanche, making them the primary group. Developers are significant users via gas, deployment, and protocol tooling. Speculators are present but, relative to core network usage and builder activity, are best characterized as a minor group for this classification exercise.
A9: A1-N | B9: ≤120-word narrative summary for A.1 (purpose & design). | C9: AVAX is the native utility token of the Avalanche Primary Network, designed to secure a high‑throughput, proof‑of‑stake, Snowman/Avalanche‑based blockchain platform. AVAX’s primary purposes are to pay transaction and subnet fees, provide the staking collateral that secures validators and delegators, and serve as the unit of account across Avalanche L1s and subnets. Supply is hard‑capped at 720M AVAX, with about half minted at genesis and the remainder issued as staking rewards. All base transaction fees are paid in AVAX and burned, aligning tokenholder incentives with network usage and security. | D9: High | E9: 0 | F9: =IF(D9="High",0,IF(D9="Medium",0.05,IF(D9="Low",0.1,IF(D9="Unknown",0.15,"")))) -> 0 | G9: =E9*(1+F9) -> 0 | H9: https://build.avax.network/docs/primary-network/avax-token; https://support.avax.network/en/articles/6912428-tokenomics-faq; https://www.cube.exchange/what-is/avalanche | I9: 2024-10-15; 2024-10-01; 2025-12-01 | J9: 2025-12-12; 2025-12-12; 2025-12-12 | K9: =IF(I9="","",MAX(IFERROR(DATEVALUE(TRIM(MID(SUBSTITUTE(I9,";",REPT(" ",50)),1,50))),0),IFERROR(DATEVALUE(TRIM(MID(SUBSTITUTE(I9,";",REPT(" ",50)),51,50))),0),IFERROR(DATEVALUE(TRIM(MID(SUBSTITUTE(I9,";",REPT(" ",50)),101,50))),0),IFERROR(DATEVALUE(TRIM(MID(SUBSTITUTE(I9,";",REPT(" ",50)),151,50))),0),IFERROR(DATEVALUE(TRIM(MID(SUBSTITUTE(I9,";",REPT(" ",50)),201,50))),0),IFERROR(DATEVALUE(TRIM(MID(SUBSTITUTE(I9,";",REPT(" ",50)),251,50))),0),IFERROR(DATEVALUE(TRIM(MID(SUBSTITUTE(I9,";",REPT(" ",50)),301,50))),0),IFERROR(DATEVALUE(TRIM(MID(SUBSTITUTE(I9,";",REPT(" ",50)),351,50))),0),IFERROR(DATEVALUE(TRIM(MID(SUBSTITUTE(I9,";",REPT(" ",50)),401,50))),0),IFERROR(DATEVALUE(TRIM(MID(SUBSTITUTE(I9,";",REPT(" ",50)),451,50))),0))) -> 45992 | L9: =IF(K9="","",TODAY()-K9) -> 12 | M9: Evergreen–No Penalty | N9: =IF(M9="","",IF(L9="",INDEX($F$92:$F$95,MATCH(M9,$C$92:$C$95,0)),IF(L9<=INDEX($D$92:$D$95,MATCH(M9,$C$92:$C$95,0)),0,IF(L9<=INDEX($E$92:$E$95,MATCH(M9,$C$92:$C$95,0)),INDEX($F$92:$F$95,MATCH(M9,$C$92:$C$95,0)),INDEX($G$92:$G$95,MATCH(M9,$C$92:$C$95,0)))))) -> 0 | O9: =G9+N9 -> 0 | P9: No Review | Q9: Informational only; no trigger. | R9: Summary focuses on AVAX’s role in fees, staking-based security, unit of account across L1s/subnets, capped supply, and fee burn, all of which are clearly described in Avalanche’s official docs and tokenomics FAQs. These directly support the described purpose and design of the token.
A11: A2.1 | B11: Is the token required for core protocol operation? (Yes / Partially / No). | C11: Yes | D11: High | E11: =IF(C11="Yes",0,IF(C11="Partially",10,IF(C11="No",20,""))) -> 0 | F11: =IF(D11="High",0,IF(D11="Medium",0.05,IF(D11="Low",0.1,IF(D11="Unknown",0.15,"")))) -> 0 | G11: =E11*(1+F11) -> 0 | H11: https://build.avax.network/docs/primary-network/avax-token; https://support.avax.network/en/articles/6187511-validator-faq; https://support.avax.network/en/articles/6912428-tokenomics-faq | I11: 2024-11-15; 2024-10-01; 2024-10-01 | J11: 2025-12-12; 2025-12-12; 2025-12-12 | K11: =IF(I11="","",MAX(IFERROR(DATEVALUE(TRIM(MID(SUBSTITUTE(I11,";",REPT(" ",50)),1,50))),0),IFERROR(DATEVALUE(TRIM(MID(SUBSTITUTE(I11,";",REPT(" ",50)),51,50))),0),IFERROR(DATEVALUE(TRIM(MID(SUBSTITUTE(I11,";",REPT(" ",50)),101,50))),0),IFERROR(DATEVALUE(TRIM(MID(SUBSTITUTE(I11,";",REPT(" ",50)),151,50))),0),IFERROR(DATEVALUE(TRIM(MID(SUBSTITUTE(I11,";",REPT(" ",50)),201,50))),0),IFERROR(DATEVALUE(TRIM(MID(SUBSTITUTE(I11,";",REPT(" ",50)),251,50))),0),IFERROR(DATEVALUE(TRIM(MID(SUBSTITUTE(I11,";",REPT(" ",50)),301,50))),0),IFERROR(DATEVALUE(TRIM(MID(SUBSTITUTE(I11,";",REPT(" ",50)),351,50))),0),IFERROR(DATEVALUE(TRIM(MID(SUBSTITUTE(I11,";",REPT(" ",50)),401,50))),0),IFERROR(DATEVALUE(TRIM(MID(SUBSTITUTE(I11,";",REPT(" ",50)),451,50))),0))) -> 45611 | L11: =IF(K11="","",TODAY()-K11) -> 393 | M11: Evergreen–No Penalty | N11: =IF(M11="","",IF(L11="",INDEX($F$92:$F$95,MATCH(M11,$C$92:$C$95,0)),IF(L11<=INDEX($D$92:$D$95,MATCH(M11,$C$92:$C$95,0)),0,IF(L11<=INDEX($E$92:$E$95,MATCH(M11,$C$92:$C$95,0)),INDEX($F$92:$F$95,MATCH(M11,$C$92:$C$95,0)),INDEX($G$92:$G$95,MATCH(M11,$C$92:$C$95,0)))))) -> 0 | O11: =G11+N11 -> 0 | P11: No Review | R11: AVAX is the native utility token of the Avalanche Primary Network and is used to pay transaction fees (gas) and to secure the network via proof-of-stake validator staking. Validators must stake AVAX to participate in consensus, and all Primary Network gas fees are paid in AVAX and burned. These roles are intrinsic to core protocol operation, so the token is required rather than optional.
A12: A2.2 | B12: Does the token provide access to meaningful network services? (Yes / Limited / No). | C12: Yes | D12: High | E12: =IF(C12="Yes",0,IF(C12="Limited",10,IF(C12="No",20,""))) -> 0 | F12: =IF(D12="High",0,IF(D12="Medium",0.05,IF(D12="Low",0.1,IF(D12="Unknown",0.15,"")))) -> 0 | G12: =E12*(1+F12) -> 0 | H12: https://docs.avax.network/learn/avalanche/avax-token; https://docs.avax.network/validators/overview | I12: 2023-06-01; 2023-05-01 | J12: 2025-12-12; 2025-12-12 | K12: =IF(I12="","",MAX(IFERROR(DATEVALUE(TRIM(MID(SUBSTITUTE(I12,";",REPT(" ",50)),1,50))),0),IFERROR(DATEVALUE(TRIM(MID(SUBSTITUTE(I12,";",REPT(" ",50)),51,50))),0),IFERROR(DATEVALUE(TRIM(MID(SUBSTITUTE(I12,";",REPT(" ",50)),101,50))),0),IFERROR(DATEVALUE(TRIM(MID(SUBSTITUTE(I12,";",REPT(" ",50)),151,50))),0),IFERROR(DATEVALUE(TRIM(MID(SUBSTITUTE(I12,";",REPT(" ",50)),201,50))),0),IFERROR(DATEVALUE(TRIM(MID(SUBSTITUTE(I12,";",REPT(" ",50)),251,50))),0),IFERROR(DATEVALUE(TRIM(MID(SUBSTITUTE(I12,";",REPT(" ",50)),301,50))),0),IFERROR(DATEVALUE(TRIM(MID(SUBSTITUTE(I12,";",REPT(" ",50)),351,50))),0),IFERROR(DATEVALUE(TRIM(MID(SUBSTITUTE(I12,";",REPT(" ",50)),401,50))),0),IFERROR(DATEVALUE(TRIM(MID(SUBSTITUTE(I12,";",REPT(" ",50)),451,50))),0))) -> 45078 | L12: =IF(K12="","",TODAY()-K12) -> 926 | M12: Evergreen–No Penalty | N12: =IF(M12="","",IF(L12="",INDEX($F$92:$F$95,MATCH(M12,$C$92:$C$95,0)),IF(L12<=INDEX($D$92:$D$95,MATCH(M12,$C$92:$C$95,0)),0,IF(L12<=INDEX($E$92:$E$95,MATCH(M12,$C$92:$C$95,0)),INDEX($F$92:$F$95,MATCH(M12,$C$92:$C$95,0)),INDEX($G$92:$G$95,MATCH(M12,$C$92:$C$95,0)))))) -> 0 | O12: =G12+N12 -> 0 | P12: No Review | R12: AVAX is the native token of the Avalanche network and is required to pay transaction fees, secure the network via staking as a validator or delegator, and participate in governance/parameter decisions. It is also used across Avalanche subnets and as a unit of account for creating and operating custom blockchains on the platform. These constitute meaningful, core network services rather than purely speculative or cosmetic functions.
A13: A2.3 | B13: How dependent is utility on future network growth? (Low / Moderate / High). | C13: High | D13: High | E13: =IF(C13="Low",0,IF(C13="Moderate",10,IF(C13="High",20,""))) -> 20 | F13: =IF(D13="High",0,IF(D13="Medium",0.05,IF(D13="Low",0.1,IF(D13="Unknown",0.15,"")))) -> 0 | G13: =E13*(1+F13) -> 20 | H13: https://docs.avax.network/learn/avalanche/avax-token; https://docs.avax.network/learn/avalanche/subnets; https://subnets.avax.network | I13: 2024-06-01; 2023-10-01 | J13: 2025-12-12; 2025-12-12; 2025-12-12 | K13: =IF(I13="","",MAX(IFERROR(DATEVALUE(TRIM(MID(SUBSTITUTE(I13,";",REPT(" ",50)),1,50))),0),IFERROR(DATEVALUE(TRIM(MID(SUBSTITUTE(I13,";",REPT(" ",50)),51,50))),0),IFERROR(DATEVALUE(TRIM(MID(SUBSTITUTE(I13,";",REPT(" ",50)),101,50))),0),IFERROR(DATEVALUE(TRIM(MID(SUBSTITUTE(I13,";",REPT(" ",50)),151,50))),0),IFERROR(DATEVALUE(TRIM(MID(SUBSTITUTE(I13,";",REPT(" ",50)),201,50))),0),IFERROR(DATEVALUE(TRIM(MID(SUBSTITUTE(I13,";",REPT(" ",50)),251,50))),0),IFERROR(DATEVALUE(TRIM(MID(SUBSTITUTE(I13,";",REPT(" ",50)),301,50))),0),IFERROR(DATEVALUE(TRIM(MID(SUBSTITUTE(I13,";",REPT(" ",50)),351,50))),0),IFERROR(DATEVALUE(TRIM(MID(SUBSTITUTE(I13,";",REPT(" ",50)),401,50))),0),IFERROR(DATEVALUE(TRIM(MID(SUBSTITUTE(I13,";",REPT(" ",50)),451,50))),0))) -> 45444 | L13: =IF(K13="","",TODAY()-K13) -> 560 | M13: Evergreen–No Penalty | N13: =IF(M13="","",IF(L13="",INDEX($F$92:$F$95,MATCH(M13,$C$92:$C$95,0)),IF(L13<=INDEX($D$92:$D$95,MATCH(M13,$C$92:$C$95,0)),0,IF(L13<=INDEX($E$92:$E$95,MATCH(M13,$C$92:$C$95,0)),INDEX($F$92:$F$95,MATCH(M13,$C$92:$C$95,0)),INDEX($G$92:$G$95,MATCH(M13,$C$92:$C$95,0)))))) -> 0 | O13: =G13+N13 -> 20 | P13: No Review | R13: AVAX’s primary utilities—gas for smart contracts and subnets, staking for validator rewards, and use as a base unit of account across Avalanche’s DeFi, NFT, and gaming ecosystems—scale directly with on-chain activity and the number of subnets/applications. While AVAX already has existing usage, long‑term demand is structurally tied to future growth in transaction volume, dApp adoption, and subnet proliferation, implying high dependence on continued network growth for sustaining and expanding utility.
A14: A2-N | B14: ≤120-word narrative summary for A.2 (utility & necessity). | C14: AVAX is the native utility token of the Avalanche Primary Network, required to pay gas fees across the P‑, X‑ and C‑Chains and many subnets. All base transaction fees are paid in AVAX and burned, linking token demand to actual network usage. AVAX must be staked by validators and delegators to secure consensus in Avalanche’s proof‑of‑stake system, with stake weight determining validator influence and rewards. It also serves as the unit of account for value transfer and for creating/operating subnets and L1s, making AVAX structurally necessary for core network operation rather than an optional or purely speculative asset. | D14: High | E14: 0 | F14: =IF(D14="High",0,IF(D14="Medium",0.05,IF(D14="Low",0.1,IF(D14="Unknown",0.15,"")))) -> 0 | G14: =E14*(1+F14) -> 0 | H14: https://build.avax.network/docs/primary-network/avax-token; https://support.avax.network/en/articles/6912428-tokenomics-faq; https://www.cube.exchange/what-is/avalanche | I14: 2024-06-01; 2024-10-01; 2024-05-15 | J14: 2025-12-12; 2025-12-12; 2025-12-12 | K14: =IF(I14="","",MAX(IFERROR(DATEVALUE(TRIM(MID(SUBSTITUTE(I14,";",REPT(" ",50)),1,50))),0),IFERROR(DATEVALUE(TRIM(MID(SUBSTITUTE(I14,";",REPT(" ",50)),51,50))),0),IFERROR(DATEVALUE(TRIM(MID(SUBSTITUTE(I14,";",REPT(" ",50)),101,50))),0),IFERROR(DATEVALUE(TRIM(MID(SUBSTITUTE(I14,";",REPT(" ",50)),151,50))),0),IFERROR(DATEVALUE(TRIM(MID(SUBSTITUTE(I14,";",REPT(" ",50)),201,50))),0),IFERROR(DATEVALUE(TRIM(MID(SUBSTITUTE(I14,";",REPT(" ",50)),251,50))),0),IFERROR(DATEVALUE(TRIM(MID(SUBSTITUTE(I14,";",REPT(" ",50)),301,50))),0),IFERROR(DATEVALUE(TRIM(MID(SUBSTITUTE(I14,";",REPT(" ",50)),351,50))),0),IFERROR(DATEVALUE(TRIM(MID(SUBSTITUTE(I14,";",REPT(" ",50)),401,50))),0),IFERROR(DATEVALUE(TRIM(MID(SUBSTITUTE(I14,";",REPT(" ",50)),451,50))),0))) -> 45566 | L14: =IF(K14="","",TODAY()-K14) -> 438 | M14: Evergreen–No Penalty | N14: =IF(M14="","",IF(L14="",INDEX($F$92:$F$95,MATCH(M14,$C$92:$C$95,0)),IF(L14<=INDEX($D$92:$D$95,MATCH(M14,$C$92:$C$95,0)),0,IF(L14<=INDEX($E$92:$E$95,MATCH(M14,$C$92:$C$95,0)),INDEX($F$92:$F$95,MATCH(M14,$C$92:$C$95,0)),INDEX($G$92:$G$95,MATCH(M14,$C$92:$C$95,0)))))) -> 0 | O14: =G14+N14 -> 0 | P14: No Review | Q14: Informational only; no trigger. | R14: Official docs and multiple independent analyses consistently state that AVAX is required for gas, staking-based security, and subnet operations, with all fees burned. These functions tie AVAX demand and economic value directly to core protocol usage, indicating strong, non-optional utility within the Avalanche ecosystem.
A16: A3.1 | B16: Is token demand usage-driven, mixed, or speculative? (Usage-driven / Mixed / Speculative). | C16: Mixed | D16: High | E16: =IF(C16="Usage-driven",0,IF(C16="Mixed",10,IF(C16="Speculative",20,""))) -> 10 | F16: =IF(D16="High",0,IF(D16="Medium",0.05,IF(D16="Low",0.1,IF(D16="Unknown",0.15,"")))) -> 0 | G16: =E16*(1+F16) -> 10 | H16: https://docs.avax.network/learn/avalanche/avax; https://docs.avax.network/validators/staking; https://www.coingecko.com/en/coins/avalanche | I16: 2024-01-15; 2023-10-01; 2025-12-10 | J16: 2025-12-12; 2025-12-12; 2025-12-12 | K16: =IF(I16="","",MAX(IFERROR(DATEVALUE(TRIM(MID(SUBSTITUTE(I16,";",REPT(" ",50)),1,50))),0),IFERROR(DATEVALUE(TRIM(MID(SUBSTITUTE(I16,";",REPT(" ",50)),51,50))),0),IFERROR(DATEVALUE(TRIM(MID(SUBSTITUTE(I16,";",REPT(" ",50)),101,50))),0),IFERROR(DATEVALUE(TRIM(MID(SUBSTITUTE(I16,";",REPT(" ",50)),151,50))),0),IFERROR(DATEVALUE(TRIM(MID(SUBSTITUTE(I16,";",REPT(" ",50)),201,50))),0),IFERROR(DATEVALUE(TRIM(MID(SUBSTITUTE(I16,";",REPT(" ",50)),251,50))),0),IFERROR(DATEVALUE(TRIM(MID(SUBSTITUTE(I16,";",REPT(" ",50)),301,50))),0),IFERROR(DATEVALUE(TRIM(MID(SUBSTITUTE(I16,";",REPT(" ",50)),351,50))),0),IFERROR(DATEVALUE(TRIM(MID(SUBSTITUTE(I16,";",REPT(" ",50)),401,50))),0),IFERROR(DATEVALUE(TRIM(MID(SUBSTITUTE(I16,";",REPT(" ",50)),451,50))),0))) -> 46001 | L16: =IF(K16="","",TODAY()-K16) -> 3 | M16: Operational–Medium | N16: =IF(M16="","",IF(L16="",INDEX($F$92:$F$95,MATCH(M16,$C$92:$C$95,0)),IF(L16<=INDEX($D$92:$D$95,MATCH(M16,$C$92:$C$95,0)),0,IF(L16<=INDEX($E$92:$E$95,MATCH(M16,$C$92:$C$95,0)),INDEX($F$92:$F$95,MATCH(M16,$C$92:$C$95,0)),INDEX($G$92:$G$95,MATCH(M16,$C$92:$C$95,0)))))) -> 0 | O16: =G16+N16 -> 10 | P16: =IF(AND(C16="Speculative",E7=20),"Review Required","No Review") -> No Review | Q16: Escalate only if demand is speculative AND no real use cases exist (A1.4 = 0 items). | R16: AVAX demand is mixed. It has clear usage utility: used for gas fees, staking and validator rewards, and as the primary unit of account across Avalanche subnets and DeFi/NFT applications, giving it ongoing transactional and security demand. At the same time, it is widely traded on centralized and decentralized exchanges with significant speculative activity and price volatility, so a substantial share of demand is investment/speculation rather than purely usage-driven.
A17: A3-N | B17: ≤120-word narrative summary for A.3 (demand characterization). | C17: Demand for AVAX is driven by its role as the primary gas token and fee unit on Avalanche’s C-Chain and broader network, validator staking collateral, and participation in governance. Validators must stake AVAX to secure the network and earn rewards, creating structural demand and some lock-up. AVAX is also required for deploying and interacting with smart contracts and subnets, and is used for cross-chain transfers within the Avalanche tri-chain architecture. Additional demand comes from DeFi, NFTs, and other dApps built on Avalanche that use AVAX for trading pairs, collateral, and incentives, linking usage growth to token demand. | D17: High | E17: 0 | F17: =IF(D17="High",0,IF(D17="Medium",0.05,IF(D17="Low",0.1,IF(D17="Unknown",0.15,"")))) -> 0 | G17: =E17*(1+F17) -> 0 | H17: https://docs.avax.network/learn/avalanche/avax-token; https://docs.avax.network/learn/avalanche/why-avalanche; https://docs.avax.network/quickstart/fund-a-wallet | I17: 2024-04-01; 2023-08-01; 2023-06-01 | J17: 2025-12-12; 2025-12-12; 2025-12-12 | K17: =IF(I17="","",MAX(IFERROR(DATEVALUE(TRIM(MID(SUBSTITUTE(I17,";",REPT(" ",50)),1,50))),0),IFERROR(DATEVALUE(TRIM(MID(SUBSTITUTE(I17,";",REPT(" ",50)),51,50))),0),IFERROR(DATEVALUE(TRIM(MID(SUBSTITUTE(I17,";",REPT(" ",50)),101,50))),0),IFERROR(DATEVALUE(TRIM(MID(SUBSTITUTE(I17,";",REPT(" ",50)),151,50))),0),IFERROR(DATEVALUE(TRIM(MID(SUBSTITUTE(I17,";",REPT(" ",50)),201,50))),0),IFERROR(DATEVALUE(TRIM(MID(SUBSTITUTE(I17,";",REPT(" ",50)),251,50))),0),IFERROR(DATEVALUE(TRIM(MID(SUBSTITUTE(I17,";",REPT(" ",50)),301,50))),0),IFERROR(DATEVALUE(TRIM(MID(SUBSTITUTE(I17,";",REPT(" ",50)),351,50))),0),IFERROR(DATEVALUE(TRIM(MID(SUBSTITUTE(I17,";",REPT(" ",50)),401,50))),0),IFERROR(DATEVALUE(TRIM(MID(SUBSTITUTE(I17,";",REPT(" ",50)),451,50))),0))) -> 45383 | L17: =IF(K17="","",TODAY()-K17) -> 621 | M17: Operational–Medium | N17: =IF(M17="","",IF(L17="",INDEX($F$92:$F$95,MATCH(M17,$C$92:$C$95,0)),IF(L17<=INDEX($D$92:$D$95,MATCH(M17,$C$92:$C$95,0)),0,IF(L17<=INDEX($E$92:$E$95,MATCH(M17,$C$92:$C$95,0)),INDEX($F$92:$F$95,MATCH(M17,$C$92:$C$95,0)),INDEX($G$92:$G$95,MATCH(M17,$C$92:$C$95,0)))))) -> 6 | O17: =G17+N17 -> 6 | P17: No Review | Q17: Informational only; no trigger. | R17: Summary is based on Avalanche’s documented token utility (gas, staking, governance) and its role across C-Chain and subnets, plus ecosystem usage in DeFi and dApps. These are well-established, stable design features, so confidence is high.
B18: B. Governance & Control | K18: =IF(I18="","",MAX(IFERROR(DATEVALUE(TRIM(MID(SUBSTITUTE(I18,";",REPT(" ",50)),1,50))),0),IFERROR(DATEVALUE(TRIM(MID(SUBSTITUTE(I18,";",REPT(" ",50)),51,50))),0),IFERROR(DATEVALUE(TRIM(MID(SUBSTITUTE(I18,";",REPT(" ",50)),101,50))),0),IFERROR(DATEVALUE(TRIM(MID(SUBSTITUTE(I18,";",REPT(" ",50)),151,50))),0),IFERROR(DATEVALUE(TRIM(MID(SUBSTITUTE(I18,";",REPT(" ",50)),201,50))),0),IFERROR(DATEVALUE(TRIM(MID(SUBSTITUTE(I18,";",REPT(" ",50)),251,50))),0),IFERROR(DATEVALUE(TRIM(MID(SUBSTITUTE(I18,";",REPT(" ",50)),301,50))),0),IFERROR(DATEVALUE(TRIM(MID(SUBSTITUTE(I18,";",REPT(" ",50)),351,50))),0),IFERROR(DATEVALUE(TRIM(MID(SUBSTITUTE(I18,";",REPT(" ",50)),401,50))),0),IFERROR(DATEVALUE(TRIM(MID(SUBSTITUTE(I18,";",REPT(" ",50)),451,50))),0))) | N18: =IF(M18="","",IF(L18="",INDEX($F$92:$F$95,MATCH(M18,$C$92:$C$95,0)),IF(L18<=INDEX($D$92:$D$95,MATCH(M18,$C$92:$C$95,0)),0,IF(L18<=INDEX($E$92:$E$95,MATCH(M18,$C$92:$C$95,0)),INDEX($F$92:$F$95,MATCH(M18,$C$92:$C$95,0)),INDEX($G$92:$G$95,MATCH(M18,$C$92:$C$95,0))))))
A20: B1.1 | B20: What legal/organisational form anchors the protocol? Choose one: DAO, Hybrid (Foundation + DAO), Foundation, Company, Unknown. | C20: Foundation | D20: High | E20: =IF(C20="DAO",0,IF(C20="Hybrid (Foundation + DAO)",10,IF(C20="Foundation",10,IF(C20="Company",20,IF(C20="Unknown",20,""))))) -> 10 | F20: =IF(D20="High",0,IF(D20="Medium",0.05,IF(D20="Low",0.1,IF(D20="Unknown",0.15,"")))) -> 0 | G20: =E20*(1+F20) -> 10 | H20: https://www.avax.network/about/foundation; https://cryptonews.net/news/finance/31600238/; https://www.ft.com/content/87b5cb20-e86c-4849-8959-ee1f87ffb388 | I20: 2025-12-09; 2025-09-11; 2025-09-11 | J20: 2025-12-12; 2025-12-12; 2025-12-12 | K20: =IF(I20="","",MAX(IFERROR(DATEVALUE(TRIM(MID(SUBSTITUTE(I20,";",REPT(" ",50)),1,50))),0),IFERROR(DATEVALUE(TRIM(MID(SUBSTITUTE(I20,";",REPT(" ",50)),51,50))),0),IFERROR(DATEVALUE(TRIM(MID(SUBSTITUTE(I20,";",REPT(" ",50)),101,50))),0),IFERROR(DATEVALUE(TRIM(MID(SUBSTITUTE(I20,";",REPT(" ",50)),151,50))),0),IFERROR(DATEVALUE(TRIM(MID(SUBSTITUTE(I20,";",REPT(" ",50)),201,50))),0),IFERROR(DATEVALUE(TRIM(MID(SUBSTITUTE(I20,";",REPT(" ",50)),251,50))),0),IFERROR(DATEVALUE(TRIM(MID(SUBSTITUTE(I20,";",REPT(" ",50)),301,50))),0),IFERROR(DATEVALUE(TRIM(MID(SUBSTITUTE(I20,";",REPT(" ",50)),351,50))),0),IFERROR(DATEVALUE(TRIM(MID(SUBSTITUTE(I20,";",REPT(" ",50)),401,50))),0),IFERROR(DATEVALUE(TRIM(MID(SUBSTITUTE(I20,";",REPT(" ",50)),451,50))),0))) -> 46000 | L20: =IF(K20="","",TODAY()-K20) -> 4 | M20: Evergreen–No Penalty | N20: =IF(M20="","",IF(L20="",INDEX($F$92:$F$95,MATCH(M20,$C$92:$C$95,0)),IF(L20<=INDEX($D$92:$D$95,MATCH(M20,$C$92:$C$95,0)),0,IF(L20<=INDEX($E$92:$E$95,MATCH(M20,$C$92:$C$95,0)),INDEX($F$92:$F$95,MATCH(M20,$C$92:$C$95,0)),INDEX($G$92:$G$95,MATCH(M20,$C$92:$C$95,0)))))) -> 0 | O20: =G20+N20 -> 10 | P20: No Review | R20: The Avalanche protocol is primarily anchored by the Avalanche Foundation, a non-profit organization that supports the long-term growth and decentralization of the Avalanche network. Multiple sources describe Avalanche Foundation as the non-profit group overseeing or backing the Avalanche blockchain and managing AVAX reserves, indicating a foundation-centric governance anchor rather than a pure DAO or single company structure.
A21: B1.2 | B21: Is the governing entity’s jurisdiction and registration publicly disclosed? Answer Yes / No / Partial. | C21: Yes | D21: High | E21: =IF(C21="Yes",0,IF(C21="Partial",10,IF(C21="No",20,""))) -> 0 | F21: =IF(D21="High",0,IF(D21="Medium",0.05,IF(D21="Low",0.1,IF(D21="Unknown",0.15,"")))) -> 0 | G21: =E21*(1+F21) -> 0 | H21: https://lei.bloomberg.com/leis/view/254900FM9C1FUTT81V36; https://www.lei-lookup.com/record/254900FM9C1FUTT81V36/; https://opendatalei.com/lei/254900FM9C1FUTT81V36 | I21: 2025-11-19; 2025-11-19; 2025-10-01 | J21: 2025-12-12; 2025-12-12; 2025-12-12 | K21: =IF(I21="","",MAX(IFERROR(DATEVALUE(TRIM(MID(SUBSTITUTE(I21,";",REPT(" ",50)),1,50))),0),IFERROR(DATEVALUE(TRIM(MID(SUBSTITUTE(I21,";",REPT(" ",50)),51,50))),0),IFERROR(DATEVALUE(TRIM(MID(SUBSTITUTE(I21,";",REPT(" ",50)),101,50))),0),IFERROR(DATEVALUE(TRIM(MID(SUBSTITUTE(I21,";",REPT(" ",50)),151,50))),0),IFERROR(DATEVALUE(TRIM(MID(SUBSTITUTE(I21,";",REPT(" ",50)),201,50))),0),IFERROR(DATEVALUE(TRIM(MID(SUBSTITUTE(I21,";",REPT(" ",50)),251,50))),0),IFERROR(DATEVALUE(TRIM(MID(SUBSTITUTE(I21,";",REPT(" ",50)),301,50))),0),IFERROR(DATEVALUE(TRIM(MID(SUBSTITUTE(I21,";",REPT(" ",50)),351,50))),0),IFERROR(DATEVALUE(TRIM(MID(SUBSTITUTE(I21,";",REPT(" ",50)),401,50))),0),IFERROR(DATEVALUE(TRIM(MID(SUBSTITUTE(I21,";",REPT(" ",50)),451,50))),0))) -> 45980 | L21: =IF(K21="","",TODAY()-K21) -> 24 | M21: Evergreen–No Penalty | N21: =IF(M21="","",IF(L21="",INDEX($F$92:$F$95,MATCH(M21,$C$92:$C$95,0)),IF(L21<=INDEX($D$92:$D$95,MATCH(M21,$C$92:$C$95,0)),0,IF(L21<=INDEX($E$92:$E$95,MATCH(M21,$C$92:$C$95,0)),INDEX($F$92:$F$95,MATCH(M21,$C$92:$C$95,0)),INDEX($G$92:$G$95,MATCH(M21,$C$92:$C$95,0)))))) -> 0 | O21: =G21+N21 -> 0 | P21: No Review | R21: Avalanche is developed and governed by Ava Labs, Inc. Ava Labs’ legal name, jurisdiction, and registration are publicly disclosed: it is a Delaware corporation registered with the Delaware Division of Corporations, with LEI records listing its legal jurisdiction as United States – Delaware and providing its Delaware registration authority ID and entity ID. This satisfies public disclosure of governing entity jurisdiction and registration.
A22: B1.3 | B22: Are project leaders (core team / council) publicly identified? Answer Yes / No / Unknown. | C22: Yes | D22: High | E22: =IF(C22="Yes",0,IF(C22="No",20,IF(C22="Unknown",10,""))) -> 0 | F22: =IF(D22="High",0,IF(D22="Medium",0.05,IF(D22="Low",0.1,IF(D22="Unknown",0.15,"")))) -> 0 | G22: =E22*(1+F22) -> 0 | H22: https://www.avalabs.org/team; https://en.wikipedia.org/wiki/Avalanche_(blockchain_platform); https://news.cornell.edu/stories/2020/08/blockchain-startup-raises-quick-42m-first-sale | I22: 2025-12-10; 2024-10-15; 2020-08-06 | J22: 2025-12-12; 2025-12-12; 2025-12-12 | K22: =IF(I22="","",MAX(IFERROR(DATEVALUE(TRIM(MID(SUBSTITUTE(I22,";",REPT(" ",50)),1,50))),0),IFERROR(DATEVALUE(TRIM(MID(SUBSTITUTE(I22,";",REPT(" ",50)),51,50))),0),IFERROR(DATEVALUE(TRIM(MID(SUBSTITUTE(I22,";",REPT(" ",50)),101,50))),0),IFERROR(DATEVALUE(TRIM(MID(SUBSTITUTE(I22,";",REPT(" ",50)),151,50))),0),IFERROR(DATEVALUE(TRIM(MID(SUBSTITUTE(I22,";",REPT(" ",50)),201,50))),0),IFERROR(DATEVALUE(TRIM(MID(SUBSTITUTE(I22,";",REPT(" ",50)),251,50))),0),IFERROR(DATEVALUE(TRIM(MID(SUBSTITUTE(I22,";",REPT(" ",50)),301,50))),0),IFERROR(DATEVALUE(TRIM(MID(SUBSTITUTE(I22,";",REPT(" ",50)),351,50))),0),IFERROR(DATEVALUE(TRIM(MID(SUBSTITUTE(I22,";",REPT(" ",50)),401,50))),0),IFERROR(DATEVALUE(TRIM(MID(SUBSTITUTE(I22,";",REPT(" ",50)),451,50))),0))) -> 46001 | L22: =IF(K22="","",TODAY()-K22) -> 3 | M22: Evergreen–No Penalty | N22: =IF(M22="","",IF(L22="",INDEX($F$92:$F$95,MATCH(M22,$C$92:$C$95,0)),IF(L22<=INDEX($D$92:$D$95,MATCH(M22,$C$92:$C$95,0)),0,IF(L22<=INDEX($E$92:$E$95,MATCH(M22,$C$92:$C$95,0)),INDEX($F$92:$F$95,MATCH(M22,$C$92:$C$95,0)),INDEX($G$92:$G$95,MATCH(M22,$C$92:$C$95,0)))))) -> 0 | O22: =G22+N22 -> 0 | P22: No Review | R22: Yes. Avalanche is developed by Ava Labs, whose leadership and key contributors are publicly named, including founder and CEO Emin Gün Sirer and other executives. This makes the core project leaders clearly and publicly identified rather than anonymous or pseudonymous.
A23: B1.4 | B23: Are governance documents (constitution, voting rules, charters) published? Answer Yes / No / Unknown. | C23: No | D23: Medium | E23: =IF(C23="Yes",0,IF(C23="No",20,IF(C23="Unknown",10,""))) -> 20 | F23: =IF(D23="High",0,IF(D23="Medium",0.05,IF(D23="Low",0.1,IF(D23="Unknown",0.15,"")))) -> 0.05 | G23: =E23*(1+F23) -> 21 | H23: https://build.avax.network/docs/primary-network/avax-token; https://bestdapps.com/blogs/news/a-deepdive-into-avax-2026 | I23: 2025-11-30; 2025-10-15 | J23: 2025-12-12; 2025-12-12 | K23: =IF(I23="","",MAX(IFERROR(DATEVALUE(TRIM(MID(SUBSTITUTE(I23,";",REPT(" ",50)),1,50))),0),IFERROR(DATEVALUE(TRIM(MID(SUBSTITUTE(I23,";",REPT(" ",50)),51,50))),0),IFERROR(DATEVALUE(TRIM(MID(SUBSTITUTE(I23,";",REPT(" ",50)),101,50))),0),IFERROR(DATEVALUE(TRIM(MID(SUBSTITUTE(I23,";",REPT(" ",50)),151,50))),0),IFERROR(DATEVALUE(TRIM(MID(SUBSTITUTE(I23,";",REPT(" ",50)),201,50))),0),IFERROR(DATEVALUE(TRIM(MID(SUBSTITUTE(I23,";",REPT(" ",50)),251,50))),0),IFERROR(DATEVALUE(TRIM(MID(SUBSTITUTE(I23,";",REPT(" ",50)),301,50))),0),IFERROR(DATEVALUE(TRIM(MID(SUBSTITUTE(I23,";",REPT(" ",50)),351,50))),0),IFERROR(DATEVALUE(TRIM(MID(SUBSTITUTE(I23,";",REPT(" ",50)),401,50))),0),IFERROR(DATEVALUE(TRIM(MID(SUBSTITUTE(I23,";",REPT(" ",50)),451,50))),0))) -> 45991 | L23: =IF(K23="","",TODAY()-K23) -> 13 | M23: Evergreen–No Penalty | N23: =IF(M23="","",IF(L23="",INDEX($F$92:$F$95,MATCH(M23,$C$92:$C$95,0)),IF(L23<=INDEX($D$92:$D$95,MATCH(M23,$C$92:$C$95,0)),0,IF(L23<=INDEX($E$92:$E$95,MATCH(M23,$C$92:$C$95,0)),INDEX($F$92:$F$95,MATCH(M23,$C$92:$C$95,0)),INDEX($G$92:$G$95,MATCH(M23,$C$92:$C$95,0)))))) -> 0 | O23: =G23+N23 -> 21 | P23: No Review | R23: Avalanche publishes technical docs, whitepapers, and staking/validator rules, but there is no clear, formalized on‑chain governance framework or DAO-style constitution/voting charter for the AVAX main network. Upgrades are largely driven off‑chain by core developers and client releases, and third‑party analyses explicitly note the absence of on‑chain governance for protocol upgrades. Therefore, dedicated governance documents (constitution, voting rules, charters) are not considered published.
A24: B1.5 | B24: Are governance decisions and change logs publicly recorded? Answer Yes / No / Partial. | C24: Yes | D24: High | E24: =IF(C24="Yes",0,IF(C24="Partial",10,IF(C24="No",20,""))) -> 0 | F24: =IF(D24="High",0,IF(D24="Medium",0.05,IF(D24="Low",0.1,IF(D24="Unknown",0.15,"")))) -> 0 | G24: =E24*(1+F24) -> 0 | H24: https://www.avax.network/about/blog/etna-enhancing-the-sovereignty-of-avalanche-l1-networks/; https://github.com/ava-labs/avalanchego/releases | I24: 2024-12-02; 2025-11-05 | J24: 2025-12-12; 2025-12-12 | K24: =IF(I24="","",MAX(IFERROR(DATEVALUE(TRIM(MID(SUBSTITUTE(I24,";",REPT(" ",50)),1,50))),0),IFERROR(DATEVALUE(TRIM(MID(SUBSTITUTE(I24,";",REPT(" ",50)),51,50))),0),IFERROR(DATEVALUE(TRIM(MID(SUBSTITUTE(I24,";",REPT(" ",50)),101,50))),0),IFERROR(DATEVALUE(TRIM(MID(SUBSTITUTE(I24,";",REPT(" ",50)),151,50))),0),IFERROR(DATEVALUE(TRIM(MID(SUBSTITUTE(I24,";",REPT(" ",50)),201,50))),0),IFERROR(DATEVALUE(TRIM(MID(SUBSTITUTE(I24,";",REPT(" ",50)),251,50))),0),IFERROR(DATEVALUE(TRIM(MID(SUBSTITUTE(I24,";",REPT(" ",50)),301,50))),0),IFERROR(DATEVALUE(TRIM(MID(SUBSTITUTE(I24,";",REPT(" ",50)),351,50))),0),IFERROR(DATEVALUE(TRIM(MID(SUBSTITUTE(I24,";",REPT(" ",50)),401,50))),0),IFERROR(DATEVALUE(TRIM(MID(SUBSTITUTE(I24,";",REPT(" ",50)),451,50))),0))) -> 45966 | L24: =IF(K24="","",TODAY()-K24) -> 38 | M24: Evergreen–No Penalty | N24: =IF(M24="","",IF(L24="",INDEX($F$92:$F$95,MATCH(M24,$C$92:$C$95,0)),IF(L24<=INDEX($D$92:$D$95,MATCH(M24,$C$92:$C$95,0)),0,IF(L24<=INDEX($E$92:$E$95,MATCH(M24,$C$92:$C$95,0)),INDEX($F$92:$F$95,MATCH(M24,$C$92:$C$95,0)),INDEX($G$92:$G$95,MATCH(M24,$C$92:$C$95,0)))))) -> 0 | O24: =G24+N24 -> 0 | P24: No Review | R24: Avalanche governance decisions for protocol upgrades and parameter changes are documented through Avalanche Community Proposals (ACPs) referenced in official upgrade announcements and release notes, and node software releases specify which ACPs are activated and when. These upgrade posts and avalanchego GitHub release logs are publicly accessible, serving as both decision records and change logs.
A26: B2.1 | B26: Who controls upgrade/admin authority over core contracts? Choose: No upgrades (immutable), DAO vote, Large multisig (≥4), Small multisig (≤3), Single dev, or Unknown if public sources do not clearly indicate this. | C26: No upgrades (immutable) | D26: Medium | E26: =IF(C26="No upgrades (immutable)",0, IF(C26="DAO vote",0, IF(C26="Large multisig (≥4)",10, IF(C26="Small multisig (≤3)",10, IF(C26="Single dev",20, IF(C26="Unknown",10,""))))) ) -> 0 | F26: =IF(D26="High",0,IF(D26="Medium",0.05,IF(D26="Low",0.1,IF(D26="Unknown",0.15,"")))) -> 0.05 | G26: =E26*(1+F26) -> 0 | H26: https://docs.chainstack.com/docs/avalanche-tooling; https://cryptoslate.com/coins/avalanche/; https://github.com/ava-labs/avalanchego | I26: 2024-01-15; 2025-12-08; 2024-11-01 | J26: 2025-12-12; 2025-12-12; 2025-12-12 | K26: =IF(I26="","",MAX(IFERROR(DATEVALUE(TRIM(MID(SUBSTITUTE(I26,";",REPT(" ",50)),1,50))),0),IFERROR(DATEVALUE(TRIM(MID(SUBSTITUTE(I26,";",REPT(" ",50)),51,50))),0),IFERROR(DATEVALUE(TRIM(MID(SUBSTITUTE(I26,";",REPT(" ",50)),101,50))),0),IFERROR(DATEVALUE(TRIM(MID(SUBSTITUTE(I26,";",REPT(" ",50)),151,50))),0),IFERROR(DATEVALUE(TRIM(MID(SUBSTITUTE(I26,";",REPT(" ",50)),201,50))),0),IFERROR(DATEVALUE(TRIM(MID(SUBSTITUTE(I26,";",REPT(" ",50)),251,50))),0),IFERROR(DATEVALUE(TRIM(MID(SUBSTITUTE(I26,";",REPT(" ",50)),301,50))),0),IFERROR(DATEVALUE(TRIM(MID(SUBSTITUTE(I26,";",REPT(" ",50)),351,50))),0),IFERROR(DATEVALUE(TRIM(MID(SUBSTITUTE(I26,";",REPT(" ",50)),401,50))),0),IFERROR(DATEVALUE(TRIM(MID(SUBSTITUTE(I26,";",REPT(" ",50)),451,50))),0))) -> 45999 | L26: =IF(K26="","",TODAY()-K26) -> 5 | M26: Critical–Fast | N26: =IF(M26="","",IF(L26="",INDEX($F$92:$F$95,MATCH(M26,$C$92:$C$95,0)),IF(L26<=INDEX($D$92:$D$95,MATCH(M26,$C$92:$C$95,0)),0,IF(L26<=INDEX($E$92:$E$95,MATCH(M26,$C$92:$C$95,0)),INDEX($F$92:$F$95,MATCH(M26,$C$92:$C$95,0)),INDEX($G$92:$G$95,MATCH(M26,$C$92:$C$95,0)))))) -> 0 | O26: =G26+N26 -> 0 | P26: =IF(C26="Single dev","Review Required","No Review") -> No Review | Q26: Escalate only if upgrade/admin control is held by a single developer/key. | R26: AVAX is the native asset of the Avalanche primary network (X‑Chain/P‑Chain/C‑Chain), defined at the protocol level via the AVAX assetID rather than an upgradable smart contract. Public technical docs and explorer references treat AVAX as a built‑in asset of the chains, with no disclosed proxy/admin or upgradeable token contract; protocol changes occur through node/client upgrades, not via an admin key on a token contract.
A27: B2.2 | B27: Is the upgrade process documented and transparent (e.g., repo, docs, forums)? Answer Yes / No / Partial. | C27: Yes | D27: High | E27: =IF(C27="Yes",0,IF(C27="Partial",10,IF(C27="No",20,""))) -> 0 | F27: =IF(D27="High",0,IF(D27="Medium",0.05,IF(D27="Low",0.1,IF(D27="Unknown",0.15,"")))) -> 0 | G27: =E27*(1+F27) -> 0 | H27: https://github.com/ava-labs/avalanchego/releases; https://build.avax.network/docs/nodes/maintain/upgrade; https://build.avax.network/docs/acps | I27: 2025-11-05; 2024-11-20; 2025-11-01 | J27: 2025-12-12; 2025-12-12; 2025-12-12 | K27: =IF(I27="","",MAX(IFERROR(DATEVALUE(TRIM(MID(SUBSTITUTE(I27,";",REPT(" ",50)),1,50))),0),IFERROR(DATEVALUE(TRIM(MID(SUBSTITUTE(I27,";",REPT(" ",50)),51,50))),0),IFERROR(DATEVALUE(TRIM(MID(SUBSTITUTE(I27,";",REPT(" ",50)),101,50))),0),IFERROR(DATEVALUE(TRIM(MID(SUBSTITUTE(I27,";",REPT(" ",50)),151,50))),0),IFERROR(DATEVALUE(TRIM(MID(SUBSTITUTE(I27,";",REPT(" ",50)),201,50))),0),IFERROR(DATEVALUE(TRIM(MID(SUBSTITUTE(I27,";",REPT(" ",50)),251,50))),0),IFERROR(DATEVALUE(TRIM(MID(SUBSTITUTE(I27,";",REPT(" ",50)),301,50))),0),IFERROR(DATEVALUE(TRIM(MID(SUBSTITUTE(I27,";",REPT(" ",50)),351,50))),0),IFERROR(DATEVALUE(TRIM(MID(SUBSTITUTE(I27,";",REPT(" ",50)),401,50))),0),IFERROR(DATEVALUE(TRIM(MID(SUBSTITUTE(I27,";",REPT(" ",50)),451,50))),0))) -> 45966 | L27: =IF(K27="","",TODAY()-K27) -> 38 | M27: Evergreen–No Penalty | N27: =IF(M27="","",IF(L27="",INDEX($F$92:$F$95,MATCH(M27,$C$92:$C$95,0)),IF(L27<=INDEX($D$92:$D$95,MATCH(M27,$C$92:$C$95,0)),0,IF(L27<=INDEX($E$92:$E$95,MATCH(M27,$C$92:$C$95,0)),INDEX($F$92:$F$95,MATCH(M27,$C$92:$C$95,0)),INDEX($G$92:$G$95,MATCH(M27,$C$92:$C$95,0)))))) -> 0 | O27: =G27+N27 -> 0 | P27: No Review | R27: Yes. Avalanche’s upgrade process is documented and publicly visible: the AvalancheGo client has a transparent release history with detailed notes about scheduled network activations and required node actions, and the Builder Hub includes explicit documentation on how to upgrade nodes and manage mandatory vs optional upgrades. In addition, protocol-level changes are tracked via Avalanche Community Proposals (ACPs), an open, documented framework for proposing and activating upgrades.
A28: B2.3 | B28: Is there a time-lock or DAO safeguard (e.g., delay, veto) on upgrades? Answer Yes / No / Unknown. | C28: No | D28: Medium | E28: =IF(C28="Yes",0,IF(C28="No",20,IF(C28="Unknown",10,""))) -> 20 | F28: =IF(D28="High",0,IF(D28="Medium",0.05,IF(D28="Low",0.1,IF(D28="Unknown",0.15,"")))) -> 0.05 | G28: =E28*(1+F28) -> 21 | H28: https://build.avax.network/docs/acps; https://www.avax.network/about/blog/durango-avalanche-warp-messaging-comes-to-the-evm | I28: 2024-01-01; 2024-02-13 | J28: 2025-12-12; 2025-12-12 | K28: =IF(I28="","",MAX(IFERROR(DATEVALUE(TRIM(MID(SUBSTITUTE(I28,";",REPT(" ",50)),1,50))),0),IFERROR(DATEVALUE(TRIM(MID(SUBSTITUTE(I28,";",REPT(" ",50)),51,50))),0),IFERROR(DATEVALUE(TRIM(MID(SUBSTITUTE(I28,";",REPT(" ",50)),101,50))),0),IFERROR(DATEVALUE(TRIM(MID(SUBSTITUTE(I28,";",REPT(" ",50)),151,50))),0),IFERROR(DATEVALUE(TRIM(MID(SUBSTITUTE(I28,";",REPT(" ",50)),201,50))),0),IFERROR(DATEVALUE(TRIM(MID(SUBSTITUTE(I28,";",REPT(" ",50)),251,50))),0),IFERROR(DATEVALUE(TRIM(MID(SUBSTITUTE(I28,";",REPT(" ",50)),301,50))),0),IFERROR(DATEVALUE(TRIM(MID(SUBSTITUTE(I28,";",REPT(" ",50)),351,50))),0),IFERROR(DATEVALUE(TRIM(MID(SUBSTITUTE(I28,";",REPT(" ",50)),401,50))),0),IFERROR(DATEVALUE(TRIM(MID(SUBSTITUTE(I28,";",REPT(" ",50)),451,50))),0))) -> 45335 | L28: =IF(K28="","",TODAY()-K28) -> 669 | M28: Critical–Fast | N28: =IF(M28="","",IF(L28="",INDEX($F$92:$F$95,MATCH(M28,$C$92:$C$95,0)),IF(L28<=INDEX($D$92:$D$95,MATCH(M28,$C$92:$C$95,0)),0,IF(L28<=INDEX($E$92:$E$95,MATCH(M28,$C$92:$C$95,0)),INDEX($F$92:$F$95,MATCH(M28,$C$92:$C$95,0)),INDEX($G$92:$G$95,MATCH(M28,$C$92:$C$95,0)))))) -> 10 | O28: =G28+N28 -> 31 | P28: =IF(AND(C28="No", OR(C26="Single dev", C26="Small multisig (≤3)")),"Review Required","No Review") -> No Review | Q28: Escalate only if there is no safeguard AND control is Single dev or Small multisig (≤3). | R28: Avalanche network upgrades are proposed via Avalanche Community Proposals (ACPs) and activated when an overwhelming majority of the community and validators signal support by running compatible Avalanche Network Clients. Validators opt in by upgrading their node software; there is no mention of an on-chain timelock, formal DAO vote, or veto mechanism that must elapse before mainnet activation. Upgrades are executed at predefined activation times once the client release is available and installed by validators.
A29: B2.4 | B29: Are emergency pause/kill-switch functions present? Answer Yes / No / Unknown. | C29: No | D29: Medium | E29: =IF(C29="Yes",10,IF(C29="No",0,IF(C29="Unknown",5,""))) -> 0 | F29: =IF(D29="High",0,IF(D29="Medium",0.05,IF(D29="Low",0.1,IF(D29="Unknown",0.15,"")))) -> 0.05 | G29: =E29*(1+F29) -> 0 | H29: https://support.avax.network/en/articles/5232004-what-is-the-avalanche-avax-contract-address; https://support.avax.network/en/articles/4064680-what-is-the-avalanche-consensus-protocol | I29: 2024-10-15; 2024-10-01 | J29: 2025-12-12; 2025-12-12 | K29: =IF(I29="","",MAX(IFERROR(DATEVALUE(TRIM(MID(SUBSTITUTE(I29,";",REPT(" ",50)),1,50))),0),IFERROR(DATEVALUE(TRIM(MID(SUBSTITUTE(I29,";",REPT(" ",50)),51,50))),0),IFERROR(DATEVALUE(TRIM(MID(SUBSTITUTE(I29,";",REPT(" ",50)),101,50))),0),IFERROR(DATEVALUE(TRIM(MID(SUBSTITUTE(I29,";",REPT(" ",50)),151,50))),0),IFERROR(DATEVALUE(TRIM(MID(SUBSTITUTE(I29,";",REPT(" ",50)),201,50))),0),IFERROR(DATEVALUE(TRIM(MID(SUBSTITUTE(I29,";",REPT(" ",50)),251,50))),0),IFERROR(DATEVALUE(TRIM(MID(SUBSTITUTE(I29,";",REPT(" ",50)),301,50))),0),IFERROR(DATEVALUE(TRIM(MID(SUBSTITUTE(I29,";",REPT(" ",50)),351,50))),0),IFERROR(DATEVALUE(TRIM(MID(SUBSTITUTE(I29,";",REPT(" ",50)),401,50))),0),IFERROR(DATEVALUE(TRIM(MID(SUBSTITUTE(I29,";",REPT(" ",50)),451,50))),0))) -> 45580 | L29: =IF(K29="","",TODAY()-K29) -> 424 | M29: Critical–Fast | N29: =IF(M29="","",IF(L29="",INDEX($F$92:$F$95,MATCH(M29,$C$92:$C$95,0)),IF(L29<=INDEX($D$92:$D$95,MATCH(M29,$C$92:$C$95,0)),0,IF(L29<=INDEX($E$92:$E$95,MATCH(M29,$C$92:$C$95,0)),INDEX($F$92:$F$95,MATCH(M29,$C$92:$C$95,0)),INDEX($G$92:$G$95,MATCH(M29,$C$92:$C$95,0)))))) -> 10 | O29: =G29+N29 -> 10 | P29: No Review | R29: AVAX is the native coin of the Avalanche network and is governed directly by the protocol rather than by an upgradable smart contract with admin-controlled methods. Avalanche support explicitly notes that AVAX is not governed by any smart contract (i.e., no ERC‑20 style contract with pausable/kill functions). Public technical and consensus documentation describe a decentralized, validator-driven protocol and do not indicate any centralized emergency pause or kill-switch for the native token.
A30: B2.5 | B30: Is the multisig / admin address publicly verifiable (e.g., Safe, Etherscan labels)? Answer Yes / No / Unknown. | C30: No | D30: High | E30: =IF(C30="Yes",0,IF(C30="No",20,IF(C30="Unknown",10,""))) -> 20 | F30: =IF(D30="High",0,IF(D30="Medium",0.05,IF(D30="Low",0.1,IF(D30="Unknown",0.15,"")))) -> 0 | G30: =E30*(1+F30) -> 20 | H30: https://support.avax.network/en/articles/5232004-what-is-the-avalanche-avax-contract-address | I30: 2024-11-01 | J30: 2025-12-12 | K30: =IF(I30="","",MAX(IFERROR(DATEVALUE(TRIM(MID(SUBSTITUTE(I30,";",REPT(" ",50)),1,50))),0),IFERROR(DATEVALUE(TRIM(MID(SUBSTITUTE(I30,";",REPT(" ",50)),51,50))),0),IFERROR(DATEVALUE(TRIM(MID(SUBSTITUTE(I30,";",REPT(" ",50)),101,50))),0),IFERROR(DATEVALUE(TRIM(MID(SUBSTITUTE(I30,";",REPT(" ",50)),151,50))),0),IFERROR(DATEVALUE(TRIM(MID(SUBSTITUTE(I30,";",REPT(" ",50)),201,50))),0),IFERROR(DATEVALUE(TRIM(MID(SUBSTITUTE(I30,";",REPT(" ",50)),251,50))),0),IFERROR(DATEVALUE(TRIM(MID(SUBSTITUTE(I30,";",REPT(" ",50)),301,50))),0),IFERROR(DATEVALUE(TRIM(MID(SUBSTITUTE(I30,";",REPT(" ",50)),351,50))),0),IFERROR(DATEVALUE(TRIM(MID(SUBSTITUTE(I30,";",REPT(" ",50)),401,50))),0),IFERROR(DATEVALUE(TRIM(MID(SUBSTITUTE(I30,";",REPT(" ",50)),451,50))),0))) -> 45597 | L30: =IF(K30="","",TODAY()-K30) -> 407 | M30: Operational–Medium | N30: =IF(M30="","",IF(L30="",INDEX($F$92:$F$95,MATCH(M30,$C$92:$C$95,0)),IF(L30<=INDEX($D$92:$D$95,MATCH(M30,$C$92:$C$95,0)),0,IF(L30<=INDEX($E$92:$E$95,MATCH(M30,$C$92:$C$95,0)),INDEX($F$92:$F$95,MATCH(M30,$C$92:$C$95,0)),INDEX($G$92:$G$95,MATCH(M30,$C$92:$C$95,0)))))) -> 6 | O30: =G30+N30 -> 26 | P30: No Review | R30: AVAX is the native asset of the Avalanche network and is not implemented as a smart contract token; Avalanche’s own documentation notes that AVAX is governed by the base protocol and has no token contract address. With no token contract, there is no associated admin or multisig address to verify on explorers such as Etherscan/SnowTrace, so a verifiable multisig/admin does not apply here.
A31: B2.6 | B31: Is DAO voting binding (on-chain execution) or advisory-only? Choose: Binding, Advisory, No DAO, or Unknown if public sources do not clearly indicate this. | C31: Binding | D31: Medium | E31: =IF(C31="","", IF(C31="Binding",0, IF(C31="Advisory",10, IF(C31="No DAO",20, IF(C31="Unknown",10,""))))) -> 0 | F31: =IF(D31="High",0,IF(D31="Medium",0.05,IF(D31="Low",0.1,IF(D31="Unknown",0.15,"")))) -> 0.05 | G31: =E31*(1+F31) -> 0 | H31: https://docs.avax.network/learn/avalanche/avax-token; https://www.avalabs.org/whitepapers | I31: 2023-06-01; 2020-03-01 | J31: 2025-12-12; 2025-12-12 | K31: =IF(I31="","",MAX(IFERROR(DATEVALUE(TRIM(MID(SUBSTITUTE(I31,";",REPT(" ",50)),1,50))),0),IFERROR(DATEVALUE(TRIM(MID(SUBSTITUTE(I31,";",REPT(" ",50)),51,50))),0),IFERROR(DATEVALUE(TRIM(MID(SUBSTITUTE(I31,";",REPT(" ",50)),101,50))),0),IFERROR(DATEVALUE(TRIM(MID(SUBSTITUTE(I31,";",REPT(" ",50)),151,50))),0),IFERROR(DATEVALUE(TRIM(MID(SUBSTITUTE(I31,";",REPT(" ",50)),201,50))),0),IFERROR(DATEVALUE(TRIM(MID(SUBSTITUTE(I31,";",REPT(" ",50)),251,50))),0),IFERROR(DATEVALUE(TRIM(MID(SUBSTITUTE(I31,";",REPT(" ",50)),301,50))),0),IFERROR(DATEVALUE(TRIM(MID(SUBSTITUTE(I31,";",REPT(" ",50)),351,50))),0),IFERROR(DATEVALUE(TRIM(MID(SUBSTITUTE(I31,";",REPT(" ",50)),401,50))),0),IFERROR(DATEVALUE(TRIM(MID(SUBSTITUTE(I31,";",REPT(" ",50)),451,50))),0))) -> 45078 | L31: =IF(K31="","",TODAY()-K31) -> 926 | M31: Background–Slow | N31: =IF(M31="","",IF(L31="",INDEX($F$92:$F$95,MATCH(M31,$C$92:$C$95,0)),IF(L31<=INDEX($D$92:$D$95,MATCH(M31,$C$92:$C$95,0)),0,IF(L31<=INDEX($E$92:$E$95,MATCH(M31,$C$92:$C$95,0)),INDEX($F$92:$F$95,MATCH(M31,$C$92:$C$95,0)),INDEX($G$92:$G$95,MATCH(M31,$C$92:$C$95,0)))))) -> 4 | O31: =G31+N31 -> 4 | P31: No Review | R31: Avalanche governance is designed so that AVAX token holders can vote on-chain to change network parameters and upgrades, with successful votes executed via protocol mechanisms rather than being purely advisory. The Avalanche docs describe AVAX as used for securing the network and for on-chain governance of parameters and decisions, implying binding outcomes rather than off-chain advisory polling. However, public documentation does not always spell out every governance process end‑to‑end, so confidence is medium.
A32: B2.7 | B32: Have there been prior governance disputes, forks, or emergency upgrades? Answer Yes / No / Unknown (explain in Narrative if Yes). | C32: Yes | D32: High | E32: =IF(C32="No",0,IF(C32="Yes",10,IF(C32="Unknown",5,""))) -> 10 | F32: =IF(D32="High",0,IF(D32="Medium",0.05,IF(D32="Low",0.1,IF(D32="Unknown",0.15,"")))) -> 0 | G32: =E32*(1+F32) -> 10 | H32: https://www.coindesk.com/tech/2021/02/14/avalanche-crippled-by-bug-triggered-by-unusually-high-volume-engineer-says/; https://www.reddit.com/r/Avax/comments/li5q0d; https://www.coindesk.com/business/2024/02/23/avalanche-suffers-outage-fails-to-produce-block-for-almost-two-hours | I32: 2021-02-14; 2021-02-12; 2024-02-23 | J32: 2025-12-12; 2025-12-12; 2025-12-12 | K32: =IF(I32="","",MAX(IFERROR(DATEVALUE(TRIM(MID(SUBSTITUTE(I32,";",REPT(" ",50)),1,50))),0),IFERROR(DATEVALUE(TRIM(MID(SUBSTITUTE(I32,";",REPT(" ",50)),51,50))),0),IFERROR(DATEVALUE(TRIM(MID(SUBSTITUTE(I32,";",REPT(" ",50)),101,50))),0),IFERROR(DATEVALUE(TRIM(MID(SUBSTITUTE(I32,";",REPT(" ",50)),151,50))),0),IFERROR(DATEVALUE(TRIM(MID(SUBSTITUTE(I32,";",REPT(" ",50)),201,50))),0),IFERROR(DATEVALUE(TRIM(MID(SUBSTITUTE(I32,";",REPT(" ",50)),251,50))),0),IFERROR(DATEVALUE(TRIM(MID(SUBSTITUTE(I32,";",REPT(" ",50)),301,50))),0),IFERROR(DATEVALUE(TRIM(MID(SUBSTITUTE(I32,";",REPT(" ",50)),351,50))),0),IFERROR(DATEVALUE(TRIM(MID(SUBSTITUTE(I32,";",REPT(" ",50)),401,50))),0),IFERROR(DATEVALUE(TRIM(MID(SUBSTITUTE(I32,";",REPT(" ",50)),451,50))),0))) -> 45345 | L32: =IF(K32="","",TODAY()-K32) -> 659 | M32: Operational–Medium | N32: =IF(M32="","",IF(L32="",INDEX($F$92:$F$95,MATCH(M32,$C$92:$C$95,0)),IF(L32<=INDEX($D$92:$D$95,MATCH(M32,$C$92:$C$95,0)),0,IF(L32<=INDEX($E$92:$E$95,MATCH(M32,$C$92:$C$95,0)),INDEX($F$92:$F$95,MATCH(M32,$C$92:$C$95,0)),INDEX($G$92:$G$95,MATCH(M32,$C$92:$C$95,0)))))) -> 6 | O32: =G32+N32 -> 16 | P32: No Review | R32: Yes. Avalanche has experienced several emergency-type client upgrades in response to critical bugs and outages, though not contentious governance-driven forks. In Feb 2021, heavy load around Pangolin’s launch triggered a cross-chain finality bug that effectively halted transactions until developers deployed a non–backwards-compatible AvalancheGo patch and validators upgraded. In March 2023 and Feb 2024, further software bugs caused block production/finalization stalls that were resolved via rapid node software updates.
A34: B3.1 | B34: How many distinct parties (independent entities or individuals) effectively control the treasury keys for the main treasury and ecosystem funds? Choose one: DAO, ≥4, ≤3, Single. | C34: Single | D34: Medium | E34: =IF(C34="DAO",0,IF(C34="≥4",10,IF(C34="≤3",20,IF(C34="Single",20,"")))) -> 20 | F34: =IF(D34="High",0,IF(D34="Medium",0.05,IF(D34="Low",0.1,IF(D34="Unknown",0.15,"")))) -> 0.05 | G34: =E34*(1+F34) -> 21 | H34: https://www.coindesk.com/business/2025/09/11/avalanche-foundation-eyes-usd1b-raise-to-fund-two-crypto-treasury-companies-ft/; https://www.cointribune.com/en/avalanche-foundation-plans-1b-for-avax-treasury-firms/; https://messari.io/organization/avalanche-foundation | I34: 2025-09-11; 2025-09-12 | J34: 2025-12-12; 2025-12-12; 2025-12-12 | K34: =IF(I34="","",MAX(IFERROR(DATEVALUE(TRIM(MID(SUBSTITUTE(I34,";",REPT(" ",50)),1,50))),0),IFERROR(DATEVALUE(TRIM(MID(SUBSTITUTE(I34,";",REPT(" ",50)),51,50))),0),IFERROR(DATEVALUE(TRIM(MID(SUBSTITUTE(I34,";",REPT(" ",50)),101,50))),0),IFERROR(DATEVALUE(TRIM(MID(SUBSTITUTE(I34,";",REPT(" ",50)),151,50))),0),IFERROR(DATEVALUE(TRIM(MID(SUBSTITUTE(I34,";",REPT(" ",50)),201,50))),0),IFERROR(DATEVALUE(TRIM(MID(SUBSTITUTE(I34,";",REPT(" ",50)),251,50))),0),IFERROR(DATEVALUE(TRIM(MID(SUBSTITUTE(I34,";",REPT(" ",50)),301,50))),0),IFERROR(DATEVALUE(TRIM(MID(SUBSTITUTE(I34,";",REPT(" ",50)),351,50))),0),IFERROR(DATEVALUE(TRIM(MID(SUBSTITUTE(I34,";",REPT(" ",50)),401,50))),0),IFERROR(DATEVALUE(TRIM(MID(SUBSTITUTE(I34,";",REPT(" ",50)),451,50))),0))) -> 45912 | L34: =IF(K34="","",TODAY()-K34) -> 92 | M34: Critical–Fast | N34: =IF(M34="","",IF(L34="",INDEX($F$92:$F$95,MATCH(M34,$C$92:$C$95,0)),IF(L34<=INDEX($D$92:$D$95,MATCH(M34,$C$92:$C$95,0)),0,IF(L34<=INDEX($E$92:$E$95,MATCH(M34,$C$92:$C$95,0)),INDEX($F$92:$F$95,MATCH(M34,$C$92:$C$95,0)),INDEX($G$92:$G$95,MATCH(M34,$C$92:$C$95,0)))))) -> 5 | O34: =G34+N34 -> 26 | P34: =IF(OR(C34="Single",C34="≤3"),IF(OR(C35="No",C36="No",C37="No",C38="No",C39="Yes"),"Review Required","No Review"),"No Review") -> No Review | Q34: Triggers Board review if treasury control is highly concentrated (Single or ≤3 distinct parties) and at least one of the following is true: treasury rules are not published, disbursements are not transparently tracked, there is no clear separation of duties, no periodic treasury reporting, or there has been a material treasury controversy. | R34: Available evidence indicates that AVAX’s main treasury and ecosystem reserves are controlled centrally by the Avalanche Foundation, a single non‑profit entity that oversees the blockchain and sells AVAX from its own reserves into new treasury vehicles. There is no indication of a community DAO controlling these funds; governance over reserves appears to be foundation‑driven, even if internal multisig procedures exist, so effective control is best classified as Single rather than DAO or widely distributed.
A35: B3.2 | B35: Are treasury disbursement rules published (policy/charter)? Answer Yes / No / Unknown. | C35: Unknown | D35: Medium | E35: =IF(C35="Yes",0,IF(C35="No",20,IF(C35="Unknown",10,""))) -> 10 | F35: =IF(D35="High",0,IF(D35="Medium",0.05,IF(D35="Low",0.1,IF(D35="Unknown",0.15,"")))) -> 0.05 | G35: =E35*(1+F35) -> 10.5 | H35: https://forum.avax.network/t/eligibility-criteria/1948; https://build.avax.network/grants | I35: 2023-05-01 | J35: 2025-12-12; 2025-12-12 | K35: =IF(I35="","",MAX(IFERROR(DATEVALUE(TRIM(MID(SUBSTITUTE(I35,";",REPT(" ",50)),1,50))),0),IFERROR(DATEVALUE(TRIM(MID(SUBSTITUTE(I35,";",REPT(" ",50)),51,50))),0),IFERROR(DATEVALUE(TRIM(MID(SUBSTITUTE(I35,";",REPT(" ",50)),101,50))),0),IFERROR(DATEVALUE(TRIM(MID(SUBSTITUTE(I35,";",REPT(" ",50)),151,50))),0),IFERROR(DATEVALUE(TRIM(MID(SUBSTITUTE(I35,";",REPT(" ",50)),201,50))),0),IFERROR(DATEVALUE(TRIM(MID(SUBSTITUTE(I35,";",REPT(" ",50)),251,50))),0),IFERROR(DATEVALUE(TRIM(MID(SUBSTITUTE(I35,";",REPT(" ",50)),301,50))),0),IFERROR(DATEVALUE(TRIM(MID(SUBSTITUTE(I35,";",REPT(" ",50)),351,50))),0),IFERROR(DATEVALUE(TRIM(MID(SUBSTITUTE(I35,";",REPT(" ",50)),401,50))),0),IFERROR(DATEVALUE(TRIM(MID(SUBSTITUTE(I35,";",REPT(" ",50)),451,50))),0))) -> 45047 | L35: =IF(K35="","",TODAY()-K35) -> 957 | M35: Evergreen–No Penalty | N35: =IF(M35="","",IF(L35="",INDEX($F$92:$F$95,MATCH(M35,$C$92:$C$95,0)),IF(L35<=INDEX($D$92:$D$95,MATCH(M35,$C$92:$C$95,0)),0,IF(L35<=INDEX($E$92:$E$95,MATCH(M35,$C$92:$C$95,0)),INDEX($F$92:$F$95,MATCH(M35,$C$92:$C$95,0)),INDEX($G$92:$G$95,MATCH(M35,$C$92:$C$95,0)))))) -> 0 | O35: =G35+N35 -> 10.5 | P35: No Review | R35: Avalanche publishes some program-specific funding criteria (e.g., Community Grants eligibility and Builder Hub grant descriptions), but I could not locate a comprehensive, overarching treasury disbursement policy or charter that clearly governs all treasury spending. Because existing materials appear fragmented and program-focused rather than a unified treasury rulebook, the status of a formal, published treasury disbursement policy is best recorded as Unknown.
A36: B3.3 | B36: Are grants/dev fund disbursements tracked transparently (public reports or dashboards)? Answer Yes / No / Partial. | C36: Partial | D36: Medium | E36: =IF(C36="Yes",0,IF(C36="Partial",10,IF(C36="No",20,""))) -> 10 | F36: =IF(D36="High",0,IF(D36="Medium",0.05,IF(D36="Low",0.1,IF(D36="Unknown",0.15,"")))) -> 0.05 | G36: =E36*(1+F36) -> 10.5 | H36: https://www.avax.network/blog/dexalot-subnet-earns-avalanche-multiverse-incentives-of-up-to-3-million; https://www.avax.network/about/blog/avalanche-foundation-launches-community-grants-program-with-gitcoin/ | I36: 2023-08-16; 2024-03-25 | J36: 2025-12-12; 2025-12-12 | K36: =IF(I36="","",MAX(IFERROR(DATEVALUE(TRIM(MID(SUBSTITUTE(I36,";",REPT(" ",50)),1,50))),0),IFERROR(DATEVALUE(TRIM(MID(SUBSTITUTE(I36,";",REPT(" ",50)),51,50))),0),IFERROR(DATEVALUE(TRIM(MID(SUBSTITUTE(I36,";",REPT(" ",50)),101,50))),0),IFERROR(DATEVALUE(TRIM(MID(SUBSTITUTE(I36,";",REPT(" ",50)),151,50))),0),IFERROR(DATEVALUE(TRIM(MID(SUBSTITUTE(I36,";",REPT(" ",50)),201,50))),0),IFERROR(DATEVALUE(TRIM(MID(SUBSTITUTE(I36,";",REPT(" ",50)),251,50))),0),IFERROR(DATEVALUE(TRIM(MID(SUBSTITUTE(I36,";",REPT(" ",50)),301,50))),0),IFERROR(DATEVALUE(TRIM(MID(SUBSTITUTE(I36,";",REPT(" ",50)),351,50))),0),IFERROR(DATEVALUE(TRIM(MID(SUBSTITUTE(I36,";",REPT(" ",50)),401,50))),0),IFERROR(DATEVALUE(TRIM(MID(SUBSTITUTE(I36,";",REPT(" ",50)),451,50))),0))) -> 45376 | L36: =IF(K36="","",TODAY()-K36) -> 628 | M36: Operational–Medium | N36: =IF(M36="","",IF(L36="",INDEX($F$92:$F$95,MATCH(M36,$C$92:$C$95,0)),IF(L36<=INDEX($D$92:$D$95,MATCH(M36,$C$92:$C$95,0)),0,IF(L36<=INDEX($E$92:$E$95,MATCH(M36,$C$92:$C$95,0)),INDEX($F$92:$F$95,MATCH(M36,$C$92:$C$95,0)),INDEX($G$92:$G$95,MATCH(M36,$C$92:$C$95,0)))))) -> 6 | O36: =G36+N36 -> 16.5 | P36: No Review | R36: Avalanche’s Foundation publishes some information on specific grant and incentive programs (e.g., Multiverse subnet incentives, Dexalot award) and has launched a Community Grants Program via Gitcoin, whose rounds and matching distributions are transparently viewable on Gitcoin’s own infrastructure. However, there is no evidence of a single comprehensive, continuously updated public dashboard or report covering all Foundation/treasury dev-fund disbursements, so transparency appears program‑specific rather than holistic.
A37: B3.4 | B37: Is there separation of duties between leadership (foundation execs) and treasury controllers? Answer Yes / No / Unknown. | C37: Unknown | D37: Low | E37: =IF(C37="Yes",0,IF(C37="No",20,IF(C37="Unknown",10,""))) -> 10 | F37: =IF(D37="High",0,IF(D37="Medium",0.05,IF(D37="Low",0.1,IF(D37="Unknown",0.15,"")))) -> 0.1 | G37: =E37*(1+F37) -> 11 | K37: =IF(I37="","",MAX(IFERROR(DATEVALUE(TRIM(MID(SUBSTITUTE(I37,";",REPT(" ",50)),1,50))),0),IFERROR(DATEVALUE(TRIM(MID(SUBSTITUTE(I37,";",REPT(" ",50)),51,50))),0),IFERROR(DATEVALUE(TRIM(MID(SUBSTITUTE(I37,";",REPT(" ",50)),101,50))),0),IFERROR(DATEVALUE(TRIM(MID(SUBSTITUTE(I37,";",REPT(" ",50)),151,50))),0),IFERROR(DATEVALUE(TRIM(MID(SUBSTITUTE(I37,";",REPT(" ",50)),201,50))),0),IFERROR(DATEVALUE(TRIM(MID(SUBSTITUTE(I37,";",REPT(" ",50)),251,50))),0),IFERROR(DATEVALUE(TRIM(MID(SUBSTITUTE(I37,";",REPT(" ",50)),301,50))),0),IFERROR(DATEVALUE(TRIM(MID(SUBSTITUTE(I37,";",REPT(" ",50)),351,50))),0),IFERROR(DATEVALUE(TRIM(MID(SUBSTITUTE(I37,";",REPT(" ",50)),401,50))),0),IFERROR(DATEVALUE(TRIM(MID(SUBSTITUTE(I37,";",REPT(" ",50)),451,50))),0))) | L37: =IF(K37="","",TODAY()-K37) | M37: Background–Slow | N37: =IF(M37="","",IF(L37="",INDEX($F$92:$F$95,MATCH(M37,$C$92:$C$95,0)),IF(L37<=INDEX($D$92:$D$95,MATCH(M37,$C$92:$C$95,0)),0,IF(L37<=INDEX($E$92:$E$95,MATCH(M37,$C$92:$C$95,0)),INDEX($F$92:$F$95,MATCH(M37,$C$92:$C$95,0)),INDEX($G$92:$G$95,MATCH(M37,$C$92:$C$95,0)))))) -> 2 | O37: =G37+N37 -> 13 | P37: No Review | R37: Public materials describe Avalanche’s governance, token distribution, and the role of the Avalanche Foundation, but do not clearly specify whether treasury assets are controlled by individuals distinct from foundation executives or whether formal separation-of-duties controls exist. In the absence of explicit disclosures about treasury controller roles and internal controls, the presence or absence of such separation cannot be confirmed.
A38: B3.5 | B38: Does the project publish periodic financial/treasury reports? Answer Yes / No / Unknown. | C38: Yes | D38: Medium | E38: =IF(C38="Yes",0,IF(C38="No",20,IF(C38="Unknown",10,""))) -> 0 | F38: =IF(D38="High",0,IF(D38="Medium",0.05,IF(D38="Low",0.1,IF(D38="Unknown",0.15,"")))) -> 0.05 | G38: =E38*(1+F38) -> 0 | H38: https://www.chaincatcher.com/en/article/2171499; https://www.avax.network/about/foundation | I38: 2025-03-08 | J38: 2025-12-12; 2025-12-12 | K38: =IF(I38="","",MAX(IFERROR(DATEVALUE(TRIM(MID(SUBSTITUTE(I38,";",REPT(" ",50)),1,50))),0),IFERROR(DATEVALUE(TRIM(MID(SUBSTITUTE(I38,";",REPT(" ",50)),51,50))),0),IFERROR(DATEVALUE(TRIM(MID(SUBSTITUTE(I38,";",REPT(" ",50)),101,50))),0),IFERROR(DATEVALUE(TRIM(MID(SUBSTITUTE(I38,";",REPT(" ",50)),151,50))),0),IFERROR(DATEVALUE(TRIM(MID(SUBSTITUTE(I38,";",REPT(" ",50)),201,50))),0),IFERROR(DATEVALUE(TRIM(MID(SUBSTITUTE(I38,";",REPT(" ",50)),251,50))),0),IFERROR(DATEVALUE(TRIM(MID(SUBSTITUTE(I38,";",REPT(" ",50)),301,50))),0),IFERROR(DATEVALUE(TRIM(MID(SUBSTITUTE(I38,";",REPT(" ",50)),351,50))),0),IFERROR(DATEVALUE(TRIM(MID(SUBSTITUTE(I38,";",REPT(" ",50)),401,50))),0),IFERROR(DATEVALUE(TRIM(MID(SUBSTITUTE(I38,";",REPT(" ",50)),451,50))),0))) -> 45724 | L38: =IF(K38="","",TODAY()-K38) -> 280 | M38: Operational–Medium | N38: =IF(M38="","",IF(L38="",INDEX($F$92:$F$95,MATCH(M38,$C$92:$C$95,0)),IF(L38<=INDEX($D$92:$D$95,MATCH(M38,$C$92:$C$95,0)),0,IF(L38<=INDEX($E$92:$E$95,MATCH(M38,$C$92:$C$95,0)),INDEX($F$92:$F$95,MATCH(M38,$C$92:$C$95,0)),INDEX($G$92:$G$95,MATCH(M38,$C$92:$C$95,0)))))) -> 3 | O38: =G38+N38 -> 3 | P38: No Review | R38: Evidence indicates the Avalanche Foundation has begun publishing formal annual reports, which qualify as periodic financial/treasury-style disclosures. A former board member noted that during an 18‑month tenure the Foundation released its first annual report, suggesting a move toward recurring, structured reporting rather than purely ad‑hoc announcements.
A39: B3.6 | B39: Has the treasury been subject to material controversy (misuse, loss, litigation)? Answer Yes / No / Unknown (explain in Narrative if Yes). | C39: No | D39: Medium | E39: =IF(C39="No",0,IF(C39="Yes",10,IF(C39="Unknown",5,""))) -> 0 | F39: =IF(D39="High",0,IF(D39="Medium",0.05,IF(D39="Low",0.1,IF(D39="Unknown",0.15,"")))) -> 0.05 | G39: =E39*(1+F39) -> 0 | H39: https://cointelegraph.com/news/avalanche-buyback-1-97-million-avax-tokens-terra; https://forklog.com/en/avalanche-foundation-to-repurchase-avax-tokens-sold-to-terra/; https://www.coindesk.com/business/2025/09/11/avalanche-foundation-eyes-usd1b-raise-to-fund-two-crypto-treasury-companies-ft/ | I39: 2024-11-07; 2024-10-14; 2025-09-11 | J39: 2025-12-12; 2025-12-12; 2025-12-12 | K39: =IF(I39="","",MAX(IFERROR(DATEVALUE(TRIM(MID(SUBSTITUTE(I39,";",REPT(" ",50)),1,50))),0),IFERROR(DATEVALUE(TRIM(MID(SUBSTITUTE(I39,";",REPT(" ",50)),51,50))),0),IFERROR(DATEVALUE(TRIM(MID(SUBSTITUTE(I39,";",REPT(" ",50)),101,50))),0),IFERROR(DATEVALUE(TRIM(MID(SUBSTITUTE(I39,";",REPT(" ",50)),151,50))),0),IFERROR(DATEVALUE(TRIM(MID(SUBSTITUTE(I39,";",REPT(" ",50)),201,50))),0),IFERROR(DATEVALUE(TRIM(MID(SUBSTITUTE(I39,";",REPT(" ",50)),251,50))),0),IFERROR(DATEVALUE(TRIM(MID(SUBSTITUTE(I39,";",REPT(" ",50)),301,50))),0),IFERROR(DATEVALUE(TRIM(MID(SUBSTITUTE(I39,";",REPT(" ",50)),351,50))),0),IFERROR(DATEVALUE(TRIM(MID(SUBSTITUTE(I39,";",REPT(" ",50)),401,50))),0),IFERROR(DATEVALUE(TRIM(MID(SUBSTITUTE(I39,";",REPT(" ",50)),451,50))),0))) -> 45911 | L39: =IF(K39="","",TODAY()-K39) -> 93 | M39: Operational–Medium | N39: =IF(M39="","",IF(L39="",INDEX($F$92:$F$95,MATCH(M39,$C$92:$C$95,0)),IF(L39<=INDEX($D$92:$D$95,MATCH(M39,$C$92:$C$95,0)),0,IF(L39<=INDEX($E$92:$E$95,MATCH(M39,$C$92:$C$95,0)),INDEX($F$92:$F$95,MATCH(M39,$C$92:$C$95,0)),INDEX($G$92:$G$95,MATCH(M39,$C$92:$C$95,0)))))) -> 0 | O39: =G39+N39 -> 0 | P39: No Review | R39: Public reporting on Avalanche’s finances focuses on the Avalanche Foundation’s token sales, buybacks and plans to raise capital via AVAX treasury vehicles, as well as its negotiated settlement to repurchase AVAX from Terra-related entities. These involve commercial decisions and counterparties’ bankruptcy proceedings, not allegations that Avalanche’s own treasury assets were hacked, lost, or misused, nor litigation accusing the Foundation of treasury mismanagement.
A41: B-N1 | B41: In ≤120 words, summarise the governance model and how decisions are proposed/approved/enforced. | C41: Avalanche governance is focused on protocol and economic parameters rather than full on-chain policymaking. AVAX holders who stake to become validators (or delegate to them) participate in consensus, and governance voting power is effectively stake‑weighted. Any network node can submit governance proposals on specific parameters (for example, staking amounts and durations, minting/issuance rate, and transaction fee levels). These proposals are voted on-chain; if approved by the validator set, the updated parameters are automatically applied by the protocol, enforcing decisions at the network level without separate off-chain execution. | D41: Medium | E41: =0 -> 0 | F41: =IF(D41="High",0,IF(D41="Medium",0.05,IF(D41="Low",0.1,IF(D41="Unknown",0.15,"")))) -> 0.05 | G41: =E41*(1+F41) -> 0 | H41: https://cointelegraph.com/learn/avalanche-avax-ecosystem; https://www.platinumcryptoacademy.com/cryptocurrency-investment/navigating-the-avalanche-avax-ecosystem-a-comprehensive-overview/ | I41: 2023-06-01; 2024-01-15 | J41: 2025-12-12; 2025-12-12 | K41: =IF(I41="","",MAX(IFERROR(DATEVALUE(TRIM(MID(SUBSTITUTE(I41,";",REPT(" ",50)),1,50))),0),IFERROR(DATEVALUE(TRIM(MID(SUBSTITUTE(I41,";",REPT(" ",50)),51,50))),0),IFERROR(DATEVALUE(TRIM(MID(SUBSTITUTE(I41,";",REPT(" ",50)),101,50))),0),IFERROR(DATEVALUE(TRIM(MID(SUBSTITUTE(I41,";",REPT(" ",50)),151,50))),0),IFERROR(DATEVALUE(TRIM(MID(SUBSTITUTE(I41,";",REPT(" ",50)),201,50))),0),IFERROR(DATEVALUE(TRIM(MID(SUBSTITUTE(I41,";",REPT(" ",50)),251,50))),0),IFERROR(DATEVALUE(TRIM(MID(SUBSTITUTE(I41,";",REPT(" ",50)),301,50))),0),IFERROR(DATEVALUE(TRIM(MID(SUBSTITUTE(I41,";",REPT(" ",50)),351,50))),0),IFERROR(DATEVALUE(TRIM(MID(SUBSTITUTE(I41,";",REPT(" ",50)),401,50))),0),IFERROR(DATEVALUE(TRIM(MID(SUBSTITUTE(I41,";",REPT(" ",50)),451,50))),0))) -> 45306 | L41: =IF(K41="","",TODAY()-K41) -> 698 | M41: Background–Slow | N41: =IF(M41="","",IF(L41="",INDEX($F$92:$F$95,MATCH(M41,$C$92:$C$95,0)),IF(L41<=INDEX($D$92:$D$95,MATCH(M41,$C$92:$C$95,0)),0,IF(L41<=INDEX($E$92:$E$95,MATCH(M41,$C$92:$C$95,0)),INDEX($F$92:$F$95,MATCH(M41,$C$92:$C$95,0)),INDEX($G$92:$G$95,MATCH(M41,$C$92:$C$95,0)))))) -> 2 | O41: =G41+N41 -> 2 | P41: No Review | Q41: Informational only; no board trigger. | R41: Sources describe AVAX as enabling token holders/validators to vote on key network parameters (staking, issuance, fees) via on‑chain governance, which then adjusts protocol settings directly. Some details (e.g., exact proposal mechanics) are less clearly specified, so I use Medium confidence.
A42: B-N2 | B42: Is governance evolving toward more decentralisation (e.g., expanding multisig, increasing DAO scope)? Answer Yes / No / Unclear. | C42: Unclear | D42: Medium | E42: =IF(C42="Yes",0,IF(C42="Unclear",10,IF(C42="No",20,""))) -> 10 | F42: =IF(D42="High",0,IF(D42="Medium",0.05,IF(D42="Low",0.1,IF(D42="Unknown",0.15,"")))) -> 0.05 | G42: =E42*(1+F42) -> 10.5 | H42: https://build.avax.network/blog/etna-enhancing-sovereignty-avalanche-l1-networks; https://support.avax.network/en/articles/6235660-staking-faq | I42: 2024-12-02; 2025-10-01 | J42: 2025-12-12; 2025-12-12 | K42: =IF(I42="","",MAX(IFERROR(DATEVALUE(TRIM(MID(SUBSTITUTE(I42,";",REPT(" ",50)),1,50))),0),IFERROR(DATEVALUE(TRIM(MID(SUBSTITUTE(I42,";",REPT(" ",50)),51,50))),0),IFERROR(DATEVALUE(TRIM(MID(SUBSTITUTE(I42,";",REPT(" ",50)),101,50))),0),IFERROR(DATEVALUE(TRIM(MID(SUBSTITUTE(I42,";",REPT(" ",50)),151,50))),0),IFERROR(DATEVALUE(TRIM(MID(SUBSTITUTE(I42,";",REPT(" ",50)),201,50))),0),IFERROR(DATEVALUE(TRIM(MID(SUBSTITUTE(I42,";",REPT(" ",50)),251,50))),0),IFERROR(DATEVALUE(TRIM(MID(SUBSTITUTE(I42,";",REPT(" ",50)),301,50))),0),IFERROR(DATEVALUE(TRIM(MID(SUBSTITUTE(I42,";",REPT(" ",50)),351,50))),0),IFERROR(DATEVALUE(TRIM(MID(SUBSTITUTE(I42,";",REPT(" ",50)),401,50))),0),IFERROR(DATEVALUE(TRIM(MID(SUBSTITUTE(I42,";",REPT(" ",50)),451,50))),0))) -> 45931 | L42: =IF(K42="","",TODAY()-K42) -> 73 | M42: Operational–Medium | N42: =IF(M42="","",IF(L42="",INDEX($F$92:$F$95,MATCH(M42,$C$92:$C$95,0)),IF(L42<=INDEX($D$92:$D$95,MATCH(M42,$C$92:$C$95,0)),0,IF(L42<=INDEX($E$92:$E$95,MATCH(M42,$C$92:$C$95,0)),INDEX($F$92:$F$95,MATCH(M42,$C$92:$C$95,0)),INDEX($G$92:$G$95,MATCH(M42,$C$92:$C$95,0)))))) -> 0 | O42: =G42+N42 -> 10.5 | P42: No Review | Q42: Informational only; no board trigger. | R42: Avalanche network changes are proposed via Avalanche Community Proposals (ACPs) like those bundled in the 2024 Etna upgrade, suggesting some community-driven evolution. However, key protocol parameters (e.g., minimum delegation amount) are still hard‑coded, with Avalanche support stating that the long‑term plan is to make such parameters decided by consensus but that this code “hasn’t been written yet.” Public information does not clearly show a concrete, implemented shift of AVAX governance toward broader on‑chain or DAO-style decentralisation.
B43: C. Token Holder Rights (Regulatory Characteristics) | K43: =IF(I43="","",MAX(IFERROR(DATEVALUE(TRIM(MID(SUBSTITUTE(I43,";",REPT(" ",50)),1,50))),0),IFERROR(DATEVALUE(TRIM(MID(SUBSTITUTE(I43,";",REPT(" ",50)),51,50))),0),IFERROR(DATEVALUE(TRIM(MID(SUBSTITUTE(I43,";",REPT(" ",50)),101,50))),0),IFERROR(DATEVALUE(TRIM(MID(SUBSTITUTE(I43,";",REPT(" ",50)),151,50))),0),IFERROR(DATEVALUE(TRIM(MID(SUBSTITUTE(I43,";",REPT(" ",50)),201,50))),0),IFERROR(DATEVALUE(TRIM(MID(SUBSTITUTE(I43,";",REPT(" ",50)),251,50))),0),IFERROR(DATEVALUE(TRIM(MID(SUBSTITUTE(I43,";",REPT(" ",50)),301,50))),0),IFERROR(DATEVALUE(TRIM(MID(SUBSTITUTE(I43,";",REPT(" ",50)),351,50))),0),IFERROR(DATEVALUE(TRIM(MID(SUBSTITUTE(I43,";",REPT(" ",50)),401,50))),0),IFERROR(DATEVALUE(TRIM(MID(SUBSTITUTE(I43,";",REPT(" ",50)),451,50))),0))) | N43: =IF(M43="","",IF(L43="",INDEX($F$92:$F$95,MATCH(M43,$C$92:$C$95,0)),IF(L43<=INDEX($D$92:$D$95,MATCH(M43,$C$92:$C$95,0)),0,IF(L43<=INDEX($E$92:$E$95,MATCH(M43,$C$92:$C$95,0)),INDEX($F$92:$F$95,MATCH(M43,$C$92:$C$95,0)),INDEX($G$92:$G$95,MATCH(M43,$C$92:$C$95,0))))))
A45: C1 | B45: Does the token provide any governance or voting rights? Answer one: Yes / No / Limited / Unclear. | C45: Yes | D45: High | E45: =IF(C45="No",0,IF(C45="Limited",10,IF(C45="Unclear",10,IF(C45="Yes",10,"")))) -> 10 | F45: =IF(D45="High",0,IF(D45="Medium",0.05,IF(D45="Low",0.1,IF(D45="Unknown",0.15,"")))) -> 0 | G45: =E45*(1+F45) -> 10 | H45: https://docs.avax.network/learn/avalanche/avax-token; https://docs.avax.network/validators/overview | I45: 2023-08-01; 2023-06-01 | J45: 2025-12-12; 2025-12-12 | K45: =IF(I45="","",MAX(IFERROR(DATEVALUE(TRIM(MID(SUBSTITUTE(I45,";",REPT(" ",50)),1,50))),0),IFERROR(DATEVALUE(TRIM(MID(SUBSTITUTE(I45,";",REPT(" ",50)),51,50))),0),IFERROR(DATEVALUE(TRIM(MID(SUBSTITUTE(I45,";",REPT(" ",50)),101,50))),0),IFERROR(DATEVALUE(TRIM(MID(SUBSTITUTE(I45,";",REPT(" ",50)),151,50))),0),IFERROR(DATEVALUE(TRIM(MID(SUBSTITUTE(I45,";",REPT(" ",50)),201,50))),0),IFERROR(DATEVALUE(TRIM(MID(SUBSTITUTE(I45,";",REPT(" ",50)),251,50))),0),IFERROR(DATEVALUE(TRIM(MID(SUBSTITUTE(I45,";",REPT(" ",50)),301,50))),0),IFERROR(DATEVALUE(TRIM(MID(SUBSTITUTE(I45,";",REPT(" ",50)),351,50))),0),IFERROR(DATEVALUE(TRIM(MID(SUBSTITUTE(I45,";",REPT(" ",50)),401,50))),0),IFERROR(DATEVALUE(TRIM(MID(SUBSTITUTE(I45,";",REPT(" ",50)),451,50))),0))) -> 45139 | L45: =IF(K45="","",TODAY()-K45) -> 865 | M45: Evergreen–No Penalty | N45: =IF(M45="","",IF(L45="",INDEX($F$92:$F$95,MATCH(M45,$C$92:$C$95,0)),IF(L45<=INDEX($D$92:$D$95,MATCH(M45,$C$92:$C$95,0)),0,IF(L45<=INDEX($E$92:$E$95,MATCH(M45,$C$92:$C$95,0)),INDEX($F$92:$F$95,MATCH(M45,$C$92:$C$95,0)),INDEX($G$92:$G$95,MATCH(M45,$C$92:$C$95,0)))))) -> 0 | O45: =G45+N45 -> 10 | P45: No Review | R45: Avalanche is a PoS-based network where AVAX is the native token. Staking AVAX is required to run a validator or delegate, and validators participate in network governance, including parameter and upgrade decisions. Multiple sources describe AVAX as a governance token used for voting and protocol decision-making, so the token clearly provides governance/voting rights, at least for stakers/validators.
A46: C2 | B46: Do token holders receive any share of fees, revenue, interest, or yields generated by the project? Answer one: Yes / No / Indirect / Unclear. | C46: Yes | D46: High | E46: =IF(C46="No",0,IF(C46="Indirect",10,IF(C46="Unclear",10,IF(C46="Yes",20,"")))) -> 20 | F46: =IF(D46="High",0,IF(D46="Medium",0.05,IF(D46="Low",0.1,IF(D46="Unknown",0.15,"")))) -> 0 | G46: =E46*(1+F46) -> 20 | H46: https://support.avax.network/en/articles/6912428-tokenomics-faq; https://build.avax.network/docs/primary-network/validate/how-to-stake | I46: 2024-10-01; 2024-10-01 | J46: 2025-12-12; 2025-12-12 | K46: =IF(I46="","",MAX(IFERROR(DATEVALUE(TRIM(MID(SUBSTITUTE(I46,";",REPT(" ",50)),1,50))),0),IFERROR(DATEVALUE(TRIM(MID(SUBSTITUTE(I46,";",REPT(" ",50)),51,50))),0),IFERROR(DATEVALUE(TRIM(MID(SUBSTITUTE(I46,";",REPT(" ",50)),101,50))),0),IFERROR(DATEVALUE(TRIM(MID(SUBSTITUTE(I46,";",REPT(" ",50)),151,50))),0),IFERROR(DATEVALUE(TRIM(MID(SUBSTITUTE(I46,";",REPT(" ",50)),201,50))),0),IFERROR(DATEVALUE(TRIM(MID(SUBSTITUTE(I46,";",REPT(" ",50)),251,50))),0),IFERROR(DATEVALUE(TRIM(MID(SUBSTITUTE(I46,";",REPT(" ",50)),301,50))),0),IFERROR(DATEVALUE(TRIM(MID(SUBSTITUTE(I46,";",REPT(" ",50)),351,50))),0),IFERROR(DATEVALUE(TRIM(MID(SUBSTITUTE(I46,";",REPT(" ",50)),401,50))),0),IFERROR(DATEVALUE(TRIM(MID(SUBSTITUTE(I46,";",REPT(" ",50)),451,50))),0))) -> 45566 | L46: =IF(K46="","",TODAY()-K46) -> 438 | M46: Evergreen–No Penalty | N46: =IF(M46="","",IF(L46="",INDEX($F$92:$F$95,MATCH(M46,$C$92:$C$95,0)),IF(L46<=INDEX($D$92:$D$95,MATCH(M46,$C$92:$C$95,0)),0,IF(L46<=INDEX($E$92:$E$95,MATCH(M46,$C$92:$C$95,0)),INDEX($F$92:$F$95,MATCH(M46,$C$92:$C$95,0)),INDEX($G$92:$G$95,MATCH(M46,$C$92:$C$95,0)))))) -> 0 | O46: =G46+N46 -> 20 | P46: =IF(C46="Yes","Review Required","No Review") -> Review Required | Q46: Escalate only if token confers direct revenue/fee/interest share (Answer = Yes). | R46: AVAX token holders who stake as validators or delegators receive staking rewards in AVAX for helping secure the network, i.e., they earn protocol yields on their stake. Avalanche docs describe validator and delegator staking rewards paid in AVAX. At the same time, network transaction fees are burned rather than distributed, so rewards come from token minting/inflation rather than fee revenue sharing.
A47: C3 | B47: Are token holders entitled to residual claims on treasury assets or protocol revenue? Answer one: Yes / No / Unclear. | C47: No | D47: Medium | E47: =IF(C47="No",0,IF(C47="Unclear",10,IF(C47="Yes",20,""))) -> 0 | F47: =IF(D47="High",0,IF(D47="Medium",0.05,IF(D47="Low",0.1,IF(D47="Unknown",0.15,"")))) -> 0.05 | G47: =E47*(1+F47) -> 0 | H47: https://docs.avax.network/learn/token; https://www.avalabs.org/whitepapers | I47: 2023-08-01; 2020-03-01 | J47: 2025-12-12; 2025-12-12 | K47: =IF(I47="","",MAX(IFERROR(DATEVALUE(TRIM(MID(SUBSTITUTE(I47,";",REPT(" ",50)),1,50))),0),IFERROR(DATEVALUE(TRIM(MID(SUBSTITUTE(I47,";",REPT(" ",50)),51,50))),0),IFERROR(DATEVALUE(TRIM(MID(SUBSTITUTE(I47,";",REPT(" ",50)),101,50))),0),IFERROR(DATEVALUE(TRIM(MID(SUBSTITUTE(I47,";",REPT(" ",50)),151,50))),0),IFERROR(DATEVALUE(TRIM(MID(SUBSTITUTE(I47,";",REPT(" ",50)),201,50))),0),IFERROR(DATEVALUE(TRIM(MID(SUBSTITUTE(I47,";",REPT(" ",50)),251,50))),0),IFERROR(DATEVALUE(TRIM(MID(SUBSTITUTE(I47,";",REPT(" ",50)),301,50))),0),IFERROR(DATEVALUE(TRIM(MID(SUBSTITUTE(I47,";",REPT(" ",50)),351,50))),0),IFERROR(DATEVALUE(TRIM(MID(SUBSTITUTE(I47,";",REPT(" ",50)),401,50))),0),IFERROR(DATEVALUE(TRIM(MID(SUBSTITUTE(I47,";",REPT(" ",50)),451,50))),0))) -> 45139 | L47: =IF(K47="","",TODAY()-K47) -> 865 | M47: Evergreen–No Penalty | N47: =IF(M47="","",IF(L47="",INDEX($F$92:$F$95,MATCH(M47,$C$92:$C$95,0)),IF(L47<=INDEX($D$92:$D$95,MATCH(M47,$C$92:$C$95,0)),0,IF(L47<=INDEX($E$92:$E$95,MATCH(M47,$C$92:$C$95,0)),INDEX($F$92:$F$95,MATCH(M47,$C$92:$C$95,0)),INDEX($G$92:$G$95,MATCH(M47,$C$92:$C$95,0)))))) -> 0 | O47: =G47+N47 -> 0 | P47: =IF(C47="Yes","Review","No Review") -> No Review | Q47: Escalate only if token confers residual asset claims (Answer = Yes). | R47: Avalanche/AVAX is primarily a utility and staking token used for network security, fees, and governance. Publicly available documentation and third‑party research describe AVAX holders as earning staking rewards for validating or delegating, but do not indicate any formal, enforceable equity‑like residual claim on the protocol’s treasury assets or broader network revenues. In absence of explicit rights language, token holders should not be assumed to have such residual claims.
A48: C4 | B48: Is the token's value dependent on the managerial or entrepreneurial efforts of a core team or foundation? Answer one: High / Moderate / Low. | C48: High | D48: Medium | E48: =IF(C48="Low",0,IF(C48="Moderate",10,IF(C48="High",20,""))) -> 20 | F48: =IF(D48="High",0,IF(D48="Medium",0.05,IF(D48="Low",0.1,IF(D48="Unknown",0.15,"")))) -> 0.05 | G48: =E48*(1+F48) -> 21 | H48: https://docs.avax.network/overview/getting-started/avalanche-overview; https://docs.avax.network/validators | I48: 2023-08-01; 2023-06-01 | J48: 2025-12-12; 2025-12-12 | K48: =IF(I48="","",MAX(IFERROR(DATEVALUE(TRIM(MID(SUBSTITUTE(I48,";",REPT(" ",50)),1,50))),0),IFERROR(DATEVALUE(TRIM(MID(SUBSTITUTE(I48,";",REPT(" ",50)),51,50))),0),IFERROR(DATEVALUE(TRIM(MID(SUBSTITUTE(I48,";",REPT(" ",50)),101,50))),0),IFERROR(DATEVALUE(TRIM(MID(SUBSTITUTE(I48,";",REPT(" ",50)),151,50))),0),IFERROR(DATEVALUE(TRIM(MID(SUBSTITUTE(I48,";",REPT(" ",50)),201,50))),0),IFERROR(DATEVALUE(TRIM(MID(SUBSTITUTE(I48,";",REPT(" ",50)),251,50))),0),IFERROR(DATEVALUE(TRIM(MID(SUBSTITUTE(I48,";",REPT(" ",50)),301,50))),0),IFERROR(DATEVALUE(TRIM(MID(SUBSTITUTE(I48,";",REPT(" ",50)),351,50))),0),IFERROR(DATEVALUE(TRIM(MID(SUBSTITUTE(I48,";",REPT(" ",50)),401,50))),0),IFERROR(DATEVALUE(TRIM(MID(SUBSTITUTE(I48,";",REPT(" ",50)),451,50))),0))) -> 45139 | L48: =IF(K48="","",TODAY()-K48) -> 865 | M48: Evergreen–No Penalty | N48: =IF(M48="","",IF(L48="",INDEX($F$92:$F$95,MATCH(M48,$C$92:$C$95,0)),IF(L48<=INDEX($D$92:$D$95,MATCH(M48,$C$92:$C$95,0)),0,IF(L48<=INDEX($E$92:$E$95,MATCH(M48,$C$92:$C$95,0)),INDEX($F$92:$F$95,MATCH(M48,$C$92:$C$95,0)),INDEX($G$92:$G$95,MATCH(M48,$C$92:$C$95,0)))))) -> 0 | O48: =G48+N48 -> 21 | P48: No Review | R48: AVAX’s value is materially linked to the Avalanche core team and Ava Labs: they design and upgrade the consensus, manage the subnet framework, and drive key ecosystem, DeFi, and institutional partnerships. Governance, staking economics, and major roadmap execution remain closely associated with this core group, so market perception and token value are still highly dependent on their managerial and entrepreneurial efforts.
A49: C5 | B49: Are token holders relying on future network growth for token appreciation? Answer one: Yes / No / Partial. | C49: Yes | D49: High | E49: =IF(C49="No",0,IF(C49="Partial",10,IF(C49="Yes",10,""))) -> 10 | F49: =IF(D49="High",0,IF(D49="Medium",0.05,IF(D49="Low",0.1,IF(D49="Unknown",0.15,"")))) -> 0 | G49: =E49*(1+F49) -> 10 | H49: https://docs.avax.network/learn/avalanche/avax-token; https://docs.avax.network/learn/platform-overview/fees | I49: 2023-06-01; 2023-06-01 | J49: 2025-12-12; 2025-12-12 | K49: =IF(I49="","",MAX(IFERROR(DATEVALUE(TRIM(MID(SUBSTITUTE(I49,";",REPT(" ",50)),1,50))),0),IFERROR(DATEVALUE(TRIM(MID(SUBSTITUTE(I49,";",REPT(" ",50)),51,50))),0),IFERROR(DATEVALUE(TRIM(MID(SUBSTITUTE(I49,";",REPT(" ",50)),101,50))),0),IFERROR(DATEVALUE(TRIM(MID(SUBSTITUTE(I49,";",REPT(" ",50)),151,50))),0),IFERROR(DATEVALUE(TRIM(MID(SUBSTITUTE(I49,";",REPT(" ",50)),201,50))),0),IFERROR(DATEVALUE(TRIM(MID(SUBSTITUTE(I49,";",REPT(" ",50)),251,50))),0),IFERROR(DATEVALUE(TRIM(MID(SUBSTITUTE(I49,";",REPT(" ",50)),301,50))),0),IFERROR(DATEVALUE(TRIM(MID(SUBSTITUTE(I49,";",REPT(" ",50)),351,50))),0),IFERROR(DATEVALUE(TRIM(MID(SUBSTITUTE(I49,";",REPT(" ",50)),401,50))),0),IFERROR(DATEVALUE(TRIM(MID(SUBSTITUTE(I49,";",REPT(" ",50)),451,50))),0))) -> 45078 | L49: =IF(K49="","",TODAY()-K49) -> 926 | M49: Evergreen–No Penalty | N49: =IF(M49="","",IF(L49="",INDEX($F$92:$F$95,MATCH(M49,$C$92:$C$95,0)),IF(L49<=INDEX($D$92:$D$95,MATCH(M49,$C$92:$C$95,0)),0,IF(L49<=INDEX($E$92:$E$95,MATCH(M49,$C$92:$C$95,0)),INDEX($F$92:$F$95,MATCH(M49,$C$92:$C$95,0)),INDEX($G$92:$G$95,MATCH(M49,$C$92:$C$95,0)))))) -> 0 | O49: =G49+N49 -> 10 | P49: No Review | R49: AVAX is used for staking, paying fees, and securing the Avalanche network. Its supply is capped and all fees are burned, so valuation arguments commonly hinge on future transaction volume, protocol adoption, and demand for staking. This means token holders are materially reliant on expectations of future network growth for potential token appreciation, even though AVAX also has current utility.
A50: C6 | B50: Are token holders financially or contractually disadvantaged versus insiders or early backers (e.g., preferences, seniority, redemption rights)? Answer one: Yes / No / Unclear. | C50: Unclear | D50: Low | E50: =IF(C50="No",0,IF(C50="Unclear",10,IF(C50="Yes",20,""))) -> 10 | F50: =IF(D50="High",0,IF(D50="Medium",0.05,IF(D50="Low",0.1,IF(D50="Unknown",0.15,"")))) -> 0.1 | G50: =E50*(1+F50) -> 11 | H50: https://support.avax.network/en/articles/4065301-avax-token-distribution; https://messari.io/asset/avalanche/profile | I50: 2020-07-01; 2024-05-01 | J50: 2025-12-12; 2025-12-12 | K50: =IF(I50="","",MAX(IFERROR(DATEVALUE(TRIM(MID(SUBSTITUTE(I50,";",REPT(" ",50)),1,50))),0),IFERROR(DATEVALUE(TRIM(MID(SUBSTITUTE(I50,";",REPT(" ",50)),51,50))),0),IFERROR(DATEVALUE(TRIM(MID(SUBSTITUTE(I50,";",REPT(" ",50)),101,50))),0),IFERROR(DATEVALUE(TRIM(MID(SUBSTITUTE(I50,";",REPT(" ",50)),151,50))),0),IFERROR(DATEVALUE(TRIM(MID(SUBSTITUTE(I50,";",REPT(" ",50)),201,50))),0),IFERROR(DATEVALUE(TRIM(MID(SUBSTITUTE(I50,";",REPT(" ",50)),251,50))),0),IFERROR(DATEVALUE(TRIM(MID(SUBSTITUTE(I50,";",REPT(" ",50)),301,50))),0),IFERROR(DATEVALUE(TRIM(MID(SUBSTITUTE(I50,";",REPT(" ",50)),351,50))),0),IFERROR(DATEVALUE(TRIM(MID(SUBSTITUTE(I50,";",REPT(" ",50)),401,50))),0),IFERROR(DATEVALUE(TRIM(MID(SUBSTITUTE(I50,";",REPT(" ",50)),451,50))),0))) -> 45413 | L50: =IF(K50="","",TODAY()-K50) -> 591 | M50: Evergreen–No Penalty | N50: =IF(M50="","",IF(L50="",INDEX($F$92:$F$95,MATCH(M50,$C$92:$C$95,0)),IF(L50<=INDEX($D$92:$D$95,MATCH(M50,$C$92:$C$95,0)),0,IF(L50<=INDEX($E$92:$E$95,MATCH(M50,$C$92:$C$95,0)),INDEX($F$92:$F$95,MATCH(M50,$C$92:$C$95,0)),INDEX($G$92:$G$95,MATCH(M50,$C$92:$C$95,0)))))) -> 0 | O50: =G50+N50 -> 11 | P50: No Review | R50: Public materials for AVAX focus on token supply, allocations, and staking; they describe vesting schedules and allocations for private sale/seed investors and the Avalanche Foundation, but do not clearly set out any explicit seniority, liquidation preference, or special redemption rights that would contractually disadvantage public token holders. Because detailed investor-side agreements and side letters are not public, it is not possible to rule out preferential financial or contractual terms for insiders or early backers with high confidence.
A51: C7 | B51: Provide a ≤120-word justification explaining why this token is or is not securities-like under UK perimeter, citing rights, revenue share, reliance on managerial efforts, and expectations. (Narrative only). | C51: AVAX primarily functions as a native utility/token for gas, staking and network security, with fees burned rather than distributed as protocol revenue, and no formal claim on platform profits or equity-like rights.citeturn0search0turn0search3 Staking rewards are minted protocol‑level inflation, contingent on validator performance, rather than revenue share from a common enterprise.citeturn0search2turn0search3 Governance influence is tied to stake but does not currently grant enforceable rights to management or cash flows.citeturn0search9 Economically, some holders may nevertheless expect price appreciation based on Avalanche/Ava Labs’ ongoing development, so AVAX can exhibit securities‑like features in certain promotional or staking contexts, but its core design is more utility‑/payments‑oriented than profit‑right‑bearing under the UK perimeter. | D51: Medium | E51: =0 -> 0 | F51: =IF(D51="High",0,IF(D51="Medium",0.05,IF(D51="Low",0.1,IF(D51="Unknown",0.15,"")))) -> 0.05 | G51: =E51*(1+F51) -> 0 | H51: https://www.avax.network/about/tokens; https://build.avax.network/docs/primary-network/validate/how-to-stake; https://support.avax.network/en/articles/6912428-tokenomics-faq | I51: 2024-01-01; 2024-06-01; 2025-10-01 | J51: 2025-12-12; 2025-12-12; 2025-12-12 | K51: =IF(I51="","",MAX(IFERROR(DATEVALUE(TRIM(MID(SUBSTITUTE(I51,";",REPT(" ",50)),1,50))),0),IFERROR(DATEVALUE(TRIM(MID(SUBSTITUTE(I51,";",REPT(" ",50)),51,50))),0),IFERROR(DATEVALUE(TRIM(MID(SUBSTITUTE(I51,";",REPT(" ",50)),101,50))),0),IFERROR(DATEVALUE(TRIM(MID(SUBSTITUTE(I51,";",REPT(" ",50)),151,50))),0),IFERROR(DATEVALUE(TRIM(MID(SUBSTITUTE(I51,";",REPT(" ",50)),201,50))),0),IFERROR(DATEVALUE(TRIM(MID(SUBSTITUTE(I51,";",REPT(" ",50)),251,50))),0),IFERROR(DATEVALUE(TRIM(MID(SUBSTITUTE(I51,";",REPT(" ",50)),301,50))),0),IFERROR(DATEVALUE(TRIM(MID(SUBSTITUTE(I51,";",REPT(" ",50)),351,50))),0),IFERROR(DATEVALUE(TRIM(MID(SUBSTITUTE(I51,";",REPT(" ",50)),401,50))),0),IFERROR(DATEVALUE(TRIM(MID(SUBSTITUTE(I51,";",REPT(" ",50)),451,50))),0))) -> 45931 | L51: =IF(K51="","",TODAY()-K51) -> 73 | M51: Evergreen–No Penalty | N51: =IF(M51="","",IF(L51="",INDEX($F$92:$F$95,MATCH(M51,$C$92:$C$95,0)),IF(L51<=INDEX($D$92:$D$95,MATCH(M51,$C$92:$C$95,0)),0,IF(L51<=INDEX($E$92:$E$95,MATCH(M51,$C$92:$C$95,0)),INDEX($F$92:$F$95,MATCH(M51,$C$92:$C$95,0)),INDEX($G$92:$G$95,MATCH(M51,$C$92:$C$95,0)))))) -> 0 | O51: =G51+N51 -> 0 | P51: No Review | Q51: Informational only; no board trigger. | R51: Answer draws on primary docs describing AVAX’s role, fee burn, and staking rewards, showing no direct profit/share rights but some profit-expectation features via staking and development. UK characterisation is fact-specific, so assessment is medium confidence.
B52: D. Whitepaper & Disclosure Quality (Accuracy, Transparency, Fairness) | K52: =IF(I52="","",MAX(IFERROR(DATEVALUE(TRIM(MID(SUBSTITUTE(I52,";",REPT(" ",50)),1,50))),0),IFERROR(DATEVALUE(TRIM(MID(SUBSTITUTE(I52,";",REPT(" ",50)),51,50))),0),IFERROR(DATEVALUE(TRIM(MID(SUBSTITUTE(I52,";",REPT(" ",50)),101,50))),0),IFERROR(DATEVALUE(TRIM(MID(SUBSTITUTE(I52,";",REPT(" ",50)),151,50))),0),IFERROR(DATEVALUE(TRIM(MID(SUBSTITUTE(I52,";",REPT(" ",50)),201,50))),0),IFERROR(DATEVALUE(TRIM(MID(SUBSTITUTE(I52,";",REPT(" ",50)),251,50))),0),IFERROR(DATEVALUE(TRIM(MID(SUBSTITUTE(I52,";",REPT(" ",50)),301,50))),0),IFERROR(DATEVALUE(TRIM(MID(SUBSTITUTE(I52,";",REPT(" ",50)),351,50))),0),IFERROR(DATEVALUE(TRIM(MID(SUBSTITUTE(I52,";",REPT(" ",50)),401,50))),0),IFERROR(DATEVALUE(TRIM(MID(SUBSTITUTE(I52,";",REPT(" ",50)),451,50))),0))) | N52: =IF(M52="","",IF(L52="",INDEX($F$92:$F$95,MATCH(M52,$C$92:$C$95,0)),IF(L52<=INDEX($D$92:$D$95,MATCH(M52,$C$92:$C$95,0)),0,IF(L52<=INDEX($E$92:$E$95,MATCH(M52,$C$92:$C$95,0)),INDEX($F$92:$F$95,MATCH(M52,$C$92:$C$95,0)),INDEX($G$92:$G$95,MATCH(M52,$C$92:$C$95,0))))))
A54: D1 | B54: Does the project have a current whitepaper or technical documentation available from an official source? (Yes / No / Outdated / Unclear) | C54: Yes | D54: High | E54: =IF(C54="Yes",0,IF(C54="Outdated",10,IF(C54="Unclear",10,IF(C54="No",20,"")))) -> 0 | F54: =IF(D54="High",0,IF(D54="Medium",0.05,IF(D54="Low",0.1,IF(D54="Unknown",0.15,"")))) -> 0 | G54: =E54*(1+F54) -> 0 | H54: https://build.avax.network/docs; https://www.custonomy.io/supported-tokens/avalanche/avax-on-avalanche-c-chain; https://build.avax.network/docs/primary-network/avalanche-consensus | I54: 2024-11-20; 2024-11-15; 2024-11-25 | J54: 2025-12-12; 2025-12-12; 2025-12-12 | K54: =IF(I54="","",MAX(IFERROR(DATEVALUE(TRIM(MID(SUBSTITUTE(I54,";",REPT(" ",50)),1,50))),0),IFERROR(DATEVALUE(TRIM(MID(SUBSTITUTE(I54,";",REPT(" ",50)),51,50))),0),IFERROR(DATEVALUE(TRIM(MID(SUBSTITUTE(I54,";",REPT(" ",50)),101,50))),0),IFERROR(DATEVALUE(TRIM(MID(SUBSTITUTE(I54,";",REPT(" ",50)),151,50))),0),IFERROR(DATEVALUE(TRIM(MID(SUBSTITUTE(I54,";",REPT(" ",50)),201,50))),0),IFERROR(DATEVALUE(TRIM(MID(SUBSTITUTE(I54,";",REPT(" ",50)),251,50))),0),IFERROR(DATEVALUE(TRIM(MID(SUBSTITUTE(I54,";",REPT(" ",50)),301,50))),0),IFERROR(DATEVALUE(TRIM(MID(SUBSTITUTE(I54,";",REPT(" ",50)),351,50))),0),IFERROR(DATEVALUE(TRIM(MID(SUBSTITUTE(I54,";",REPT(" ",50)),401,50))),0),IFERROR(DATEVALUE(TRIM(MID(SUBSTITUTE(I54,";",REPT(" ",50)),451,50))),0))) -> 45621 | L54: =IF(K54="","",TODAY()-K54) -> 383 | M54: Background–Slow | N54: =IF(M54="","",IF(L54="",INDEX($F$92:$F$95,MATCH(M54,$C$92:$C$95,0)),IF(L54<=INDEX($D$92:$D$95,MATCH(M54,$C$92:$C$95,0)),0,IF(L54<=INDEX($E$92:$E$95,MATCH(M54,$C$92:$C$95,0)),INDEX($F$92:$F$95,MATCH(M54,$C$92:$C$95,0)),INDEX($G$92:$G$95,MATCH(M54,$C$92:$C$95,0)))))) -> 2 | O54: =G54+N54 -> 2 | P54: =IF(C54="No","Review","No Review") -> No Review | Q54: Escalate only if no official whitepaper/technical documentation exists (Answer = "No"). | R54: Avalanche maintains official technical documentation via the Avalanche Builder Hub and related docs site, which provide protocol, consensus, and developer documentation. In addition, Ava Labs hosts a dedicated whitepapers page for Avalanche, linked by multiple reputable sources, indicating current, officially maintained technical papers are available.
A55: D2 | B55: Does the whitepaper clearly state the purpose and function of the token? (Yes / No / Partially) | C55: Yes | D55: High | E55: =IF(C55="Yes",0,IF(C55="Partially",10,IF(C55="No",20,""))) -> 0 | F55: =IF(D55="High",0,IF(D55="Medium",0.05,IF(D55="Low",0.1,IF(D55="Unknown",0.15,"")))) -> 0 | G55: =E55*(1+F55) -> 0 | H55: https://www.avalabs.org/whitepapers; https://news92039.tistory.com/96; https://build.avax.network/docs/primary-network/avax-token | I55: 2023-08-20; 2023-03-01; 2024-06-01 | J55: 2025-12-12; 2025-12-12; 2025-12-12 | K55: =IF(I55="","",MAX(IFERROR(DATEVALUE(TRIM(MID(SUBSTITUTE(I55,";",REPT(" ",50)),1,50))),0),IFERROR(DATEVALUE(TRIM(MID(SUBSTITUTE(I55,";",REPT(" ",50)),51,50))),0),IFERROR(DATEVALUE(TRIM(MID(SUBSTITUTE(I55,";",REPT(" ",50)),101,50))),0),IFERROR(DATEVALUE(TRIM(MID(SUBSTITUTE(I55,";",REPT(" ",50)),151,50))),0),IFERROR(DATEVALUE(TRIM(MID(SUBSTITUTE(I55,";",REPT(" ",50)),201,50))),0),IFERROR(DATEVALUE(TRIM(MID(SUBSTITUTE(I55,";",REPT(" ",50)),251,50))),0),IFERROR(DATEVALUE(TRIM(MID(SUBSTITUTE(I55,";",REPT(" ",50)),301,50))),0),IFERROR(DATEVALUE(TRIM(MID(SUBSTITUTE(I55,";",REPT(" ",50)),351,50))),0),IFERROR(DATEVALUE(TRIM(MID(SUBSTITUTE(I55,";",REPT(" ",50)),401,50))),0),IFERROR(DATEVALUE(TRIM(MID(SUBSTITUTE(I55,";",REPT(" ",50)),451,50))),0))) -> 45444 | L55: =IF(K55="","",TODAY()-K55) -> 560 | M55: Evergreen–No Penalty | N55: =IF(M55="","",IF(L55="",INDEX($F$92:$F$95,MATCH(M55,$C$92:$C$95,0)),IF(L55<=INDEX($D$92:$D$95,MATCH(M55,$C$92:$C$95,0)),0,IF(L55<=INDEX($E$92:$E$95,MATCH(M55,$C$92:$C$95,0)),INDEX($F$92:$F$95,MATCH(M55,$C$92:$C$95,0)),INDEX($G$92:$G$95,MATCH(M55,$C$92:$C$95,0)))))) -> 0 | O55: =G55+N55 -> 0 | P55: No Review | R55: Avalanche has a dedicated token whitepaper, “Avalanche Native Token Dynamics,” which explicitly covers the principles, governance, and token economy of AVAX, i.e., its purpose and functions within the platform. This is in addition to platform documentation describing AVAX’s concrete roles (fees, staking/security, unit of account, and governance). Together, these materials clearly articulate the token’s purpose and functionality.
A56: D3 | B56: Does the whitepaper clearly describe the governance model? (Yes / No / Partially) | C56: Yes | D56: High | E56: =IF(C56="Yes",0,IF(C56="Partially",10,IF(C56="No",20,""))) -> 0 | F56: =IF(D56="High",0,IF(D56="Medium",0.05,IF(D56="Low",0.1,IF(D56="Unknown",0.15,"")))) -> 0 | G56: =E56*(1+F56) -> 0 | H56: https://www.avalabs.org/whitepapers; https://levex.com/en/blog/avalanche-guide; https://www.cryptofal.com/info-hub/what-is-avax-avalanche | I56: 2020-09-23; 2024-09-01; 2024-07-01 | J56: 2025-12-12; 2025-12-12; 2025-12-12 | K56: =IF(I56="","",MAX(IFERROR(DATEVALUE(TRIM(MID(SUBSTITUTE(I56,";",REPT(" ",50)),1,50))),0),IFERROR(DATEVALUE(TRIM(MID(SUBSTITUTE(I56,";",REPT(" ",50)),51,50))),0),IFERROR(DATEVALUE(TRIM(MID(SUBSTITUTE(I56,";",REPT(" ",50)),101,50))),0),IFERROR(DATEVALUE(TRIM(MID(SUBSTITUTE(I56,";",REPT(" ",50)),151,50))),0),IFERROR(DATEVALUE(TRIM(MID(SUBSTITUTE(I56,";",REPT(" ",50)),201,50))),0),IFERROR(DATEVALUE(TRIM(MID(SUBSTITUTE(I56,";",REPT(" ",50)),251,50))),0),IFERROR(DATEVALUE(TRIM(MID(SUBSTITUTE(I56,";",REPT(" ",50)),301,50))),0),IFERROR(DATEVALUE(TRIM(MID(SUBSTITUTE(I56,";",REPT(" ",50)),351,50))),0),IFERROR(DATEVALUE(TRIM(MID(SUBSTITUTE(I56,";",REPT(" ",50)),401,50))),0),IFERROR(DATEVALUE(TRIM(MID(SUBSTITUTE(I56,";",REPT(" ",50)),451,50))),0))) -> 45536 | L56: =IF(K56="","",TODAY()-K56) -> 468 | M56: Evergreen–No Penalty | N56: =IF(M56="","",IF(L56="",INDEX($F$92:$F$95,MATCH(M56,$C$92:$C$95,0)),IF(L56<=INDEX($D$92:$D$95,MATCH(M56,$C$92:$C$95,0)),0,IF(L56<=INDEX($E$92:$E$95,MATCH(M56,$C$92:$C$95,0)),INDEX($F$92:$F$95,MATCH(M56,$C$92:$C$95,0)),INDEX($G$92:$G$95,MATCH(M56,$C$92:$C$95,0)))))) -> 0 | O56: =G56+N56 -> 0 | P56: No Review | R56: Avalanche’s governance model is clearly laid out in its Native Token Dynamics / platform whitepaper, which explains that AVAX holders can vote on key financial and protocol parameters (e.g., staking minimums, minting/issuance rate) and that only a fixed, pre-defined set of parameters is governable, with bounds to keep changes predictable. This indicates a well‑specified on‑chain governance scheme rather than a vague mention of voting rights.
A57: D4 | B57: Does the whitepaper disclose tokenomics, including supply schedule, issuance model, and allocations? (Yes / No / Partial / Unclear) | C57: Yes | D57: High | E57: =IF(C57="Yes",0,IF(C57="Partial",10,IF(C57="Unclear",10,IF(C57="No",20,"")))) -> 0 | F57: =IF(D57="High",0,IF(D57="Medium",0.05,IF(D57="Low",0.1,IF(D57="Unknown",0.15,"")))) -> 0 | G57: =E57*(1+F57) -> 0 | H57: https://support.avax.network/en/articles/6912428-tokenomics-faq; https://build.avax.network/docs/primary-network/avax-token; https://www.reddit.com/r/Avax/comments/15wa6qo | I57: 2023-11-01; 2024-06-01; 2023-08-20 | J57: 2025-12-12; 2025-12-12; 2025-12-12 | K57: =IF(I57="","",MAX(IFERROR(DATEVALUE(TRIM(MID(SUBSTITUTE(I57,";",REPT(" ",50)),1,50))),0),IFERROR(DATEVALUE(TRIM(MID(SUBSTITUTE(I57,";",REPT(" ",50)),51,50))),0),IFERROR(DATEVALUE(TRIM(MID(SUBSTITUTE(I57,";",REPT(" ",50)),101,50))),0),IFERROR(DATEVALUE(TRIM(MID(SUBSTITUTE(I57,";",REPT(" ",50)),151,50))),0),IFERROR(DATEVALUE(TRIM(MID(SUBSTITUTE(I57,";",REPT(" ",50)),201,50))),0),IFERROR(DATEVALUE(TRIM(MID(SUBSTITUTE(I57,";",REPT(" ",50)),251,50))),0),IFERROR(DATEVALUE(TRIM(MID(SUBSTITUTE(I57,";",REPT(" ",50)),301,50))),0),IFERROR(DATEVALUE(TRIM(MID(SUBSTITUTE(I57,";",REPT(" ",50)),351,50))),0),IFERROR(DATEVALUE(TRIM(MID(SUBSTITUTE(I57,";",REPT(" ",50)),401,50))),0),IFERROR(DATEVALUE(TRIM(MID(SUBSTITUTE(I57,";",REPT(" ",50)),451,50))),0))) -> 45444 | L57: =IF(K57="","",TODAY()-K57) -> 560 | M57: Evergreen–No Penalty | N57: =IF(M57="","",IF(L57="",INDEX($F$92:$F$95,MATCH(M57,$C$92:$C$95,0)),IF(L57<=INDEX($D$92:$D$95,MATCH(M57,$C$92:$C$95,0)),0,IF(L57<=INDEX($E$92:$E$95,MATCH(M57,$C$92:$C$95,0)),INDEX($F$92:$F$95,MATCH(M57,$C$92:$C$95,0)),INDEX($G$92:$G$95,MATCH(M57,$C$92:$C$95,0)))))) -> 0 | O57: =G57+N57 -> 0 | P57: =IF(C57="No","Review","No Review") -> No Review | Q57: Escalate only if tokenomics (supply, issuance, allocations) are undisclosed (Answer = "No"). | R57: Avalanche has a dedicated whitepaper titled “Avalanche Native Token ($AVAX) Dynamics” that focuses specifically on AVAX tokenomics. Official support documentation points users to this whitepaper for more detailed information on tokenomics, implying it covers supply cap/schedule, issuance via staking rewards, and allocation mechanics. Other official docs outline these same elements, consistent with comprehensive disclosure in the token-dynamics paper.
A58: D5 | B58: Are risk factors disclosed (e.g., regulatory, governance, market, technical risks)? (Yes / Minimal / Missing / No) | C58: Yes | D58: High | E58: =IF(C58="Yes",0,IF(C58="Minimal",10,IF(C58="Missing",20,IF(C58="No",20,"")))) -> 0 | F58: =IF(D58="High",0,IF(D58="Medium",0.05,IF(D58="Low",0.1,IF(D58="Unknown",0.15,"")))) -> 0 | G58: =E58*(1+F58) -> 0 | H58: https://www.bitget.com/az-AZ/price/avalanche/whitepaper; https://www.thestandard.io/blog/due-diligence-on-avalanche-avax-evaluating-its-position-in-the-blockchain-landscape-2025-outlook-4; https://forvest.io/fortuna-abilities/news-review/avax-2025-review-analysis/ | I58: 2024-10-01; 2025-11-01; 2025-08-01 | J58: 2025-12-12; 2025-12-12; 2025-12-12 | K58: =IF(I58="","",MAX(IFERROR(DATEVALUE(TRIM(MID(SUBSTITUTE(I58,";",REPT(" ",50)),1,50))),0),IFERROR(DATEVALUE(TRIM(MID(SUBSTITUTE(I58,";",REPT(" ",50)),51,50))),0),IFERROR(DATEVALUE(TRIM(MID(SUBSTITUTE(I58,";",REPT(" ",50)),101,50))),0),IFERROR(DATEVALUE(TRIM(MID(SUBSTITUTE(I58,";",REPT(" ",50)),151,50))),0),IFERROR(DATEVALUE(TRIM(MID(SUBSTITUTE(I58,";",REPT(" ",50)),201,50))),0),IFERROR(DATEVALUE(TRIM(MID(SUBSTITUTE(I58,";",REPT(" ",50)),251,50))),0),IFERROR(DATEVALUE(TRIM(MID(SUBSTITUTE(I58,";",REPT(" ",50)),301,50))),0),IFERROR(DATEVALUE(TRIM(MID(SUBSTITUTE(I58,";",REPT(" ",50)),351,50))),0),IFERROR(DATEVALUE(TRIM(MID(SUBSTITUTE(I58,";",REPT(" ",50)),401,50))),0),IFERROR(DATEVALUE(TRIM(MID(SUBSTITUTE(I58,";",REPT(" ",50)),451,50))),0))) -> 45962 | L58: =IF(K58="","",TODAY()-K58) -> 42 | M58: Evergreen–No Penalty | N58: =IF(M58="","",IF(L58="",INDEX($F$92:$F$95,MATCH(M58,$C$92:$C$95,0)),IF(L58<=INDEX($D$92:$D$95,MATCH(M58,$C$92:$C$95,0)),0,IF(L58<=INDEX($E$92:$E$95,MATCH(M58,$C$92:$C$95,0)),INDEX($F$92:$F$95,MATCH(M58,$C$92:$C$95,0)),INDEX($G$92:$G$95,MATCH(M58,$C$92:$C$95,0)))))) -> 0 | O58: =G58+N58 -> 0 | P58: No Review | R58: Avalanche has explicit risk disclosures across technical, governance, economic/market, and regulatory dimensions. The whitepaper-style materials and multiple third‑party analyses describe smart contract and protocol risks, validator centralization, governance challenges, inflationary pressures, market volatility, and evolving regulatory/compliance risk. These constitute clear, multi-faceted disclosure of key risk factors rather than only minimal mentions.
A59: D6 | B59: Does the project provide transparent and verifiable team / foundation identities? (Yes / No / Limited / Unclear) | C59: Yes | D59: High | E59: =IF(C59="Yes",0,IF(C59="Limited",10,IF(C59="Unclear",10,IF(C59="No",20,"")))) -> 0 | F59: =IF(D59="High",0,IF(D59="Medium",0.05,IF(D59="Low",0.1,IF(D59="Unknown",0.15,"")))) -> 0 | G59: =E59*(1+F59) -> 0 | H59: https://en.wikipedia.org/wiki/Avalanche_%28blockchain_platform%29; https://www.avalabs.org; https://businessabc.net/wiki/ava-labs | I59: 2024-10-01; 2025-02-25 | J59: 2025-12-12; 2025-12-12; 2025-12-12 | K59: =IF(I59="","",MAX(IFERROR(DATEVALUE(TRIM(MID(SUBSTITUTE(I59,";",REPT(" ",50)),1,50))),0),IFERROR(DATEVALUE(TRIM(MID(SUBSTITUTE(I59,";",REPT(" ",50)),51,50))),0),IFERROR(DATEVALUE(TRIM(MID(SUBSTITUTE(I59,";",REPT(" ",50)),101,50))),0),IFERROR(DATEVALUE(TRIM(MID(SUBSTITUTE(I59,";",REPT(" ",50)),151,50))),0),IFERROR(DATEVALUE(TRIM(MID(SUBSTITUTE(I59,";",REPT(" ",50)),201,50))),0),IFERROR(DATEVALUE(TRIM(MID(SUBSTITUTE(I59,";",REPT(" ",50)),251,50))),0),IFERROR(DATEVALUE(TRIM(MID(SUBSTITUTE(I59,";",REPT(" ",50)),301,50))),0),IFERROR(DATEVALUE(TRIM(MID(SUBSTITUTE(I59,";",REPT(" ",50)),351,50))),0),IFERROR(DATEVALUE(TRIM(MID(SUBSTITUTE(I59,";",REPT(" ",50)),401,50))),0),IFERROR(DATEVALUE(TRIM(MID(SUBSTITUTE(I59,";",REPT(" ",50)),451,50))),0))) -> 45713 | L59: =IF(K59="","",TODAY()-K59) -> 291 | M59: Evergreen–No Penalty | N59: =IF(M59="","",IF(L59="",INDEX($F$92:$F$95,MATCH(M59,$C$92:$C$95,0)),IF(L59<=INDEX($D$92:$D$95,MATCH(M59,$C$92:$C$95,0)),0,IF(L59<=INDEX($E$92:$E$95,MATCH(M59,$C$92:$C$95,0)),INDEX($F$92:$F$95,MATCH(M59,$C$92:$C$95,0)),INDEX($G$92:$G$95,MATCH(M59,$C$92:$C$95,0)))))) -> 0 | O59: =G59+N59 -> 0 | P59: No Review | R59: Avalanche is developed by Ava Labs, whose core team and leadership are fully doxxed. Public sources clearly state named founders (Emin Gün Sirer, Kevin Sekniqi, Maofan “Ted” Yin) and that Ava Labs is the primary developer, with additional executives and roles listed on corporate and profile sites. These identities are verifiable via multiple independent references, including Wikipedia and company profiles, indicating high transparency.
A60: D7 | B60: Are forward-looking statements clearly separated from factual claims? (Yes / No / Unclear) | C60: Yes | D60: High | E60: =IF(C60="Yes",0,IF(C60="Unclear",10,IF(C60="No",20,""))) -> 0 | F60: =IF(D60="High",0,IF(D60="Medium",0.05,IF(D60="Low",0.1,IF(D60="Unknown",0.15,"")))) -> 0 | G60: =E60*(1+F60) -> 0 | H60: https://www.midasdigitaltimes.com/%EC%95%84%EB%B0%9C%EB%9E%80%EC%B2%B4-%ED%94%8C%EB%9E%AB%ED%8F%BC-%EB%B0%B1%EC%84%9C-avalanche-platform-whitepaper/; https://www.reddit.com/r/Avax/comments/15wa6qo/avalanche_whitepapers/ | I60: 2023-01-01; 2023-08-20 | J60: 2025-12-12; 2025-12-12 | K60: =IF(I60="","",MAX(IFERROR(DATEVALUE(TRIM(MID(SUBSTITUTE(I60,";",REPT(" ",50)),1,50))),0),IFERROR(DATEVALUE(TRIM(MID(SUBSTITUTE(I60,";",REPT(" ",50)),51,50))),0),IFERROR(DATEVALUE(TRIM(MID(SUBSTITUTE(I60,";",REPT(" ",50)),101,50))),0),IFERROR(DATEVALUE(TRIM(MID(SUBSTITUTE(I60,";",REPT(" ",50)),151,50))),0),IFERROR(DATEVALUE(TRIM(MID(SUBSTITUTE(I60,";",REPT(" ",50)),201,50))),0),IFERROR(DATEVALUE(TRIM(MID(SUBSTITUTE(I60,";",REPT(" ",50)),251,50))),0),IFERROR(DATEVALUE(TRIM(MID(SUBSTITUTE(I60,";",REPT(" ",50)),301,50))),0),IFERROR(DATEVALUE(TRIM(MID(SUBSTITUTE(I60,";",REPT(" ",50)),351,50))),0),IFERROR(DATEVALUE(TRIM(MID(SUBSTITUTE(I60,";",REPT(" ",50)),401,50))),0),IFERROR(DATEVALUE(TRIM(MID(SUBSTITUTE(I60,";",REPT(" ",50)),451,50))),0))) -> 45158 | L60: =IF(K60="","",TODAY()-K60) -> 846 | M60: Evergreen–No Penalty | N60: =IF(M60="","",IF(L60="",INDEX($F$92:$F$95,MATCH(M60,$C$92:$C$95,0)),IF(L60<=INDEX($D$92:$D$95,MATCH(M60,$C$92:$C$95,0)),0,IF(L60<=INDEX($E$92:$E$95,MATCH(M60,$C$92:$C$95,0)),INDEX($F$92:$F$95,MATCH(M60,$C$92:$C$95,0)),INDEX($G$92:$G$95,MATCH(M60,$C$92:$C$95,0)))))) -> 0 | O60: =G60+N60 -> 0 | P60: No Review | R60: Avalanche’s core technical documentation explicitly flags and defines “forward‑looking statements” separately from the main architectural and factual description. The Avalanche Platform Whitepaper includes an upfront disclosure that the paper may contain forward‑looking statements and a footnote explaining that these relate to projected performance, future development, and strategy, noting they are not guarantees and may differ from actual outcomes. This shows a clear separation between factual claims and forward‑looking content.
A61: D8 | B61: Provide a ≤120-word summary evaluating whether the whitepaper meets FCA expectations for fair, clear, non-misleading disclosure. (Narrative only). | C61: The Avalanche whitepapers collectively provide relatively clear, detailed explanations of the protocol architecture, consensus and AVAX token dynamics, with transparent supply caps, issuance formulas and validator incentives. However, they are written primarily as technical and economic research documents, not as retail-facing disclosures. They give limited, fragmented treatment of risks (e.g., governance, concentration, operational and regulatory risks) and do not frame token-holder exposures, conflicts of interest or assumptions in a way a typical UK consumer could easily understand. On that basis, they only partially meet FCA expectations for information that is fair, clear and not misleading. | D61: Medium | E61: =0 -> 0 | F61: =IF(D61="High",0,IF(D61="Medium",0.05,IF(D61="Low",0.1,IF(D61="Unknown",0.15,"")))) -> 0.05 | G61: =E61*(1+F61) -> 0 | H61: https://www.avalabs.org/whitepapers; https://build.avax.network/docs/primary-network/avax-token | I61: 2022-09-01; 2024-10-01 | J61: 2025-12-12; 2025-12-12 | K61: =IF(I61="","",MAX(IFERROR(DATEVALUE(TRIM(MID(SUBSTITUTE(I61,";",REPT(" ",50)),1,50))),0),IFERROR(DATEVALUE(TRIM(MID(SUBSTITUTE(I61,";",REPT(" ",50)),51,50))),0),IFERROR(DATEVALUE(TRIM(MID(SUBSTITUTE(I61,";",REPT(" ",50)),101,50))),0),IFERROR(DATEVALUE(TRIM(MID(SUBSTITUTE(I61,";",REPT(" ",50)),151,50))),0),IFERROR(DATEVALUE(TRIM(MID(SUBSTITUTE(I61,";",REPT(" ",50)),201,50))),0),IFERROR(DATEVALUE(TRIM(MID(SUBSTITUTE(I61,";",REPT(" ",50)),251,50))),0),IFERROR(DATEVALUE(TRIM(MID(SUBSTITUTE(I61,";",REPT(" ",50)),301,50))),0),IFERROR(DATEVALUE(TRIM(MID(SUBSTITUTE(I61,";",REPT(" ",50)),351,50))),0),IFERROR(DATEVALUE(TRIM(MID(SUBSTITUTE(I61,";",REPT(" ",50)),401,50))),0),IFERROR(DATEVALUE(TRIM(MID(SUBSTITUTE(I61,";",REPT(" ",50)),451,50))),0))) -> 45566 | L61: =IF(K61="","",TODAY()-K61) -> 438 | M61: Evergreen–No Penalty | N61: =IF(M61="","",IF(L61="",INDEX($F$92:$F$95,MATCH(M61,$C$92:$C$95,0)),IF(L61<=INDEX($D$92:$D$95,MATCH(M61,$C$92:$C$95,0)),0,IF(L61<=INDEX($E$92:$E$95,MATCH(M61,$C$92:$C$95,0)),INDEX($F$92:$F$95,MATCH(M61,$C$92:$C$95,0)),INDEX($G$92:$G$95,MATCH(M61,$C$92:$C$95,0)))))) -> 0 | O61: =G61+N61 -> 0 | P61: No Review | Q61: Informational narrative only; no board trigger. | R61: Assessment based on Avalanche’s platform, consensus and token-economics whitepapers, which are technically transparent but not structured as consumer-focused, risk-balanced disclosures, so alignment with FCA fair/clear/non-misleading expectations is only partial.
B62: E. Economic Model & Distribution | K62: =IF(I62="","",MAX(IFERROR(DATEVALUE(TRIM(MID(SUBSTITUTE(I62,";",REPT(" ",50)),1,50))),0),IFERROR(DATEVALUE(TRIM(MID(SUBSTITUTE(I62,";",REPT(" ",50)),51,50))),0),IFERROR(DATEVALUE(TRIM(MID(SUBSTITUTE(I62,";",REPT(" ",50)),101,50))),0),IFERROR(DATEVALUE(TRIM(MID(SUBSTITUTE(I62,";",REPT(" ",50)),151,50))),0),IFERROR(DATEVALUE(TRIM(MID(SUBSTITUTE(I62,";",REPT(" ",50)),201,50))),0),IFERROR(DATEVALUE(TRIM(MID(SUBSTITUTE(I62,";",REPT(" ",50)),251,50))),0),IFERROR(DATEVALUE(TRIM(MID(SUBSTITUTE(I62,";",REPT(" ",50)),301,50))),0),IFERROR(DATEVALUE(TRIM(MID(SUBSTITUTE(I62,";",REPT(" ",50)),351,50))),0),IFERROR(DATEVALUE(TRIM(MID(SUBSTITUTE(I62,";",REPT(" ",50)),401,50))),0),IFERROR(DATEVALUE(TRIM(MID(SUBSTITUTE(I62,";",REPT(" ",50)),451,50))),0))) | N62: =IF(M62="","",IF(L62="",INDEX($F$92:$F$95,MATCH(M62,$C$92:$C$95,0)),IF(L62<=INDEX($D$92:$D$95,MATCH(M62,$C$92:$C$95,0)),0,IF(L62<=INDEX($E$92:$E$95,MATCH(M62,$C$92:$C$95,0)),INDEX($F$92:$F$95,MATCH(M62,$C$92:$C$95,0)),INDEX($G$92:$G$95,MATCH(M62,$C$92:$C$95,0))))))
A64: E1.1 | B64: Token category for scoring context (choose one): L1, L2, Utility, Governance, LP/AMM, Stablecoin, Meme/Narrative, Other. | C64: L1 | D64: High | E64: 0 | F64: =IF(D64="High",0,IF(D64="Medium",0.05,IF(D64="Low",0.1,IF(D64="Unknown",0.15,"")))) -> 0 | G64: =E64*(1+F64) -> 0 | H64: https://en.wikipedia.org/wiki/Avalanche_(blockchain_platform); https://www.avax.network/about/avalanche-avax | I64: 2024-11-01; 2024-11-20 | J64: 2025-12-12; 2025-12-12 | K64: =IF(I64="","",MAX(IFERROR(DATEVALUE(TRIM(MID(SUBSTITUTE(I64,";",REPT(" ",50)),1,50))),0),IFERROR(DATEVALUE(TRIM(MID(SUBSTITUTE(I64,";",REPT(" ",50)),51,50))),0),IFERROR(DATEVALUE(TRIM(MID(SUBSTITUTE(I64,";",REPT(" ",50)),101,50))),0),IFERROR(DATEVALUE(TRIM(MID(SUBSTITUTE(I64,";",REPT(" ",50)),151,50))),0),IFERROR(DATEVALUE(TRIM(MID(SUBSTITUTE(I64,";",REPT(" ",50)),201,50))),0),IFERROR(DATEVALUE(TRIM(MID(SUBSTITUTE(I64,";",REPT(" ",50)),251,50))),0),IFERROR(DATEVALUE(TRIM(MID(SUBSTITUTE(I64,";",REPT(" ",50)),301,50))),0),IFERROR(DATEVALUE(TRIM(MID(SUBSTITUTE(I64,";",REPT(" ",50)),351,50))),0),IFERROR(DATEVALUE(TRIM(MID(SUBSTITUTE(I64,";",REPT(" ",50)),401,50))),0),IFERROR(DATEVALUE(TRIM(MID(SUBSTITUTE(I64,";",REPT(" ",50)),451,50))),0))) -> 45616 | L64: =IF(K64="","",TODAY()-K64) -> 388 | M64: Evergreen–No Penalty | N64: =IF(M64="","",IF(L64="",INDEX($F$92:$F$95,MATCH(M64,$C$92:$C$95,0)),IF(L64<=INDEX($D$92:$D$95,MATCH(M64,$C$92:$C$95,0)),0,IF(L64<=INDEX($E$92:$E$95,MATCH(M64,$C$92:$C$95,0)),INDEX($F$92:$F$95,MATCH(M64,$C$92:$C$95,0)),INDEX($G$92:$G$95,MATCH(M64,$C$92:$C$95,0)))))) -> 0 | O64: =G64+N64 -> 0 | P64: No Review | Q64: Helper row (no scoring, no trigger). | R64: Avalanche (AVAX) is described in technical and third‑party documentation as a decentralized, open‑source Layer‑1 blockchain platform, with AVAX as its native token securing the primary network and paying fees. It is not primarily framed as an application utility, governance, or LP token, but as the base L1 protocol itself.
A65: E1.2 | B65: What is the token’s total supply model? (Fixed / Capped / Inflationary / Unknown) | C65: Capped | D65: High | E65: =IF(C65="Fixed",0,IF(C65="Capped",0,IF(C65="Inflationary",10,IF(C65="Unknown",20,"")))) -> 0 | F65: =IF(D65="High",0,IF(D65="Medium",0.05,IF(D65="Low",0.1,IF(D65="Unknown",0.15,"")))) -> 0 | G65: =E65*(1+F65) -> 0 | H65: https://docs.avax.network/learn/avalanche/avax-token; https://www.coingecko.com/en/coins/avalanche | I65: 2023-06-01; 2025-11-15 | J65: 2025-12-12; 2025-12-12 | K65: =IF(I65="","",MAX(IFERROR(DATEVALUE(TRIM(MID(SUBSTITUTE(I65,";",REPT(" ",50)),1,50))),0),IFERROR(DATEVALUE(TRIM(MID(SUBSTITUTE(I65,";",REPT(" ",50)),51,50))),0),IFERROR(DATEVALUE(TRIM(MID(SUBSTITUTE(I65,";",REPT(" ",50)),101,50))),0),IFERROR(DATEVALUE(TRIM(MID(SUBSTITUTE(I65,";",REPT(" ",50)),151,50))),0),IFERROR(DATEVALUE(TRIM(MID(SUBSTITUTE(I65,";",REPT(" ",50)),201,50))),0),IFERROR(DATEVALUE(TRIM(MID(SUBSTITUTE(I65,";",REPT(" ",50)),251,50))),0),IFERROR(DATEVALUE(TRIM(MID(SUBSTITUTE(I65,";",REPT(" ",50)),301,50))),0),IFERROR(DATEVALUE(TRIM(MID(SUBSTITUTE(I65,";",REPT(" ",50)),351,50))),0),IFERROR(DATEVALUE(TRIM(MID(SUBSTITUTE(I65,";",REPT(" ",50)),401,50))),0),IFERROR(DATEVALUE(TRIM(MID(SUBSTITUTE(I65,";",REPT(" ",50)),451,50))),0))) -> 45976 | L65: =IF(K65="","",TODAY()-K65) -> 28 | M65: Evergreen–No Penalty | N65: =IF(M65="","",IF(L65="",INDEX($F$92:$F$95,MATCH(M65,$C$92:$C$95,0)),IF(L65<=INDEX($D$92:$D$95,MATCH(M65,$C$92:$C$95,0)),0,IF(L65<=INDEX($E$92:$E$95,MATCH(M65,$C$92:$C$95,0)),INDEX($F$92:$F$95,MATCH(M65,$C$92:$C$95,0)),INDEX($G$92:$G$95,MATCH(M65,$C$92:$C$95,0)))))) -> 0 | O65: =G65+N65 -> 0 | P65: No Review | R65: Avalanche’s native token AVAX has a capped maximum supply (720 million AVAX). New tokens are minted as staking rewards and offset by fee-burning, but issuance cannot exceed this fixed cap, so the supply model is best categorized as capped rather than open-ended inflationary.
A66: E1.3 | B66: Is the issuance schedule transparent and documented? (Yes / Partial / No) | C66: Yes | D66: High | E66: =IF(C66="Yes",0,IF(C66="Partial",10,IF(C66="No",20,""))) -> 0 | F66: =IF(D66="High",0,IF(D66="Medium",0.05,IF(D66="Low",0.1,IF(D66="Unknown",0.15,"")))) -> 0 | G66: =E66*(1+F66) -> 0 | H66: https://www.avax.network/about/tokens; https://messari.io/report/state-of-avalanche-q1-2025; https://www.mexc.fm/en-TR/price/AVAX/tokenomics | I66: 2024-06-01; 2025-05-01; 2025-11-15 | J66: 2025-12-12; 2025-12-12; 2025-12-12 | K66: =IF(I66="","",MAX(IFERROR(DATEVALUE(TRIM(MID(SUBSTITUTE(I66,";",REPT(" ",50)),1,50))),0),IFERROR(DATEVALUE(TRIM(MID(SUBSTITUTE(I66,";",REPT(" ",50)),51,50))),0),IFERROR(DATEVALUE(TRIM(MID(SUBSTITUTE(I66,";",REPT(" ",50)),101,50))),0),IFERROR(DATEVALUE(TRIM(MID(SUBSTITUTE(I66,";",REPT(" ",50)),151,50))),0),IFERROR(DATEVALUE(TRIM(MID(SUBSTITUTE(I66,";",REPT(" ",50)),201,50))),0),IFERROR(DATEVALUE(TRIM(MID(SUBSTITUTE(I66,";",REPT(" ",50)),251,50))),0),IFERROR(DATEVALUE(TRIM(MID(SUBSTITUTE(I66,";",REPT(" ",50)),301,50))),0),IFERROR(DATEVALUE(TRIM(MID(SUBSTITUTE(I66,";",REPT(" ",50)),351,50))),0),IFERROR(DATEVALUE(TRIM(MID(SUBSTITUTE(I66,";",REPT(" ",50)),401,50))),0),IFERROR(DATEVALUE(TRIM(MID(SUBSTITUTE(I66,";",REPT(" ",50)),451,50))),0))) -> 45976 | L66: =IF(K66="","",TODAY()-K66) -> 28 | M66: Evergreen–No Penalty | N66: =IF(M66="","",IF(L66="",INDEX($F$92:$F$95,MATCH(M66,$C$92:$C$95,0)),IF(L66<=INDEX($D$92:$D$95,MATCH(M66,$C$92:$C$95,0)),0,IF(L66<=INDEX($E$92:$E$95,MATCH(M66,$C$92:$C$95,0)),INDEX($F$92:$F$95,MATCH(M66,$C$92:$C$95,0)),INDEX($G$92:$G$95,MATCH(M66,$C$92:$C$95,0)))))) -> 0 | O66: =G66+N66 -> 0 | P66: No Review | R66: AVAX has a clearly documented, hard-capped maximum supply of 720M tokens, with 360M minted at genesis and the remaining 360M emitted via staking rewards and incentives. Official and third‑party documentation detail the capped supply, vesting timelines, and that emission parameters are governance‑tunable, but still described and tracked in public tokenomics/vesting resources. This meets a reasonable standard for a transparent, documented issuance schedule.
A67: E1.4 | B67: Do supply adjustments depend on managerial discretion? (Yes / No / Unclear) | C67: No | D67: High | E67: =IF(C67="No",0,IF(C67="Unclear",10,IF(C67="Yes",20,""))) -> 0 | F67: =IF(D67="High",0,IF(D67="Medium",0.05,IF(D67="Low",0.1,IF(D67="Unknown",0.15,"")))) -> 0 | G67: =E67*(1+F67) -> 0 | H67: https://support.avax.network/en/articles/6912428-tokenomics-faq; https://www.cube.exchange/what-is/avalanche; https://www.thetie.io/insights/avalanche-ecosystem/ | I67: 2025-10-01; 2024-08-01; 2022-03-01 | J67: 2025-12-12; 2025-12-12; 2025-12-12 | K67: =IF(I67="","",MAX(IFERROR(DATEVALUE(TRIM(MID(SUBSTITUTE(I67,";",REPT(" ",50)),1,50))),0),IFERROR(DATEVALUE(TRIM(MID(SUBSTITUTE(I67,";",REPT(" ",50)),51,50))),0),IFERROR(DATEVALUE(TRIM(MID(SUBSTITUTE(I67,";",REPT(" ",50)),101,50))),0),IFERROR(DATEVALUE(TRIM(MID(SUBSTITUTE(I67,";",REPT(" ",50)),151,50))),0),IFERROR(DATEVALUE(TRIM(MID(SUBSTITUTE(I67,";",REPT(" ",50)),201,50))),0),IFERROR(DATEVALUE(TRIM(MID(SUBSTITUTE(I67,";",REPT(" ",50)),251,50))),0),IFERROR(DATEVALUE(TRIM(MID(SUBSTITUTE(I67,";",REPT(" ",50)),301,50))),0),IFERROR(DATEVALUE(TRIM(MID(SUBSTITUTE(I67,";",REPT(" ",50)),351,50))),0),IFERROR(DATEVALUE(TRIM(MID(SUBSTITUTE(I67,";",REPT(" ",50)),401,50))),0),IFERROR(DATEVALUE(TRIM(MID(SUBSTITUTE(I67,";",REPT(" ",50)),451,50))),0))) -> 45931 | L67: =IF(K67="","",TODAY()-K67) -> 73 | M67: Evergreen–No Penalty | N67: =IF(M67="","",IF(L67="",INDEX($F$92:$F$95,MATCH(M67,$C$92:$C$95,0)),IF(L67<=INDEX($D$92:$D$95,MATCH(M67,$C$92:$C$95,0)),0,IF(L67<=INDEX($E$92:$E$95,MATCH(M67,$C$92:$C$95,0)),INDEX($F$92:$F$95,MATCH(M67,$C$92:$C$95,0)),INDEX($G$92:$G$95,MATCH(M67,$C$92:$C$95,0)))))) -> 0 | O67: =G67+N67 -> 0 | P67: No Review | R67: AVAX has a hard‑capped maximum supply of 720M tokens. 360M were minted at genesis and the remainder are minted over time as staking rewards under a predefined emissions function. While parameters such as issuance/reward rates are tunable via on‑chain governance by AVAX holders, the cap itself cannot be altered unilaterally by a managerial entity. Thus, supply adjustments do not depend on discretionary decisions of a centralized manager.
A68: E1-N | B68: ≤120-word narrative on supply credibility & transparency. (Narrative only) | C68: AVAX supply is relatively credible and well-documented. The token is hard‑capped at 720M, with 360M minted at genesis and the remainder emitted via staking rewards under a defined formula. Official docs and support materials clearly describe the cap, issuance mechanics, and fee‑burning model, and provide ongoing updates. However, governance can tune emission parameters over time, and some allocations follow vesting schedules, so future circulating supply dynamics depend on those policy choices. Overall transparency is strong for a large L1, but investors must monitor governance changes and unlock schedules. | D68: High | E68: 0 | F68: =IF(D68="High",0,IF(D68="Medium",0.05,IF(D68="Low",0.1,IF(D68="Unknown",0.15,"")))) -> 0 | G68: =E68*(1+F68) -> 0 | H68: https://build.avax.network/docs/primary-network/avax-token; https://support.avax.network/en/articles/6912428-tokenomics-faq; https://www.mexc.fm/en-TR/price/AVAX/tokenomics | I68: 2024-11-01; 2025-10-01; 2025-11-01 | J68: 2025-12-12; 2025-12-12; 2025-12-12 | K68: =IF(I68="","",MAX(IFERROR(DATEVALUE(TRIM(MID(SUBSTITUTE(I68,";",REPT(" ",50)),1,50))),0),IFERROR(DATEVALUE(TRIM(MID(SUBSTITUTE(I68,";",REPT(" ",50)),51,50))),0),IFERROR(DATEVALUE(TRIM(MID(SUBSTITUTE(I68,";",REPT(" ",50)),101,50))),0),IFERROR(DATEVALUE(TRIM(MID(SUBSTITUTE(I68,";",REPT(" ",50)),151,50))),0),IFERROR(DATEVALUE(TRIM(MID(SUBSTITUTE(I68,";",REPT(" ",50)),201,50))),0),IFERROR(DATEVALUE(TRIM(MID(SUBSTITUTE(I68,";",REPT(" ",50)),251,50))),0),IFERROR(DATEVALUE(TRIM(MID(SUBSTITUTE(I68,";",REPT(" ",50)),301,50))),0),IFERROR(DATEVALUE(TRIM(MID(SUBSTITUTE(I68,";",REPT(" ",50)),351,50))),0),IFERROR(DATEVALUE(TRIM(MID(SUBSTITUTE(I68,";",REPT(" ",50)),401,50))),0),IFERROR(DATEVALUE(TRIM(MID(SUBSTITUTE(I68,";",REPT(" ",50)),451,50))),0))) -> 45962 | L68: =IF(K68="","",TODAY()-K68) -> 42 | M68: Evergreen–No Penalty | N68: =IF(M68="","",IF(L68="",INDEX($F$92:$F$95,MATCH(M68,$C$92:$C$95,0)),IF(L68<=INDEX($D$92:$D$95,MATCH(M68,$C$92:$C$95,0)),0,IF(L68<=INDEX($E$92:$E$95,MATCH(M68,$C$92:$C$95,0)),INDEX($F$92:$F$95,MATCH(M68,$C$92:$C$95,0)),INDEX($G$92:$G$95,MATCH(M68,$C$92:$C$95,0)))))) -> 0 | O68: =G68+N68 -> 0 | P68: No Review | Q68: Informational only; no board trigger. | R68: Avalanche publishes detailed, consistent information on AVAX’s hard cap, genesis mint, emissions formula, and fee burning across its docs and tokenomics FAQ, supporting high confidence in supply transparency. Emissions parameters and vesting can change via governance, so future dynamics warrant monitoring.
A70: E2.1 | B70: Team allocation percentage (% of max/FDV supply). Enter numeric or 'Unknown'. | C70: 10 | D70: High | E70: =IF($AA$1="BTC",0,IFERROR(IF(C70="Unknown",20,IF(VALUE(SUBSTITUTE(C70,"%",""))<=15,0,IF(VALUE(SUBSTITUTE(C70,"%",""))<=30,10,20))),"")) -> 0 | F70: =IF(D70="High",0,IF(D70="Medium",0.05,IF(D70="Low",0.1,IF(D70="Unknown",0.15,"")))) -> 0 | G70: =E70*(1+F70) -> 0 | H70: https://www.mexc.fm/en-TR/price/AVAX/tokenomics; https://www.chaincatcher.com/en/article/2070411; https://cryptototem.com/avalanche-avax/ | I70: 2025-11-20; 2024-11-15; 2024-10-01 | J70: 2025-12-12; 2025-12-12; 2025-12-12 | K70: =IF(I70="","",MAX(IFERROR(DATEVALUE(TRIM(MID(SUBSTITUTE(I70,";",REPT(" ",50)),1,50))),0),IFERROR(DATEVALUE(TRIM(MID(SUBSTITUTE(I70,";",REPT(" ",50)),51,50))),0),IFERROR(DATEVALUE(TRIM(MID(SUBSTITUTE(I70,";",REPT(" ",50)),101,50))),0),IFERROR(DATEVALUE(TRIM(MID(SUBSTITUTE(I70,";",REPT(" ",50)),151,50))),0),IFERROR(DATEVALUE(TRIM(MID(SUBSTITUTE(I70,";",REPT(" ",50)),201,50))),0),IFERROR(DATEVALUE(TRIM(MID(SUBSTITUTE(I70,";",REPT(" ",50)),251,50))),0),IFERROR(DATEVALUE(TRIM(MID(SUBSTITUTE(I70,";",REPT(" ",50)),301,50))),0),IFERROR(DATEVALUE(TRIM(MID(SUBSTITUTE(I70,";",REPT(" ",50)),351,50))),0),IFERROR(DATEVALUE(TRIM(MID(SUBSTITUTE(I70,";",REPT(" ",50)),401,50))),0),IFERROR(DATEVALUE(TRIM(MID(SUBSTITUTE(I70,";",REPT(" ",50)),451,50))),0))) -> 45981 | L70: =IF(K70="","",TODAY()-K70) -> 23 | M70: Evergreen–No Penalty | N70: =IF(M70="","",IF(L70="",INDEX($F$92:$F$95,MATCH(M70,$C$92:$C$95,0)),IF(L70<=INDEX($D$92:$D$95,MATCH(M70,$C$92:$C$95,0)),0,IF(L70<=INDEX($E$92:$E$95,MATCH(M70,$C$92:$C$95,0)),INDEX($F$92:$F$95,MATCH(M70,$C$92:$C$95,0)),INDEX($G$92:$G$95,MATCH(M70,$C$92:$C$95,0)))))) -> 0 | O70: =G70+N70 -> 0 | P70: =IF($AA$1="BTC","No Review","No Review") -> No Review | R70: Multiple independent tokenomics sources state that 10% of AVAX’s max supply (720M tokens, i.e., 72M AVAX) is allocated to the project team/founding and non-founding members of Ava Labs, with a multi‑year vesting schedule. This is consistently presented as the team allocation portion of the total/max supply.
A71: E2.2 | B71: Investor/VC allocation percentage (% of max/FDV supply). Enter numeric or 'Unknown'. | C71: 11 | D71: Medium | E71: =IF($AA$1="BTC",0,IFERROR(IF(C71="Unknown",20,IF(VALUE(SUBSTITUTE(C71,"%",""))<=20,0,IF(VALUE(SUBSTITUTE(C71,"%",""))<=40,10,20))),"")) -> 0 | F71: =IF(D71="High",0,IF(D71="Medium",0.05,IF(D71="Low",0.1,IF(D71="Unknown",0.15,"")))) -> 0.05 | G71: =E71*(1+F71) -> 0 | H71: https://medium.com/coinmonks/avax-even-the-largest-avalanche-is-triggered-by-small-things-3ea5a94b7525; https://coinexplorers.com/insights/what-should-we-make-of-avalanche-s-avax-initial-token-distribution-t7jksp | I71: 2021-02-01; 2023-08-01 | J71: 2025-12-12; 2025-12-12 | K71: =IF(I71="","",MAX(IFERROR(DATEVALUE(TRIM(MID(SUBSTITUTE(I71,";",REPT(" ",50)),1,50))),0),IFERROR(DATEVALUE(TRIM(MID(SUBSTITUTE(I71,";",REPT(" ",50)),51,50))),0),IFERROR(DATEVALUE(TRIM(MID(SUBSTITUTE(I71,";",REPT(" ",50)),101,50))),0),IFERROR(DATEVALUE(TRIM(MID(SUBSTITUTE(I71,";",REPT(" ",50)),151,50))),0),IFERROR(DATEVALUE(TRIM(MID(SUBSTITUTE(I71,";",REPT(" ",50)),201,50))),0),IFERROR(DATEVALUE(TRIM(MID(SUBSTITUTE(I71,";",REPT(" ",50)),251,50))),0),IFERROR(DATEVALUE(TRIM(MID(SUBSTITUTE(I71,";",REPT(" ",50)),301,50))),0),IFERROR(DATEVALUE(TRIM(MID(SUBSTITUTE(I71,";",REPT(" ",50)),351,50))),0),IFERROR(DATEVALUE(TRIM(MID(SUBSTITUTE(I71,";",REPT(" ",50)),401,50))),0),IFERROR(DATEVALUE(TRIM(MID(SUBSTITUTE(I71,";",REPT(" ",50)),451,50))),0))) -> 45139 | L71: =IF(K71="","",TODAY()-K71) -> 865 | M71: Evergreen–No Penalty | N71: =IF(M71="","",IF(L71="",INDEX($F$92:$F$95,MATCH(M71,$C$92:$C$95,0)),IF(L71<=INDEX($D$92:$D$95,MATCH(M71,$C$92:$C$95,0)),0,IF(L71<=INDEX($E$92:$E$95,MATCH(M71,$C$92:$C$95,0)),INDEX($F$92:$F$95,MATCH(M71,$C$92:$C$95,0)),INDEX($G$92:$G$95,MATCH(M71,$C$92:$C$95,0)))))) -> 0 | O71: =G71+N71 -> 0 | P71: =IF($AA$1="BTC","No Review","No Review") -> No Review | R71: Avalanche’s published tokenomics allocate 2.5% of max supply to the Seed Sale, 3.5% to the Private Sale, and 5% to Strategic Partners, all of which are investor-style allocations, totaling ~11% of the 720m max supply. Public sale (10%) is treated as broad retail, not VC, so it is excluded from this Investor/VC figure. Exact VC share inside the Strategic Partners bucket is not fully disclosed, so 11% is an informed estimate rather than a precise upper bound.
A72: E2.3 | B72: Treasury/foundation allocation percentage (% of max/FDV supply). Enter numeric or 'Unknown'. | C72: 9.26 | D72: High | E72: =IF($AA$1="BTC",0,IFERROR(IF(C72="Unknown",10,IF(VALUE(SUBSTITUTE(C72,"%",""))<=15,0,IF(VALUE(SUBSTITUTE(C72,"%",""))<=30,10,20))),"")) -> 0 | F72: =IF(D72="High",0,IF(D72="Medium",0.05,IF(D72="Low",0.1,IF(D72="Unknown",0.15,"")))) -> 0 | G72: =E72*(1+F72) -> 0 | H72: https://www.mexc.fm/price/AVAX/tokenomics; https://www.mexc.fm/en-TR/price/AVAX/tokenomics | I72: 2024-09-01; 2024-09-01 | J72: 2025-12-12; 2025-12-12 | K72: =IF(I72="","",MAX(IFERROR(DATEVALUE(TRIM(MID(SUBSTITUTE(I72,";",REPT(" ",50)),1,50))),0),IFERROR(DATEVALUE(TRIM(MID(SUBSTITUTE(I72,";",REPT(" ",50)),51,50))),0),IFERROR(DATEVALUE(TRIM(MID(SUBSTITUTE(I72,";",REPT(" ",50)),101,50))),0),IFERROR(DATEVALUE(TRIM(MID(SUBSTITUTE(I72,";",REPT(" ",50)),151,50))),0),IFERROR(DATEVALUE(TRIM(MID(SUBSTITUTE(I72,";",REPT(" ",50)),201,50))),0),IFERROR(DATEVALUE(TRIM(MID(SUBSTITUTE(I72,";",REPT(" ",50)),251,50))),0),IFERROR(DATEVALUE(TRIM(MID(SUBSTITUTE(I72,";",REPT(" ",50)),301,50))),0),IFERROR(DATEVALUE(TRIM(MID(SUBSTITUTE(I72,";",REPT(" ",50)),351,50))),0),IFERROR(DATEVALUE(TRIM(MID(SUBSTITUTE(I72,";",REPT(" ",50)),401,50))),0),IFERROR(DATEVALUE(TRIM(MID(SUBSTITUTE(I72,";",REPT(" ",50)),451,50))),0))) -> 45536 | L72: =IF(K72="","",TODAY()-K72) -> 468 | M72: Evergreen–No Penalty | N72: =IF(M72="","",IF(L72="",INDEX($F$92:$F$95,MATCH(M72,$C$92:$C$95,0)),IF(L72<=INDEX($D$92:$D$95,MATCH(M72,$C$92:$C$95,0)),0,IF(L72<=INDEX($E$92:$E$95,MATCH(M72,$C$92:$C$95,0)),INDEX($F$92:$F$95,MATCH(M72,$C$92:$C$95,0)),INDEX($G$92:$G$95,MATCH(M72,$C$92:$C$95,0)))))) -> 0 | O72: =G72+N72 -> 0 | P72: =IF($AA$1="BTC","No Review","No Review") -> No Review | R72: Public tokenomics for AVAX show that the Avalanche Foundation was allocated approximately 9.26% of the initial total token supply (~66.67M AVAX out of 720M max supply), with a 10‑year vesting schedule. Because the initial total supply equals the capped maximum supply (720M), this corresponds to about 9.26% of max/FDV supply allocated to the foundation/treasury.
A73: E2.4 | B73: Are unlock schedules publicly disclosed? (Yes / Partial / No) | C73: Yes | D73: High | E73: {=IF($AA$1="BTC",0,IF(C73="Yes",0,IF(C73="Partial",10,IF(C73="No",20,""))))} -> 0 | F73: =IF(D73="High",0,IF(D73="Medium",0.05,IF(D73="Low",0.1,IF(D73="Unknown",0.15,"")))) -> 0 | G73: =E73*(1+F73) -> 0 | H73: https://www.21shares.com/en-eu/research/avalanche-research-primer; https://www.galaxy.com/insights/research/protocol-overview-avalanche-2024/; https://www.mexc.com/price/AVAX/tokenomics | I73: 2021-12-01; 2024-09-09; 2024-11-15 | J73: 2025-12-12; 2025-12-12; 2025-12-12 | K73: =IF(I73="","",MAX(IFERROR(DATEVALUE(TRIM(MID(SUBSTITUTE(I73,";",REPT(" ",50)),1,50))),0),IFERROR(DATEVALUE(TRIM(MID(SUBSTITUTE(I73,";",REPT(" ",50)),51,50))),0),IFERROR(DATEVALUE(TRIM(MID(SUBSTITUTE(I73,";",REPT(" ",50)),101,50))),0),IFERROR(DATEVALUE(TRIM(MID(SUBSTITUTE(I73,";",REPT(" ",50)),151,50))),0),IFERROR(DATEVALUE(TRIM(MID(SUBSTITUTE(I73,";",REPT(" ",50)),201,50))),0),IFERROR(DATEVALUE(TRIM(MID(SUBSTITUTE(I73,";",REPT(" ",50)),251,50))),0),IFERROR(DATEVALUE(TRIM(MID(SUBSTITUTE(I73,";",REPT(" ",50)),301,50))),0),IFERROR(DATEVALUE(TRIM(MID(SUBSTITUTE(I73,";",REPT(" ",50)),351,50))),0),IFERROR(DATEVALUE(TRIM(MID(SUBSTITUTE(I73,";",REPT(" ",50)),401,50))),0),IFERROR(DATEVALUE(TRIM(MID(SUBSTITUTE(I73,";",REPT(" ",50)),451,50))),0))) -> 45611 | L73: =IF(K73="","",TODAY()-K73) -> 393 | M73: Evergreen–No Penalty | N73: =IF(M73="","",IF(L73="",INDEX($F$92:$F$95,MATCH(M73,$C$92:$C$95,0)),IF(L73<=INDEX($D$92:$D$95,MATCH(M73,$C$92:$C$95,0)),0,IF(L73<=INDEX($E$92:$E$95,MATCH(M73,$C$92:$C$95,0)),INDEX($F$92:$F$95,MATCH(M73,$C$92:$C$95,0)),INDEX($G$92:$G$95,MATCH(M73,$C$92:$C$95,0)))))) -> 0 | O73: =G73+N73 -> 0 | P73: =IF($AA$1="BTC","No Review","No Review") -> No Review | R73: Comprehensive AVAX vesting and unlock schedules have been publicly disclosed. The 21Shares research primer details vesting terms for all major allocations (team, sales, foundation, airdrop, community, etc.) and describes when they start unlocking. Independent analyses from Galaxy Digital and major exchanges further publish forward-looking unlock calendars with specific dates and amounts, indicating that unlock schedules are clearly and publicly available.
A74: E2.5 | B74: What % of total supply unlocks in the next 6 months? Enter numeric or 'Unknown'. | C74: 0.46 | D74: Medium | E74: =IF($AA$1="BTC",0,IFERROR(IF(C74="Unknown",10,IF(VALUE(SUBSTITUTE(C74,"%",""))<=5,0,IF(VALUE(SUBSTITUTE(C74,"%",""))<=15,10,20))),"")) -> 0 | F74: =IF(D74="High",0,IF(D74="Medium",0.05,IF(D74="Low",0.1,IF(D74="Unknown",0.15,"")))) -> 0.05 | G74: =E74*(1+F74) -> 0 | H74: https://www.mexc.com/price/AVAX/tokenomics; https://www.coingecko.com/en/coins/avalanche | I74: 2025-12-11; 2025-11-30 | J74: 2025-12-12; 2025-12-12 | K74: =IF(I74="","",MAX(IFERROR(DATEVALUE(TRIM(MID(SUBSTITUTE(I74,";",REPT(" ",50)),1,50))),0),IFERROR(DATEVALUE(TRIM(MID(SUBSTITUTE(I74,";",REPT(" ",50)),51,50))),0),IFERROR(DATEVALUE(TRIM(MID(SUBSTITUTE(I74,";",REPT(" ",50)),101,50))),0),IFERROR(DATEVALUE(TRIM(MID(SUBSTITUTE(I74,";",REPT(" ",50)),151,50))),0),IFERROR(DATEVALUE(TRIM(MID(SUBSTITUTE(I74,";",REPT(" ",50)),201,50))),0),IFERROR(DATEVALUE(TRIM(MID(SUBSTITUTE(I74,";",REPT(" ",50)),251,50))),0),IFERROR(DATEVALUE(TRIM(MID(SUBSTITUTE(I74,";",REPT(" ",50)),301,50))),0),IFERROR(DATEVALUE(TRIM(MID(SUBSTITUTE(I74,";",REPT(" ",50)),351,50))),0),IFERROR(DATEVALUE(TRIM(MID(SUBSTITUTE(I74,";",REPT(" ",50)),401,50))),0),IFERROR(DATEVALUE(TRIM(MID(SUBSTITUTE(I74,";",REPT(" ",50)),451,50))),0))) -> 46002 | L74: =IF(K74="","",TODAY()-K74) -> 2 | M74: Critical–Fast | N74: =IF(M74="","",IF(L74="",INDEX($F$92:$F$95,MATCH(M74,$C$92:$C$95,0)),IF(L74<=INDEX($D$92:$D$95,MATCH(M74,$C$92:$C$95,0)),0,IF(L74<=INDEX($E$92:$E$95,MATCH(M74,$C$92:$C$95,0)),INDEX($F$92:$F$95,MATCH(M74,$C$92:$C$95,0)),INDEX($G$92:$G$95,MATCH(M74,$C$92:$C$95,0)))))) -> 0 | O74: =G74+N74 -> 0 | P74: =IF($AA$1="BTC","No Review",IF(AND(IFERROR(VALUE(SUBSTITUTE(#REF!,"%","")),0)+IFERROR(VALUE(SUBSTITUTE(#REF!,"%","")),0)>45,IFERROR(VALUE(SUBSTITUTE($C$19,"%","")),0)>15),"Review","No Review")) -> No Review | Q74: Escalate if insider share (Team%+VC%) > 45% AND unlocks in next 6m > 15%. Auto 'No Review' if Token_Symbol = BTC. | R74: Public calendars show AVAX unlocks of ~1,666,800 tokens each on 2026-02-11 and 2026-05-12, both within the next 6 months. Each event is ~0.39% of circulating supply and equals 1,666,800 AVAX. With a max supply of 720,000,000 AVAX, each unlock is ~0.23% of total supply, so two unlocks sum to ~0.46% of total supply. Data may change as schedules are updated, so confidence is medium.
A75: E2-N | B75: ≤120-word narrative on fairness & foreseeable harm (insider vs public). (Narrative only) | C75: AVAX’s token distribution allocates meaningful stakes to the team, foundation, strategic partners, and private/seed investors, with multi‑year vesting intended to reduce immediate insider dumping and align incentives with network growth. Public sale tranches and airdrops sought to broaden holder base, but insiders and affiliated entities still control a large aggregate share, and recent discounted institutional deals further underscore an access gap versus ordinary retail. These structural asymmetries create foreseeable harms around information and liquidity advantages, potential sell‑pressure overhang, and governance influence that may disadvantage public holders, especially during market stress or major unlock and treasury operations. | D75: High | E75: =IF($AA$1="BTC",0,0) -> 0 | F75: =IF(D75="High",0,IF(D75="Medium",0.05,IF(D75="Low",0.1,IF(D75="Unknown",0.15,"")))) -> 0 | G75: =E75*(1+F75) -> 0 | H75: https://coincodecap.com/avalanche-avax; https://www.mexc.com/en-TH/price/AVAX/tokenomics; https://www.coindesk.com/business/2025/10/02/avalanche-treasury-co-going-public-in-usd675m-spac-deal-backed-by-avax-ecosystem | I75: 2024-06-01; 2024-11-15; 2025-10-02 | J75: 2025-12-12; 2025-12-12; 2025-12-12 | K75: =IF(I75="","",MAX(IFERROR(DATEVALUE(TRIM(MID(SUBSTITUTE(I75,";",REPT(" ",50)),1,50))),0),IFERROR(DATEVALUE(TRIM(MID(SUBSTITUTE(I75,";",REPT(" ",50)),51,50))),0),IFERROR(DATEVALUE(TRIM(MID(SUBSTITUTE(I75,";",REPT(" ",50)),101,50))),0),IFERROR(DATEVALUE(TRIM(MID(SUBSTITUTE(I75,";",REPT(" ",50)),151,50))),0),IFERROR(DATEVALUE(TRIM(MID(SUBSTITUTE(I75,";",REPT(" ",50)),201,50))),0),IFERROR(DATEVALUE(TRIM(MID(SUBSTITUTE(I75,";",REPT(" ",50)),251,50))),0),IFERROR(DATEVALUE(TRIM(MID(SUBSTITUTE(I75,";",REPT(" ",50)),301,50))),0),IFERROR(DATEVALUE(TRIM(MID(SUBSTITUTE(I75,";",REPT(" ",50)),351,50))),0),IFERROR(DATEVALUE(TRIM(MID(SUBSTITUTE(I75,";",REPT(" ",50)),401,50))),0),IFERROR(DATEVALUE(TRIM(MID(SUBSTITUTE(I75,";",REPT(" ",50)),451,50))),0))) -> 45932 | L75: =IF(K75="","",TODAY()-K75) -> 72 | M75: Operational–Medium | N75: =IF(M75="","",IF(L75="",INDEX($F$92:$F$95,MATCH(M75,$C$92:$C$95,0)),IF(L75<=INDEX($D$92:$D$95,MATCH(M75,$C$92:$C$95,0)),0,IF(L75<=INDEX($E$92:$E$95,MATCH(M75,$C$92:$C$95,0)),INDEX($F$92:$F$95,MATCH(M75,$C$92:$C$95,0)),INDEX($G$92:$G$95,MATCH(M75,$C$92:$C$95,0)))))) -> 0 | O75: =G75+N75 -> 0 | P75: =IF($AA$1="BTC","No Review","No Review") -> No Review | Q75: Informational only; no board trigger. | R75: Used primary tokenomics sources showing large, vested allocations to team/foundation/partners and public vs private sale structure, plus recent evidence of discounted institutional AVAX deals. From this, it is reasonable to highlight foreseeable harms: insider overhang, preferential access, and governance influence versus public holders.
A77: E3.1 | B77: Annual inflation/emission rate (% per year). Enter numeric or 'Unknown'. (Category-aware thresholds apply.) | C77: 5.2 | D77: Medium | E77: =IFERROR( IF(C77="Unknown",10, IF(OR($C$64="L1",$C$64="L2"), IF(VALUE(SUBSTITUTE(C77,"%",""))<=4,0, IF(VALUE(SUBSTITUTE(C77,"%",""))<=8,10,20)), IF(VALUE(SUBSTITUTE(C77,"%",""))<=3,0, IF(VALUE(SUBSTITUTE(C77,"%",""))<=6,10,20)) ) ), "") -> 10 | F77: =IF(D77="High",0,IF(D77="Medium",0.05,IF(D77="Low",0.1,IF(D77="Unknown",0.15,"")))) -> 0.05 | G77: =E77*(1+F77) -> 10.5 | H77: https://messari.io/report/state-of-avalanche-q2-2024; https://messari.io/report/state-of-avalanche-q1-2024 | I77: 2024-07-01; 2024-04-01 | J77: 2025-12-12; 2025-12-12 | K77: =IF(I77="","",MAX(IFERROR(DATEVALUE(TRIM(MID(SUBSTITUTE(I77,";",REPT(" ",50)),1,50))),0),IFERROR(DATEVALUE(TRIM(MID(SUBSTITUTE(I77,";",REPT(" ",50)),51,50))),0),IFERROR(DATEVALUE(TRIM(MID(SUBSTITUTE(I77,";",REPT(" ",50)),101,50))),0),IFERROR(DATEVALUE(TRIM(MID(SUBSTITUTE(I77,";",REPT(" ",50)),151,50))),0),IFERROR(DATEVALUE(TRIM(MID(SUBSTITUTE(I77,";",REPT(" ",50)),201,50))),0),IFERROR(DATEVALUE(TRIM(MID(SUBSTITUTE(I77,";",REPT(" ",50)),251,50))),0),IFERROR(DATEVALUE(TRIM(MID(SUBSTITUTE(I77,";",REPT(" ",50)),301,50))),0),IFERROR(DATEVALUE(TRIM(MID(SUBSTITUTE(I77,";",REPT(" ",50)),351,50))),0),IFERROR(DATEVALUE(TRIM(MID(SUBSTITUTE(I77,";",REPT(" ",50)),401,50))),0),IFERROR(DATEVALUE(TRIM(MID(SUBSTITUTE(I77,";",REPT(" ",50)),451,50))),0))) -> 45474 | L77: =IF(K77="","",TODAY()-K77) -> 530 | M77: Operational–Medium | N77: =IF(M77="","",IF(L77="",INDEX($F$92:$F$95,MATCH(M77,$C$92:$C$95,0)),IF(L77<=INDEX($D$92:$D$95,MATCH(M77,$C$92:$C$95,0)),0,IF(L77<=INDEX($E$92:$E$95,MATCH(M77,$C$92:$C$95,0)),INDEX($F$92:$F$95,MATCH(M77,$C$92:$C$95,0)),INDEX($G$92:$G$95,MATCH(M77,$C$92:$C$95,0)))))) -> 6 | O77: =G77+N77 -> 16.5 | P77: =IF($AA$1="BTC","No Review",IF(OR(AND(OR(C64="L1",C64="L2"), IFERROR(VALUE(SUBSTITUTE($C$22,"%","")),0)>8),AND(NOT(OR(C64="L1",C64="L2")), IFERROR(VALUE(SUBSTITUTE($C$22,"%","")),0)>6)),"Review","No Review")) -> No Review | Q77: Escalate if annual emission >8% (L1/L2) or >6% (others). Auto 'No Review' if Token_Symbol = BTC. | R77: Messari’s Q2 2024 “State of Avalanche” report states that AVAX’s annualized inflation rate for the quarter was 5.2%. This reflects protocol-level issuance from staking rewards under current conditions; actual realized net supply growth may differ over time due to fee burns and changing staking participation. Using 5.2% provides a data-backed recent estimate but is not a guaranteed long-term rate.
A78: E3.2 | B78: Unlock pacing style (Gradual / Mixed / Cliff / Unknown). | C78: Gradual | D78: High | E78: {=IF($AA$1="BTC",0,IF(C78="Gradual",0,IF(C78="Mixed",10,IF(C78="Cliff",20,IF(C78="Unknown",10,"")))))} -> 0 | F78: =IF(D78="High",0,IF(D78="Medium",0.05,IF(D78="Low",0.1,IF(D78="Unknown",0.15,"")))) -> 0 | G78: =E78*(1+F78) -> 0 | H78: https://support.avax.network/en/articles/4138859-avax-token-distribution; https://messari.io/asset/avalanche | I78: 2020-07-01; 2021-12-01 | J78: 2025-12-12; 2025-12-12 | K78: =IF(I78="","",MAX(IFERROR(DATEVALUE(TRIM(MID(SUBSTITUTE(I78,";",REPT(" ",50)),1,50))),0),IFERROR(DATEVALUE(TRIM(MID(SUBSTITUTE(I78,";",REPT(" ",50)),51,50))),0),IFERROR(DATEVALUE(TRIM(MID(SUBSTITUTE(I78,";",REPT(" ",50)),101,50))),0),IFERROR(DATEVALUE(TRIM(MID(SUBSTITUTE(I78,";",REPT(" ",50)),151,50))),0),IFERROR(DATEVALUE(TRIM(MID(SUBSTITUTE(I78,";",REPT(" ",50)),201,50))),0),IFERROR(DATEVALUE(TRIM(MID(SUBSTITUTE(I78,";",REPT(" ",50)),251,50))),0),IFERROR(DATEVALUE(TRIM(MID(SUBSTITUTE(I78,";",REPT(" ",50)),301,50))),0),IFERROR(DATEVALUE(TRIM(MID(SUBSTITUTE(I78,";",REPT(" ",50)),351,50))),0),IFERROR(DATEVALUE(TRIM(MID(SUBSTITUTE(I78,";",REPT(" ",50)),401,50))),0),IFERROR(DATEVALUE(TRIM(MID(SUBSTITUTE(I78,";",REPT(" ",50)),451,50))),0))) -> 44531 | L78: =IF(K78="","",TODAY()-K78) -> 1473 | M78: Evergreen–No Penalty | N78: =IF(M78="","",IF(L78="",INDEX($F$92:$F$95,MATCH(M78,$C$92:$C$95,0)),IF(L78<=INDEX($D$92:$D$95,MATCH(M78,$C$92:$C$95,0)),0,IF(L78<=INDEX($E$92:$E$95,MATCH(M78,$C$92:$C$95,0)),INDEX($F$92:$F$95,MATCH(M78,$C$92:$C$95,0)),INDEX($G$92:$G$95,MATCH(M78,$C$92:$C$95,0)))))) -> 0 | O78: =G78+N78 -> 0 | P78: =IF($AA$1="BTC","No Review","No Review") -> No Review | R78: AVAX’s initial and ongoing token unlocks follow a long-term vesting schedule where various allocations (team, foundation, strategic partners, airdrops, etc.) release over several years in tranches, not in a single large cliff. Charts and schedules from Avalanche documentation and major data providers show a multi‑year, stepwise emission curve characteristic of a gradual unlock pattern rather than a dominant cliff or highly irregular mix.
A79: E3.3 | B79: Are unlocks tied to real adoption milestones? (Yes / Unclear / No) | C79: No | D79: High | E79: {=IF($AA$1="BTC",0,IF(C79="Yes",0,IF(C79="Unclear",10,IF(C79="No",20,""))))} -> 20 | F79: =IF(D79="High",0,IF(D79="Medium",0.05,IF(D79="Low",0.1,IF(D79="Unknown",0.15,"")))) -> 0 | G79: =E79*(1+F79) -> 20 | H79: https://www.mexc.fm/price/AVAX/tokenomics; https://99bitcoins.com/cryptocurrency/avalanche-review/; https://coindar.org/en/coin/avalanche/calendar | I79: 2024-11-20; 2024-11-15 | J79: 2025-12-12; 2025-12-12; 2025-12-12 | K79: =IF(I79="","",MAX(IFERROR(DATEVALUE(TRIM(MID(SUBSTITUTE(I79,";",REPT(" ",50)),1,50))),0),IFERROR(DATEVALUE(TRIM(MID(SUBSTITUTE(I79,";",REPT(" ",50)),51,50))),0),IFERROR(DATEVALUE(TRIM(MID(SUBSTITUTE(I79,";",REPT(" ",50)),101,50))),0),IFERROR(DATEVALUE(TRIM(MID(SUBSTITUTE(I79,";",REPT(" ",50)),151,50))),0),IFERROR(DATEVALUE(TRIM(MID(SUBSTITUTE(I79,";",REPT(" ",50)),201,50))),0),IFERROR(DATEVALUE(TRIM(MID(SUBSTITUTE(I79,";",REPT(" ",50)),251,50))),0),IFERROR(DATEVALUE(TRIM(MID(SUBSTITUTE(I79,";",REPT(" ",50)),301,50))),0),IFERROR(DATEVALUE(TRIM(MID(SUBSTITUTE(I79,";",REPT(" ",50)),351,50))),0),IFERROR(DATEVALUE(TRIM(MID(SUBSTITUTE(I79,";",REPT(" ",50)),401,50))),0),IFERROR(DATEVALUE(TRIM(MID(SUBSTITUTE(I79,";",REPT(" ",50)),451,50))),0))) -> 45616 | L79: =IF(K79="","",TODAY()-K79) -> 388 | M79: Evergreen–No Penalty | N79: =IF(M79="","",IF(L79="",INDEX($F$92:$F$95,MATCH(M79,$C$92:$C$95,0)),IF(L79<=INDEX($D$92:$D$95,MATCH(M79,$C$92:$C$95,0)),0,IF(L79<=INDEX($E$92:$E$95,MATCH(M79,$C$92:$C$95,0)),INDEX($F$92:$F$95,MATCH(M79,$C$92:$C$95,0)),INDEX($G$92:$G$95,MATCH(M79,$C$92:$C$95,0)))))) -> 0 | O79: =G79+N79 -> 20 | P79: =IF($AA$1="BTC","No Review","No Review") -> No Review | R79: Available sources describe AVAX unlocks as pre-set, time-based vesting for team, foundation, partners, and other allocations, with regular quarterly or scheduled dates and fixed amounts. There is no indication that release of these tranches is contingent on usage, revenue, or other concrete adoption milestones; they proceed according to a predetermined calendar instead.
